Workbook

Sheet About
A1: BFPIaE - BAU Fuel Production, Imports, Exports (state, 2024-2050) | B1: Missouri | C1: 46265
A2: State code (derived): | B2: =IFERROR(INDEX(Geography!B:B, MATCH($B$1, Geography!C:C, 0)), "") -> MO
A3: State FIPS: | B3: =IFERROR(INDEX(Geography!A:A, MATCH($B$2, Geography!B:B, 0)), "") -> 29
A4: Census division #: | B4: =IFERROR(INDEX(Geography!D:D, MATCH($B$2, Geography!B:B, 0)), "") -> 4
A5: AEO o&g supply region: | B5: =Region_crosswalk!K3 -> Midcontinent
A6: AEO coal region: | B6: =Region_crosswalk!K4 -> Interior
A7: Workbook: | B7: EPS BFPIaE - state fuel production / imports / exports
A8: Base year (anchor): | B8: 2024
A9: Forecast horizon: | B9: 2050
A10: EPS run seeding demand: | B10: bau-0831
A11: Production growth source: | B11: AEO 2026 (electrnp)
A12: Methodology: | B12: docs/methodology/BFPIaE-growth.md
A13: Design decisions: | B13: outputs/BFPIaE/plan.md
A14: Generator: | B14: outputs/BFPIaE/_build_bfpiae_workbook.py
A15: Built: | B15: 2026-08-31 11:24
A18: PHASE 2: all 21 fuel rows populated where data is available.
A20: FORECAST (2025-2050), v2 design - convergent by construction:
A21: production: 2024 EIA anchor grown on the AEO2026 (electrnp) production index -
A22: regional for crude/NG (supply-region tables 58/59 via Region_crosswalk),
A23: regional for coal (table 65), national for refined products / biofuels / LPG /
A24: hydrogen (tables 11, 19); flat for nuclear, biomass, MSW (no projection
A25: source). EPS treats production as passthrough (FPIEBP priority 3), so its
A26: forecast must come from outside the model.
A27: exports: 2024 anchor scaled by the same AEO production index as production
A28: (exports rise and fall with the state's production), floored by the supply
A29: surplus MAX(..., production - demand) - the same lift the model's
A30: second-priority balancing would apply.
... A82: Per organizational guidance: framed as input for staff review.

Sheet Methodology
A1: BFPIaE - Methodology Summary (v2, built from EPS run bau-0831)
A2: Working draft for staff review. Verify numerical claims against primary sources before external use.
A3: Full methodology: docs/methodology/BFPIaE-growth.md | Decisions: outputs/BFPIaE/plan.md
A5: 1. Scope
A6: 48 contiguous states, 2024-2050, 21 EPS fuels x 3 modes (production / imports / exports), in BTU. Output: the three BFPIaE-* tabs that EPS reads as InputData/fuels/BFPIaE/BFPIaE-{production,imports,exports}.csv. Switch state via About!B1.
A8: 2. The model fact that shapes the design
A9: FPIEBP.csv sets balancing priorities production=3, imports=1, exports=2. EPS therefore passes production through untouched (verified: run output = deployed input for 1008/1008 series) and OVERWRITES imports with MAX(0, C - P + E), where C = BAU Total Energy Use. Two consequences: (a) production must be forecast outside EPS - feeding the model its own production back is circular; (b) input and output agree only if the input already satisfies P + I - E = C.
A11: 3. Construction, per mode
A12: production(2024) = EIA observed anchor (per-fuel Calcs tabs)
A13: production(Y) = production(Y-1) x AEO2026 growth factor [AEO_growth_calcs Sec 2]
A14: demand C(Y) = P + I - E from the EPS run output [Demand_calcs]
A15: exports(Y) = MAX(0, anchor x AEO index, production(Y) - C(Y)) [Sec 3 index plus supply-surplus floor, so exports track the state own production trajectory]
... A44: Treat all outputs as inputs for staff review, not Energy Innovation institutional positions. Open for refinement.

Sheet Sources
A1: BFPIaE - Source Data Provenance
A3: Every embedded raw tab below corresponds to a downloadable EIA / Census file.
A4: All values in Coal_calcs, NG_calcs, etc. trace back to these tabs via SUMIFS / INDEX-MATCH.
A5: Local repo paths under sources/raw/bfpiae/ unless noted.
A6: EIA-API-derived CSVs are regenerated by outputs/BFPIaE/_stage_sources.py (--check re-pulls and diffs against the committed copies).
A7: Tab | B7: Rows | C7: Source file | D7: URL | E7: Vintage | F7: Notes
A8: Geography | B8: 48 | C8: config/geography/state_to_census_division.csv | D8: - | E8: - | F8: 48 contiguous states
A9: Keys | B9: 118 | C9: derived | D9: - | E9: - | F9: BTU conversion factors + state lookup constants
A10: Coal_production_raw | B10: 768 | C10: sources/raw/eia_coal/coalpublic2024.xlsx | D10: https://www.eia.gov/coal/data/browser/ | E10: 2024 | F10: EIA Hist_Coal_Prod 2024, per-mine. Helpers Q,R added for state cleanup + rank.
A11: EIA923_Page1_coal_raw | B11: 595 | C11: EIA923_Schedules_2_3_4_5_M_12_2024_Final.xlsx Page 1 | D11: https://www.eia.gov/electricity/data/eia923/ | E11: 2024 Final | F11: Filtered to coal fuel codes (BIT/SUB/ANT/RC/WC/SC/LIG). Helpers CT,CU added.
A12: Coal_distribution_raw | B12: 1207 | C12: coal_distribution_2024.xlsx (o_24state) | D12: https://www.eia.gov/coal/distribution/annual/ | E12: 2024 | F12: EIA Annual Coal Distribution Report, by quarter x origin x destination.
A13: NG_production_data1_raw | B13: 99 | C13: NG_dry_production_state.xls Data 1 | D13: https://www.eia.gov/dnav/ng/ng_prod_sum_a_EPG0_FPD_mmcf_a.htm | E13: 2024 | F13: EIA Natural Gas Dry Production by state, annual MMcf.
A14: NG_production_data2_raw | B14: 46 | C14: NG_dry_production_state.xls Data 2 | D14: (same as Data 1) | E14: 2024 | F14: Additional states (overflow tab in EIA file).
A15: NG_movements_state_raw | B15: ~1200 | C15: sources/raw/bfpiae/NG_movements_by_state_2019_2024.csv | D15: EIA API v2 route natural-gas/move/ist | E15: 2019-2024 | F15: By-state totals only (duoarea Sxx-Z0S interstate / Sxx-Z00 international); processes MIR/MID/IMI/EEI, MMcf. Replaces the US-national dnav file used through v1, which had no state columns.
A16: Crude_production_raw | B16: 129 | C16: sources/raw/eia_og/PET_CRD_CRPDN_ADC_MBBL_A.xls Data 1 | D16: https://www.eia.gov/dnav/pet/PET_CRD_CRPDN_ADC_MBBLPD_A.htm | E16: 2024 | F16: EIA Field Production of Crude Oil by state, annual thousand barrels. The "Federal Offshore--Gulf of America" column (own series, in no state) anchors the offshore component allocated via GOM_offshore_shares.
A17: GOM_offshore_shares | B17: 4 | C17: BOEM GOMR Active Lease Map (lease counts entered on-tab) | D17: https://www.data.boem.gov/Main/Mapping.aspx | E17: 2025 lease counts | F17: Federal offshore GOM crude allocated to TX/LA/MS/AL by BOEM active lease count (TX 427, MS 2, AL 11, LA remainder of 2206). Same basis as POLICY_State Mapping in OilGasLeasing_Calculations_States_406.xlsx (Jan 2025 Frozen Policy Scenario - States), keeping BAU offshore production consistent with the IiFPfOaGL leasing policy adjustment. Applied to the crude production AND export anchors (Crude_calcs B5/B7). Verify counts against the BOEM source before external use.
A18: Refinery_capacity_raw | B18: 3380 | C18: sources/raw/eia_refinery/refcap25.xlsx | D18: https://www.eia.gov/petroleum/refinerycapacity/ | E18: Jan 1, 2025 | F18: EIA Refinery Capacity by refinery x product x capacity-type. State allocation for petroleum products.
A19: PET_supply_data1_raw | B19: 94 | C19: PET_US_supply_disposition.xls Data 1 | D19: https://www.eia.gov/dnav/pet/pet_sum_snd_d_nus_mbbl_a.htm | E19: 2024 | F19: EIA US Total Petroleum Supply & Disposition, annual thousand barrels.
A20: PET_supply_data5_raw | B20: 94 | C20: PET_US_supply_disposition.xls Data 5 | D20: (same as Data 1) | E20: 2024 | F20: EIA US Finished Petroleum Products supply (gasoline/diesel/jet/heavy/LPG/etc).
A21: Biomass_facilities_raw | B21: 95 | C21: biomass_table1.csv | D21: https://www.eia.gov/biofuels/biomass/ | E21: 2024 (latest) | F21: EIA Monthly Densified Biomass Fuel Report Table 1, facility list by state x annual capacity.
A22: Uranium_production_raw | B22: 29 | C22: uranium_table3.xlsx | D22: https://www.eia.gov/uranium/production/annual/ | E22: 2024 (Jul 2025 release) | F22: EIA Domestic Uranium Production Report Table 3, US national totals (assumed 100% WY).
A23: SEDS_nuclear_raw | B23: 52 | C23: sources/raw/bfpiae/seds_nuclear_nuetb_2024.csv | D23: https://www.eia.gov/state/seds/ (Complete_SEDS_update.csv, MSN NUETB) | E23: 2024P | F23: State nuclear energy consumption (billion BTU). Nuclear imports/exports anchor as the gap vs WY-only production.
A24: H2_capacity_raw | B24: 40 | C24: sources/raw/bfpiae/refinery_h2_capacity_by_state.csv | D24: EIA API series PET.8_NA_8PH_Sxx_6.A | E24: Jan 1, 2025 | F24: Refinery hydrogen production capacity by state (MMCF/D); capacity assumed = production (legacy-workbook assumption). States w/o refineries absent -> 0.
A25: Census_exports_raw | B25: 1458 | C25: sources/raw/census_trade/legacy_census_state_exports_top25_hs6_2017_2020.csv | D25: https://www.census.gov/foreign-trade/statistics/state/data/index.html | E25: 2020 ($M) | F25: Top-25 HS-6 per state by dollar value, extracted verbatim from the legacy eps-texas BFPIaE workbook. Allocates US petroleum exports to states. CAVEAT: top-25 truncation - codes outside a state's top 25 read as zero share. Refresh path: Census intltrade API (needs API key).
A26: Census_imports_raw | B26: 1458 | C26: (as exports) | D26: (as exports) | E26: 2020 ($M) | F26: Kept for QC comparison only - 2025+ imports are the demand residual.
A27: SEDS_biofuel_raw | B27: 102 | C27: sources/raw/bfpiae/seds_biofuel_production_2023.csv | D27: EIA SEDS MSN EMFDB (fuel ethanol) + BDFDB (biodiesel), state production | E27: 2023 | F27: Share basis for splitting US ethanol / biodiesel totals to states. Feedstock-energy basis (billion Btu) - used as a share only, never as a level.
... A50: BFPIaE-imports | B50: 21 | C50: derived in-workbook | D50: - | E50: - | F50: EPS input tab. MAX(0, demand - production + exports) - the model's own first-priority balancing residual.
A52: Known source gaps / refresh paths:
A53: - Census state-trade shares are the 2020 top-25-HS-per-state extract carried over from the legacy workbook: a petroleum code outside a state top-25 list reads as a zero share. Refresh via the Census intltrade API (key-required; none on this machine).
A54: - LPG exports: no state or US series located (EIA propane export series returned nulls), so the anchor is 0 and exports arise only from the supply-surplus floor.
A55: - No public source projects fuel production by state; AEO supply regions are the finest available geography, so states inside a region share one growth shape.
A56: - No regional (PADD) refined-product production projection exists in the AEO tables on hand, so all refined products use one national index (AEO table 11).
A57: - Hydrogen production is proxied by refinery H2 capacity (capacity = production), the legacy workbook assumption; no state H2 production series exists.
A58: - BTU conversion factors on Keys are widely-cited EIA averages; AEO 2026 Suptab 73 would replace them with model-consistent values.
A59: - Region_crosswalk blend weights for split states (TX/NM o&g, KY coal) are approximate; EIA-914 basin splits and the Annual Coal Report east/west KY tonnage would pin them precisely.

Sheet Geography
A1: state_fips | B1: state_abbr | C1: state_name | D1: division_num | E1: division_name
A2: 01 | B2: AL | C2: Alabama | D2: 6 | E2: East South Central
A3: 04 | B3: AZ | C3: Arizona | D3: 9 | E3: Mountain South
A4: 05 | B4: AR | C4: Arkansas | D4: 7 | E4: West South Central
A5: 06 | B5: CA | C5: California | D5: 10 | E5: Pacific
A6: 08 | B6: CO | C6: Colorado | D6: 8 | E6: Mountain North
A7: 09 | B7: CT | C7: Connecticut | D7: 1 | E7: New England
A8: 10 | B8: DE | C8: Delaware | D8: 5 | E8: South Atlantic
A9: 12 | B9: FL | C9: Florida | D9: 5 | E9: South Atlantic
A10: 13 | B10: GA | C10: Georgia | D10: 5 | E10: South Atlantic
A11: 16 | B11: ID | C11: Idaho | D11: 8 | E11: Mountain North
A12: 17 | B12: IL | C12: Illinois | D12: 3 | E12: East North Central
A13: 18 | B13: IN | C13: Indiana | D13: 3 | E13: East North Central
... A49: 56 | B49: WY | C49: Wyoming | D49: 8 | E49: Mountain North

Sheet Keys
A1: category | B1: key | C1: value | D1: description | E1: unit
A2: coal_conversion | B2: hard_coal_mmbtu_per_ton | C2: 20.5 | D2: Hard coal energy content | E2: MMBtu/short ton
A3: coal_conversion | B3: lignite_mmbtu_per_ton | C3: 14 | D3: Lignite energy content | E3: MMBtu/short ton
A4: ng_conversion | B4: ng_btu_per_mcf | C4: 1037 | D4: Natural gas energy content (HHV) | E4: BTU/cubic foot
A5: crude_conversion | B5: crude_mmbtu_per_bbl | C5: 5.8 | D5: Crude oil energy content | E5: MMBtu/barrel
A6: pet_conversion | B6: gasoline_mmbtu_per_bbl | C6: 5.053 | D6: Motor gasoline (RFG+conv) | E6: MMBtu/barrel
A7: pet_conversion | B7: diesel_mmbtu_per_bbl | C7: 5.825 | D7: Distillate fuel oil / diesel | E7: MMBtu/barrel
A8: pet_conversion | B8: jet_mmbtu_per_bbl | C8: 5.67 | D8: Jet fuel / kerosene | E8: MMBtu/barrel
A9: pet_conversion | B9: heavy_oil_mmbtu_per_bbl | C9: 6.287 | D9: Residual (heavy) fuel oil | E9: MMBtu/barrel
A10: pet_conversion | B10: lpg_mmbtu_per_bbl | C10: 3.581 | D10: LPG (propane + butane avg) | E10: MMBtu/barrel
A11: pet_conversion | B11: biofuel_gasoline_mmbtu_per_bbl | C11: 3.539 | D11: Ethanol denatured | E11: MMBtu/barrel
A12: pet_conversion | B12: biofuel_diesel_mmbtu_per_bbl | C12: 5.359 | D12: Biodiesel (B100) | E12: MMBtu/barrel
A13: biomass_conversion | B13: biomass_mmbtu_per_ton | C13: 16 | D13: Wood pellets / densified biomass | E13: MMBtu/short ton
... A16: unit | B16: mcf_to_cf | C16: 1000 | D16: MCF -> cubic feet | E16: -
A17: coal_rank | B17: lignite_state_1 | C17: Texas | D17: Lignite-producing state | E17: -
A18: coal_rank | B18: lignite_state_2 | C18: North Dakota | D18: Lignite-producing state | E18: -
A19: coal_rank | B19: lignite_state_3 | C19: Mississippi | D19: Lignite-producing state | E19: -
A20: coal_rank | B20: lignite_state_4 | C20: Louisiana | D20: Lignite-producing state | E20: -
A21: coal_rank | B21: hard_coal_label | C21: hard_coal | D21: Rank label | E21: -
A22: coal_rank | B22: lignite_label | C22: lignite | D22: Rank label | E22: -
A23: unit | B23: thousand_to_unit | C23: 1000 | D23: Thousand barrels -> barrels; thousand lbs -> lbs | E23: -
A24: unit | B24: mmcf_to_cf | C24: 1000000 | D24: MMcf -> cubic feet | E24: -
A25: unit | B25: gal_per_bbl | C25: 42 | D25: US gallons per barrel | E25: gal/bbl
A26: source_token | B26: anchor_year | C26: 2024 | D26: Base/anchor year matched in raw source tabs | E26: Year
A27: source_token | B27: anchor_year_datewild | C27: 2024-* | D27: Anchor year as an EIA dnav date label (matched with wildcard before the plain numeric year) | E27: -
A28: source_token | B28: wildcard | C28: * | D28: Trailing wildcard appended to a state name when matching raw-tab column headers | E28: -
A29: source_token | B29: state_name_split_token | C29: ( | D29: Separator between state name and parenthetical in coalpublic STATE labels; the helper column keeps everything left of it | E29: -
A30: source_token | B30: eia923_lignite_fuel_code | C30: LIG | D30: EIA-923 Reported Fuel Type Code for lignite; every other coal code is hard coal | E30: -
A31: source_token | B31: duoarea_state_offset | C31: 2 | D31: Start position of the 2-letter state code inside an EIA duoarea code (e.g. SAL -> AL) | E31: char
A32: source_token | B32: duoarea_state_length | C32: 2 | D32: Length of the state code inside an EIA duoarea code | E32: char
A33: source_token | B33: refcap_product_operating_capacity | C33: OPERATING CAPACITY | D33: refcap25 PRODUCT value selecting operating (not idle) capacity rows | E33: -
A34: source_token | B34: refcap_supply_atm_crude | C34: Atmospheric Crude Distillation Capacity (barrels per calendar day) | D34: refcap25 SUPPLY value selecting atmospheric crude distillation capacity | E34: -
A35: source_token | B35: us_total_label | C35: U.S. | D35: Column header prefix for the US-total series in the EIA dnav by-state tabs | E35: -
A36: source_token | B36: crude_oil_label | C36: crude oil | D36: Fuel label used when matching the staged US petroleum export/production tabs | E36: -
A37: source_token | B37: biofuel_gasoline_label | C37: biofuel gasoline | D37: Fuel label in the staged US petroleum export tab | E37: -
A38: source_token | B38: biofuel_diesel_label | C38: biofuel diesel | D38: Fuel label in the staged US petroleum export tab | E38: -
A39: source_token | B39: fuel_ethanol_label | C39: fuel ethanol | D39: Fuel label in the staged US petroleum production tab | E39: -
A40: source_token | B40: us_prod_cat_lpg | C40: lpg | D40: Category in US_pet_production_raw summing propane + n-butane + isobutane (field + refinery). Ethane is deliberately EXCLUDED: the EPS fuel is "LPG propane or butane" and ethane is ~44% of US NGL field production. | E40: -
A41: source_token | B41: us_prod_cat_biofuel_diesel | C41: biofuel diesel | D41: Category in US_pet_production_raw summing biodiesel + renewable diesel net production | E41: -
A42: source_token | B42: seds_biodiesel_label | C42: biodiesel | D42: Fuel label in SEDS_biofuel_raw for the biodiesel rows | E42: -
A43: pet5_cols | B43: pet5_col_prod_gasoline | C43: 11 | D43: US Refinery and Blender Net Production of Finished Motor Gasoline | E43: col index
A44: pet5_cols | B44: pet5_col_prod_jet | C44: 40 | D44: US Refinery and Blender Net Production of Kerosene-Type Jet Fuel | E44: col index
A45: pet5_cols | B45: pet5_col_prod_distillate | C45: 54 | D45: US Refinery and Blender Net Production of Distillate Fuel Oil | E45: col index
A46: pet5_cols | B46: pet5_col_prod_residual | C46: 84 | D46: US Refinery and Blender Net Production of Residual Fuel Oil | E46: col index
A47: assumption | B47: alloc_refinery_products | C47: state share of US atmospheric crude distillation capacity | D47: ASSUMPTION - allocator for gasoline / diesel / jet / heavy fuel oil. Sound: these are refinery outputs, so refinery capacity is the right basis. | E47: -
A48: assumption | B48: alloc_lpg | C48: state share of US dry natural gas production | D48: ASSUMPTION - allocator for LPG/propane. US total is NGPL FIELD production, which comes from gas processing rather than refineries, so gas production is a closer basis than refinery capacity. Still imperfect: NGL yield per Mcf varies by basin (rich Permian/Eagle Ford gas yields more NGL than dry Appalachian gas), so gas-rich-but-dry states are over-weighted and wet-gas states under-weighted. | E48: -
A49: assumption | B49: alloc_biofuels | C49: state share of SEDS state biofuel production (EMFDB ethanol / BDFDB biodiesel) | D49: ASSUMPTION - allocator for fuel ethanol and biodiesel, from SEDS_biofuel_raw. SEDS reports these on a feedstock-energy basis (billion Btu), so it is used as a SHARE basis only, applied to the published US ethanol / biodiesel totals. Sanity: ethanol share IA 26.9%, NE 12.8%, IL 10.0%, TX 2.3% - matches where ethanol plants actually are. Supersedes refinery-capacity share, which put ~31% of US ethanol in Texas and 0% in Iowa. Vintage 2023 (latest SEDS). | E49: -
A50: source_token | B50: seds_msn_ethanol | C50: EMFDB | D50: SEDS MSN for state fuel ethanol production (feedstock-energy basis) | E50: -
A51: source_token | B51: seds_msn_biodiesel | C51: BDFDB | D51: SEDS MSN for state biodiesel production (feedstock-energy basis) | E51: -
A52: assumption | B52: biofuel_diesel_includes_renewable | C52: 1 | D52: ASSUMPTION - "biofuel diesel" sums biodiesel (FAME) AND renewable diesel (HEFA). They are chemically different but both are diesel-substitute biofuels in the EPS fuel set, and renewable diesel is now the larger of the two (76,054 vs 39,795 MBBL in 2024). Excluding it understated the fuel ~3x and zeroed Gulf Coast renewable-diesel states. | E52: boolean
A53: uranium_state | B53: uranium_only_producer | C53: Wyoming | D53: Per EIA, ~100% of US U3O8 produced in WY | E53: -
A54: eps_run | B54: eps_run_label | C54: bau-0831 | D54: EPS 48-state BAU run export supplying the growth trajectories | E54: -
A55: eps_run | B55: model_base_year | C55: 2025 | D55: EPS INITIAL TIME - first year of the run, and the growth index base year | E55: Year
A56: eps_run | B56: model_final_year | C56: 2050 | D56: EPS FINAL TIME | E56: Year
A57: eps_run | B57: key_separator | C57: | | D57: Separator used to build EPS_run_raw match keys (state|fuel|mode) | E57: -
A58: growth | B58: index_base_factor | C58: 1 | D58: Growth factor in the index base year, and wherever the prior-year value is zero (series held flat) | E58: -
A59: growth | B59: zero_test | C59: 0 | D59: Compared against a prior-year value to detect a zero denominator | E59: -
A60: growth | B60: mode_production | C60: production | D60: BFPIaE Fuel Balancing Mode subscript | E60: -
A61: growth | B61: mode_imports | C61: imports | D61: BFPIaE Fuel Balancing Mode subscript | E61: -
A62: growth | B62: mode_exports | C62: exports | D62: BFPIaE Fuel Balancing Mode subscript | E62: -
A63: ng_moves | B63: ng_process_interstate_receipts | C63: MIR | D63: Interstate Movements: Receipts | E63: -
A64: ng_moves | B64: ng_process_interstate_deliveries | C64: MID | D64: Interstate Movements: Deliveries | E64: -
A65: ng_moves | B65: ng_process_intl_receipts | C65: IMI | D65: Imports + Intransit (international receipts) | E65: -
A66: ng_moves | B66: ng_process_intl_deliveries | C66: EEI | D66: Exports + Intransit (international deliveries) | E66: -
A67: ng_moves | B67: ng_moves_year | C67: 2024 | D67: Anchor year for NG movement flows | E67: Year
A68: nuclear | B68: billion_btu_to_btu | C68: 1000000000 | D68: SEDS NUETB is billion BTU | E68: -
A69: hydrogen | B69: h2_btu_per_cf | C69: 325 | D69: Hydrogen HHV per standard cubic foot | E69: BTU/scf
A70: hydrogen | B70: days_per_year | C70: 365 | D70: Capacity (MMCF/D) -> annual volume | E70: -
A71: hydrogen | B71: mmcf_to_cf | C71: 1000000 | D71: MMcf -> cubic feet | E71: -
A72: census_hs | B72: hs_crude | C72: 270900 | D72: Crude petroleum oils | E72: -
A73: census_hs | B73: hs_gasoline | C73: 271012 | D73: Light petroleum oils (incl motor gasoline) | E73: -
A74: census_hs | B74: hs_diesel_jet_hfo | C74: 271019 | D74: Other petroleum oils (diesel/jet/heavy fuel oil share basis) | E74: -
A75: census_hs | B75: hs_ethanol | C75: 220720 | D75: Denatured fuel ethanol | E75: -
A76: census_hs | B76: hs_biodiesel | C76: 382600 | D76: Biodiesel | E76: -
A77: pet5_cols | B77: pet5_col_exports_gasoline | C77: 15 | D77: US Exports of Finished Motor Gasoline | E77: col index
A78: pet5_cols | B78: pet5_col_exports_jet | C78: 43 | D78: US Exports of Kerosene-Type Jet Fuel | E78: col index
A79: pet5_cols | B79: pet5_col_exports_distillate | C79: 58 | D79: US Exports of Distillate Fuel Oil | E79: col index
A80: pet5_cols | B80: pet5_col_exports_residual | C80: 87 | D80: US Exports of Residual Fuel Oil | E80: col index
A81: aeo | B81: aeo_first_year | C81: 2025 | D81: First AEO projection year (= EPS INITIAL TIME) | E81: Year
A82: aeo | B82: aeo58_year_header_row | C82: 1 | D82: AEO58_crude_region_raw year header row | E82: row
A83: aeo | B83: aeo59_year_header_row | C83: 1 | D83: AEO59_ng_region_raw year header row | E83: row
A84: aeo | B84: aeo65_year_header_row | C84: 1 | D84: AEO65_coal_region_raw year header row | E84: row
A85: aeo | B85: aeo11_year_header_row | C85: 10 | D85: AEO11_liquids_raw year header row | E85: row
A86: aeo | B86: aeo19_year_header_row | C86: 10 | D86: AEO19_hydrogen_raw year header row | E86: row
A87: aeo | B87: aeo58_region_block_last_row | C87: 37 | D87: Crude production block ends here; price block repeats region names below | E87: row
A88: aeo | B88: aeo59_region_block_last_row | C88: 35 | D88: NG production block ends here | E88: row
... A94: aeo | B94: aeo19_row_total_hydrogen | C94: 19 | D94: Total Hydrogen Supply | E94: row
A95: aeo | B95: fuel_group_og | C95: og | D95: Region_crosswalk fuel_group for crude oil + natural gas | E95: -
A96: aeo | B96: fuel_group_coal | C96: coal | D96: Region_crosswalk fuel_group for hard coal + lignite | E96: -
A97: aeo | B97: aeo58_row_offshore_gulf | C97: 31 | D97: AEO58 "Lower 48 Offshore" > "Gulf" crude production row - federal offshore GOM trajectory for the allocated offshore component | E97: row
A98: offshore | B98: fed_offshore_gulf_hdr | C98: Federal Offshore--Gulf | D98: Header prefix of the federal offshore GOM column on Crude_production_raw (prefix-matched so the Federal Offshore PADD 5 column cannot be picked up) | E98: -
A99: aeo_source | B99: aeo_source_electricity | C99: n/a - not a fuel / not used in this variable | D99: AEO production series driving electricity (not used in this variable) growth | E99: -
A100: aeo_source | B100: aeo_source_hard_coal | C100: AEO65_coal_region_raw, regional - Region_crosswalk fuel_group "coal" | D100: AEO production series driving hard coal growth | E100: -
A101: aeo_source | B101: aeo_source_natural_gas | C101: AEO59_ng_region_raw, regional - Region_crosswalk fuel_group "og" | D101: AEO production series driving natural gas growth | E101: -
A102: aeo_source | B102: aeo_source_nuclear | C102: none published - held flat (factor 1) | D102: AEO production series driving nuclear growth | E102: -
A103: aeo_source | B103: aeo_source_hydro | C103: n/a - not a fuel / not used in this variable | D103: AEO production series driving hydro (is not a fuel) growth | E103: -
A104: aeo_source | B104: aeo_source_wind | C104: n/a - not a fuel / not used in this variable | D104: AEO production series driving wind (is not a fuel) growth | E104: -
A105: aeo_source | B105: aeo_source_solar | C105: n/a - not a fuel / not used in this variable | D105: AEO production series driving solar (is not a fuel) growth | E105: -
A106: aeo_source | B106: aeo_source_biomass | C106: none published - held flat (factor 1) | D106: AEO production series driving biomass growth | E106: -
A107: aeo_source | B107: aeo_source_petroleum_gasoline | C107: AEO11_liquids_raw, national row per Keys aeo11_row_total_crude_supply | D107: AEO production series driving petroleum gasoline growth | E107: -
...

Sheet Region_crosswalk
A1: state_abbr | B1: fuel_group | C1: region_1 | D1: weight_1 | E1: region_2 | F1: weight_2 | G1: notes | H1: helper: match_key | J1: ACTIVE-STATE REGION ASSIGNMENT - resolved from the table at left for About!B1. Read by AEO_growth_calcs section 1.
A2: AL | B2: og | C2: Gulf Coast | D2: 1 | H2: =A2&VLOOKUP("key_separator", Keys!$B:$C, 2, FALSE)&B2 -> AL|og | J2: fuel_group | K2: region 1 | L2: weight 1 | M2: region 2 | N2: weight 2
A3: AZ | B3: og | C3: Rocky Mountain | D3: 1 | H3: =A3&VLOOKUP("key_separator", Keys!$B:$C, 2, FALSE)&B3 -> AZ|og | J3: =VLOOKUP("fuel_group_og", Keys!$B:$C, 2, FALSE) -> og | K3: =IFERROR(INDEX($C$2:$C$97, MATCH(About!$B$2&VLOOKUP("key_separator", Keys!$B:$C, 2, FALSE)&$J3, $H$2:$H$97, 0))&"", "") -> Midcontinent | L3: =IFERROR(--IFERROR(INDEX($D$2:$D$97, MATCH(About!$B$2&VLOOKUP("key_separator", Keys!$B:$C, 2, FALSE)&$J3, $H$2:$H$97, 0)), ""), VLOOKUP("zero_test", Keys!$B:$C, 2, FALSE)) -> 1 | M3: =IFERROR(INDEX($E$2:$E$97, MATCH(About!$B$2&VLOOKUP("key_separator", Keys!$B:$C, 2, FALSE)&$J3, $H$2:$H$97, 0))&"", "") | N3: =IFERROR(--IFERROR(INDEX($F$2:$F$97, MATCH(About!$B$2&VLOOKUP("key_separator", Keys!$B:$C, 2, FALSE)&$J3, $H$2:$H$97, 0)), ""), VLOOKUP("zero_test", Keys!$B:$C, 2, FALSE)) -> 0
A4: AR | B4: og | C4: Midcontinent | D4: 1 | G4: Fayetteville/Arkoma dominant; S-AR Gulf Coast share negligible | H4: =A4&VLOOKUP("key_separator", Keys!$B:$C, 2, FALSE)&B4 -> AR|og | J4: =VLOOKUP("fuel_group_coal", Keys!$B:$C, 2, FALSE) -> coal | K4: =IFERROR(INDEX($C$2:$C$97, MATCH(About!$B$2&VLOOKUP("key_separator", Keys!$B:$C, 2, FALSE)&$J4, $H$2:$H$97, 0))&"", "") -> Interior | L4: =IFERROR(--IFERROR(INDEX($D$2:$D$97, MATCH(About!$B$2&VLOOKUP("key_separator", Keys!$B:$C, 2, FALSE)&$J4, $H$2:$H$97, 0)), ""), VLOOKUP("zero_test", Keys!$B:$C, 2, FALSE)) -> 1 | M4: =IFERROR(INDEX($E$2:$E$97, MATCH(About!$B$2&VLOOKUP("key_separator", Keys!$B:$C, 2, FALSE)&$J4, $H$2:$H$97, 0))&"", "") | N4: =IFERROR(--IFERROR(INDEX($F$2:$F$97, MATCH(About!$B$2&VLOOKUP("key_separator", Keys!$B:$C, 2, FALSE)&$J4, $H$2:$H$97, 0)), ""), VLOOKUP("zero_test", Keys!$B:$C, 2, FALSE)) -> 0
A5: CA | B5: og | C5: West Coast | D5: 1 | H5: =A5&VLOOKUP("key_separator", Keys!$B:$C, 2, FALSE)&B5 -> CA|og
A6: CO | B6: og | C6: Rocky Mountain | D6: 1 | H6: =A6&VLOOKUP("key_separator", Keys!$B:$C, 2, FALSE)&B6 -> CO|og
A7: CT | B7: og | C7: East | D7: 1 | H7: =A7&VLOOKUP("key_separator", Keys!$B:$C, 2, FALSE)&B7 -> CT|og
A8: DE | B8: og | C8: East | D8: 1 | H8: =A8&VLOOKUP("key_separator", Keys!$B:$C, 2, FALSE)&B8 -> DE|og
A9: FL | B9: og | C9: Gulf Coast | D9: 1 | H9: =A9&VLOOKUP("key_separator", Keys!$B:$C, 2, FALSE)&B9 -> FL|og
A10: GA | B10: og | C10: East | D10: 1 | H10: =A10&VLOOKUP("key_separator", Keys!$B:$C, 2, FALSE)&B10 -> GA|og
A11: ID | B11: og | C11: Rocky Mountain | D11: 1 | H11: =A11&VLOOKUP("key_separator", Keys!$B:$C, 2, FALSE)&B11 -> ID|og
A12: IL | B12: og | C12: East | D12: 1 | H12: =A12&VLOOKUP("key_separator", Keys!$B:$C, 2, FALSE)&B12 -> IL|og
A13: IN | B13: og | C13: East | D13: 1 | H13: =A13&VLOOKUP("key_separator", Keys!$B:$C, 2, FALSE)&B13 -> IN|og
A14: IA | B14: og | C14: Midcontinent | D14: 1 | H14: =A14&VLOOKUP("key_separator", Keys!$B:$C, 2, FALSE)&B14 -> IA|og
A15: KS | B15: og | C15: Midcontinent | D15: 1 | H15: =A15&VLOOKUP("key_separator", Keys!$B:$C, 2, FALSE)&B15 -> KS|og
A16: KY | B16: og | C16: East | D16: 1 | H16: =A16&VLOOKUP("key_separator", Keys!$B:$C, 2, FALSE)&B16 -> KY|og
... A29: NJ | B29: og | C29: East | D29: 1 | H29: =A29&VLOOKUP("key_separator", Keys!$B:$C, 2, FALSE)&B29 -> NJ|og
A30: NM | B30: og | C30: Southwest | D30: 0.85 | E30: Rocky Mountain | F30: 0.15 | G30: Permian (SE NM) dominant; San Juan basin (NW) is Rocky Mountain - weight approximates gas-heavy SJ share | H30: =A30&VLOOKUP("key_separator", Keys!$B:$C, 2, FALSE)&B30 -> NM|og
A31: NY | B31: og | C31: East | D31: 1 | H31: =A31&VLOOKUP("key_separator", Keys!$B:$C, 2, FALSE)&B31 -> NY|og
A32: NC | B32: og | C32: East | D32: 1 | H32: =A32&VLOOKUP("key_separator", Keys!$B:$C, 2, FALSE)&B32 -> NC|og
A33: ND | B33: og | C33: Northern Great Plains | D33: 1 | H33: =A33&VLOOKUP("key_separator", Keys!$B:$C, 2, FALSE)&B33 -> ND|og
A34: OH | B34: og | C34: East | D34: 1 | H34: =A34&VLOOKUP("key_separator", Keys!$B:$C, 2, FALSE)&B34 -> OH|og
A35: OK | B35: og | C35: Midcontinent | D35: 1 | H35: =A35&VLOOKUP("key_separator", Keys!$B:$C, 2, FALSE)&B35 -> OK|og
A36: OR | B36: og | C36: West Coast | D36: 1 | H36: =A36&VLOOKUP("key_separator", Keys!$B:$C, 2, FALSE)&B36 -> OR|og
A37: PA | B37: og | C37: East | D37: 1 | H37: =A37&VLOOKUP("key_separator", Keys!$B:$C, 2, FALSE)&B37 -> PA|og
A38: RI | B38: og | C38: East | D38: 1 | H38: =A38&VLOOKUP("key_separator", Keys!$B:$C, 2, FALSE)&B38 -> RI|og
A39: SC | B39: og | C39: East | D39: 1 | H39: =A39&VLOOKUP("key_separator", Keys!$B:$C, 2, FALSE)&B39 -> SC|og
A40: SD | B40: og | C40: Northern Great Plains | D40: 1 | H40: =A40&VLOOKUP("key_separator", Keys!$B:$C, 2, FALSE)&B40 -> SD|og
A41: TN | B41: og | C41: East | D41: 1 | H41: =A41&VLOOKUP("key_separator", Keys!$B:$C, 2, FALSE)&B41 -> TN|og
A42: TX | B42: og | C42: Southwest | D42: 0.65 | E42: Gulf Coast | F42: 0.35 | G42: Permian (SW) vs Eagle Ford/Haynesville-TX/gulf districts (GC); panhandle Midcontinent share folded into SW. Approximate - staff-tunable | H42: =A42&VLOOKUP("key_separator", Keys!$B:$C, 2, FALSE)&B42 -> TX|og
A43: UT | B43: og | C43: Rocky Mountain | D43: 1 | H43: =A43&VLOOKUP("key_separator", Keys!$B:$C, 2, FALSE)&B43 -> UT|og
A44: VT | B44: og | C44: East | D44: 1 | H44: =A44&VLOOKUP("key_separator", Keys!$B:$C, 2, FALSE)&B44 -> VT|og
A45: VA | B45: og | C45: East | D45: 1 | H45: =A45&VLOOKUP("key_separator", Keys!$B:$C, 2, FALSE)&B45 -> VA|og
A46: WA | B46: og | C46: West Coast | D46: 1 | H46: =A46&VLOOKUP("key_separator", Keys!$B:$C, 2, FALSE)&B46 -> WA|og
A47: WV | B47: og | C47: East | D47: 1 | H47: =A47&VLOOKUP("key_separator", Keys!$B:$C, 2, FALSE)&B47 -> WV|og
A48: WI | B48: og | C48: East | D48: 1 | H48: =A48&VLOOKUP("key_separator", Keys!$B:$C, 2, FALSE)&B48 -> WI|og
A49: WY | B49: og | C49: Rocky Mountain | D49: 1 | G49: Powder River + Green River both inside Rocky Mountain-5 per m063 Fig 1-2 | H49: =A49&VLOOKUP("key_separator", Keys!$B:$C, 2, FALSE)&B49 -> WY|og
A50: AL | B50: coal | C50: Appalachia | D50: 1 | H50: =A50&VLOOKUP("key_separator", Keys!$B:$C, 2, FALSE)&B50 -> AL|coal
A51: AZ | B51: coal | C51: West | D51: 1 | H51: =A51&VLOOKUP("key_separator", Keys!$B:$C, 2, FALSE)&B51 -> AZ|coal
A52: AR | B52: coal | C52: Interior | D52: 1 | H52: =A52&VLOOKUP("key_separator", Keys!$B:$C, 2, FALSE)&B52 -> AR|coal
A53: CA | B53: coal | C53: West | D53: 1 | H53: =A53&VLOOKUP("key_separator", Keys!$B:$C, 2, FALSE)&B53 -> CA|coal
A54: CO | B54: coal | C54: West | D54: 1 | H54: =A54&VLOOKUP("key_separator", Keys!$B:$C, 2, FALSE)&B54 -> CO|coal
A55: CT | B55: coal | C55: Appalachia | D55: 1 | G55: no production; region irrelevant | H55: =A55&VLOOKUP("key_separator", Keys!$B:$C, 2, FALSE)&B55 -> CT|coal
A56: DE | B56: coal | C56: Appalachia | D56: 1 | G56: no production | H56: =A56&VLOOKUP("key_separator", Keys!$B:$C, 2, FALSE)&B56 -> DE|coal
A57: FL | B57: coal | C57: Interior | D57: 1 | G57: no production | H57: =A57&VLOOKUP("key_separator", Keys!$B:$C, 2, FALSE)&B57 -> FL|coal
A58: GA | B58: coal | C58: Appalachia | D58: 1 | G58: no production | H58: =A58&VLOOKUP("key_separator", Keys!$B:$C, 2, FALSE)&B58 -> GA|coal
A59: ID | B59: coal | C59: West | D59: 1 | G59: no production | H59: =A59&VLOOKUP("key_separator", Keys!$B:$C, 2, FALSE)&B59 -> ID|coal
A60: IL | B60: coal | C60: Interior | D60: 1 | H60: =A60&VLOOKUP("key_separator", Keys!$B:$C, 2, FALSE)&B60 -> IL|coal
A61: IN | B61: coal | C61: Interior | D61: 1 | H61: =A61&VLOOKUP("key_separator", Keys!$B:$C, 2, FALSE)&B61 -> IN|coal
A62: IA | B62: coal | C62: Interior | D62: 1 | G62: no production | H62: =A62&VLOOKUP("key_separator", Keys!$B:$C, 2, FALSE)&B62 -> IA|coal
A63: KS | B63: coal | C63: Interior | D63: 1 | H63: =A63&VLOOKUP("key_separator", Keys!$B:$C, 2, FALSE)&B63 -> KS|coal
A64: KY | B64: coal | C64: Appalachia | D64: 0.5 | E64: Interior | F64: 0.5 | G64: East KY = Central Appalachia; West KY = Illinois basin (Interior). Recent production roughly even - staff-tunable | H64: =A64&VLOOKUP("key_separator", Keys!$B:$C, 2, FALSE)&B64 -> KY|coal
A65: LA | B65: coal | C65: Interior | D65: 1 | G65: lignite | H65: =A65&VLOOKUP("key_separator", Keys!$B:$C, 2, FALSE)&B65 -> LA|coal
A66: ME | B66: coal | C66: Appalachia | D66: 1 | G66: no production | H66: =A66&VLOOKUP("key_separator", Keys!$B:$C, 2, FALSE)&B66 -> ME|coal
A67: MD | B67: coal | C67: Appalachia | D67: 1 | H67: =A67&VLOOKUP("key_separator", Keys!$B:$C, 2, FALSE)&B67 -> MD|coal
A68: MA | B68: coal | C68: Appalachia | D68: 1 | G68: no production | H68: =A68&VLOOKUP("key_separator", Keys!$B:$C, 2, FALSE)&B68 -> MA|coal
A69: MI | B69: coal | C69: Interior | D69: 1 | G69: no production | H69: =A69&VLOOKUP("key_separator", Keys!$B:$C, 2, FALSE)&B69 -> MI|coal
A70: MN | B70: coal | C70: Interior | D70: 1 | G70: no production | H70: =A70&VLOOKUP("key_separator", Keys!$B:$C, 2, FALSE)&B70 -> MN|coal
A71: MS | B71: coal | C71: Interior | D71: 1 | G71: lignite | H71: =A71&VLOOKUP("key_separator", Keys!$B:$C, 2, FALSE)&B71 -> MS|coal
A72: MO | B72: coal | C72: Interior | D72: 1 | H72: =A72&VLOOKUP("key_separator", Keys!$B:$C, 2, FALSE)&B72 -> MO|coal
A73: MT | B73: coal | C73: West | D73: 1 | H73: =A73&VLOOKUP("key_separator", Keys!$B:$C, 2, FALSE)&B73 -> MT|coal
A74: NE | B74: coal | C74: Interior | D74: 1 | G74: no production | H74: =A74&VLOOKUP("key_separator", Keys!$B:$C, 2, FALSE)&B74 -> NE|coal
A75: NV | B75: coal | C75: West | D75: 1 | G75: no production | H75: =A75&VLOOKUP("key_separator", Keys!$B:$C, 2, FALSE)&B75 -> NV|coal
A76: NH | B76: coal | C76: Appalachia | D76: 1 | G76: no production | H76: =A76&VLOOKUP("key_separator", Keys!$B:$C, 2, FALSE)&B76 -> NH|coal
A77: NJ | B77: coal | C77: Appalachia | D77: 1 | G77: no production | H77: =A77&VLOOKUP("key_separator", Keys!$B:$C, 2, FALSE)&B77 -> NJ|coal
A78: NM | B78: coal | C78: West | D78: 1 | H78: =A78&VLOOKUP("key_separator", Keys!$B:$C, 2, FALSE)&B78 -> NM|coal
A79: NY | B79: coal | C79: Appalachia | D79: 1 | G79: no production | H79: =A79&VLOOKUP("key_separator", Keys!$B:$C, 2, FALSE)&B79 -> NY|coal
A80: NC | B80: coal | C80: Appalachia | D80: 1 | G80: no production | H80: =A80&VLOOKUP("key_separator", Keys!$B:$C, 2, FALSE)&B80 -> NC|coal
A81: ND | B81: coal | C81: West | D81: 1 | G81: lignite | H81: =A81&VLOOKUP("key_separator", Keys!$B:$C, 2, FALSE)&B81 -> ND|coal
A82: OH | B82: coal | C82: Appalachia | D82: 1 | H82: =A82&VLOOKUP("key_separator", Keys!$B:$C, 2, FALSE)&B82 -> OH|coal
A83: OK | B83: coal | C83: Interior | D83: 1 | H83: =A83&VLOOKUP("key_separator", Keys!$B:$C, 2, FALSE)&B83 -> OK|coal
A84: OR | B84: coal | C84: West | D84: 1 | G84: no production | H84: =A84&VLOOKUP("key_separator", Keys!$B:$C, 2, FALSE)&B84 -> OR|coal
A85: PA | B85: coal | C85: Appalachia | D85: 1 | H85: =A85&VLOOKUP("key_separator", Keys!$B:$C, 2, FALSE)&B85 -> PA|coal
A86: RI | B86: coal | C86: Appalachia | D86: 1 | G86: no production | H86: =A86&VLOOKUP("key_separator", Keys!$B:$C, 2, FALSE)&B86 -> RI|coal
A87: SC | B87: coal | C87: Appalachia | D87: 1 | G87: no production | H87: =A87&VLOOKUP("key_separator", Keys!$B:$C, 2, FALSE)&B87 -> SC|coal
A88: SD | B88: coal | C88: West | D88: 1 | G88: no production | H88: =A88&VLOOKUP("key_separator", Keys!$B:$C, 2, FALSE)&B88 -> SD|coal
A89: TN | B89: coal | C89: Appalachia | D89: 1 | H89: =A89&VLOOKUP("key_separator", Keys!$B:$C, 2, FALSE)&B89 -> TN|coal
A90: TX | B90: coal | C90: Interior | D90: 1 | G90: lignite | H90: =A90&VLOOKUP("key_separator", Keys!$B:$C, 2, FALSE)&B90 -> TX|coal
A91: UT | B91: coal | C91: West | D91: 1 | H91: =A91&VLOOKUP("key_separator", Keys!$B:$C, 2, FALSE)&B91 -> UT|coal
A92: VT | B92: coal | C92: Appalachia | D92: 1 | G92: no production | H92: =A92&VLOOKUP("key_separator", Keys!$B:$C, 2, FALSE)&B92 -> VT|coal
A93: VA | B93: coal | C93: Appalachia | D93: 1 | H93: =A93&VLOOKUP("key_separator", Keys!$B:$C, 2, FALSE)&B93 -> VA|coal
A94: WA | B94: coal | C94: West | D94: 1 | H94: =A94&VLOOKUP("key_separator", Keys!$B:$C, 2, FALSE)&B94 -> WA|coal
A95: WV | B95: coal | C95: Appalachia | D95: 1 | H95: =A95&VLOOKUP("key_separator", Keys!$B:$C, 2, FALSE)&B95 -> WV|coal
A96: WI | B96: coal | C96: Interior | D96: 1 | G96: no production | H96: =A96&VLOOKUP("key_separator", Keys!$B:$C, 2, FALSE)&B96 -> WI|coal
A97: WY | B97: coal | C97: West | D97: 1 | H97: =A97&VLOOKUP("key_separator", Keys!$B:$C, 2, FALSE)&B97 -> WY|coal

Sheet GOM_offshore_shares
A1: GOM_offshore_shares - federal offshore Gulf of Mexico crude allocated to states
A2: Allocation by BOEM active lease count (BOEM GOMR Active Lease Map); Louisiana = remainder. Same basis as POLICY_State Mapping in OilGasLeasing_Calculations_States_406.xlsx (Jan 2025 Frozen Policy Scenario - States), so BAU offshore production and the IiFPfOaGL leasing adjustment are allocated consistently. EIA reports federal offshore GOM crude as its own series - it is in no state's production data.
A4: Active state share of federal offshore GOM (read by Crude_calcs!B9): | B4: =IFERROR(INDEX($C$8:$C$11, MATCH(About!$B$1, $A$8:$A$11, 0)), VLOOKUP("zero_test", Keys!$B:$C, 2, FALSE)) -> 0
A6: State | B6: BOEM active leases (GOM) | C6: share of GOM offshore
A7: Total, Gulf of Mexico region | B7: 2206
A8: Texas | B8: 427 | C8: =B8/$B$7 -> 0.19356301
A9: Mississippi | B9: 2 | C9: =B9/$B$7 -> 0.00090661831
A10: Alabama | B10: 11 | C10: =B10/$B$7 -> 0.0049864007
A11: Louisiana | B11: =B7-SUM(B8:B10) -> 1766 | C11: =B11/$B$7 -> 0.80054397
A12: check: state leases sum to total / shares sum to 1 | B12: =SUM(B8:B11) -> 2206 | C12: =SUM(C8:C11) -> 1
A14: Scope: crude oil only. Federal offshore GOM natural gas (~593 Bcf in 2024, vs LA state series ~3,598 Bcf) is NOT yet allocated - flagged follow-up. Cook Inlet (AK) offshore is out of scope (AK not in the 48-state build).

Sheet Coal_production_raw
A1: Historical Coal Production Data: 2024
A2: Source: The U.S. Energy Information Administration (EIA) and the U.S. Mine Safety and Health Administration
A4: Year | B4: MSHA ID | C4: Mine Name | D4: Mine State | E4: Mine County | F4: Mine Status | G4: Mine Type | H4: Company Type | I4: Operation Type | J4: Operating Company | K4: Operating Company Address | L4: Union Code | M4: Coal Supply Region | N4: Production (short tons) | O4: Average Employees | P4: Labor Hours | Q4: helper: state_name_clean | R4: helper: rank
A5: 2024 | B5: 103441 | C5: Marvel Mine | D5: Alabama | E5: Bibb | F5: Permanently abandoned | G5: Surface | H5: Independent Producer Operator | I5: Mine only | J5: Camellia Met Mining, Llc | K5: 1615 Kent Dairy Road, Alabaster, AL 35007 | M5: Appalachia Southern | N5: 34001 | O5: 3 | P5: 5192 | Q5: =IFERROR(LEFT(D5, FIND(VLOOKUP("state_name_split_token", Keys!$B:$C, 2, FALSE), D5)-1), D5) -> Alabama | R5: =IF(OR(Q5=VLOOKUP("lignite_state_1", Keys!$B:$C, 2, FALSE),Q5=VLOOKUP("lignite_state_2", Keys!$B:$C, 2, FALSE),Q5=VLOOKUP("lignite_state_3", Keys!$B:$C, 2, FALSE),Q5=VLOOKUP("lignite_state_4", Keys!$B:$C, 2, FALSE)),VLOOKUP("lignite_label", Keys!$B:$C, 2, FALSE),VLOOKUP("hard_coal_label", Keys!$B:$C, 2, FALSE)) -> hard_coal
A6: 2024 | B6: 103540 | C6: Dodge Mine | D6: Alabama | E6: Cullman | F6: Active | G6: Surface | H6: Independent Producer Operator | I6: Preparation Plant | J6: Southern Mineral Resources Llc | K6: 1915 County Road 8, Hanceville, AL 35077 | M6: Appalachia Southern | N6: 0 | O6: 7 | P6: 15793 | Q6: =IFERROR(LEFT(D6, FIND(VLOOKUP("state_name_split_token", Keys!$B:$C, 2, FALSE), D6)-1), D6) -> Alabama | R6: =IF(OR(Q6=VLOOKUP("lignite_state_1", Keys!$B:$C, 2, FALSE),Q6=VLOOKUP("lignite_state_2", Keys!$B:$C, 2, FALSE),Q6=VLOOKUP("lignite_state_3", Keys!$B:$C, 2, FALSE),Q6=VLOOKUP("lignite_state_4", Keys!$B:$C, 2, FALSE)),VLOOKUP("lignite_label", Keys!$B:$C, 2, FALSE),VLOOKUP("hard_coal_label", Keys!$B:$C, 2, FALSE)) -> hard_coal
A7: 2024 | B7: 100329 | C7: Oak Grove Preparation Plant | D7: Alabama | E7: Jefferson | F7: Active | G7: Underground | H7: Operating Subsidiary | I7: Preparation Plant | J7: Crimson Oak Grove Resources Ll | K7: 8360 Taylors Ferry Rd, Hueytown, AL 35023 | L7: United Mine Workers Of America | M7: Appalachia Southern | N7: 0 | O7: 55 | P7: 136552 | Q7: =IFERROR(LEFT(D7, FIND(VLOOKUP("state_name_split_token", Keys!$B:$C, 2, FALSE), D7)-1), D7) -> Alabama | R7: =IF(OR(Q7=VLOOKUP("lignite_state_1", Keys!$B:$C, 2, FALSE),Q7=VLOOKUP("lignite_state_2", Keys!$B:$C, 2, FALSE),Q7=VLOOKUP("lignite_state_3", Keys!$B:$C, 2, FALSE),Q7=VLOOKUP("lignite_state_4", Keys!$B:$C, 2, FALSE)),VLOOKUP("lignite_label", Keys!$B:$C, 2, FALSE),VLOOKUP("hard_coal_label", Keys!$B:$C, 2, FALSE)) -> hard_coal
A8: 2024 | B8: 100851 | C8: Oak Grove Mine | D8: Alabama | E8: Jefferson | F8: Active | G8: Underground | H8: Operating Subsidiary | I8: Mine only | J8: Crimson Oak Grove Resources Ll | K8: 8800 Oak Grove Mine Road, Adger, AL 35006 | L8: United Mine Workers Of America | M8: Appalachia Southern | N8: 2806000 | O8: 490 | P8: 1242668 | Q8: =IFERROR(LEFT(D8, FIND(VLOOKUP("state_name_split_token", Keys!$B:$C, 2, FALSE), D8)-1), D8) -> Alabama | R8: =IF(OR(Q8=VLOOKUP("lignite_state_1", Keys!$B:$C, 2, FALSE),Q8=VLOOKUP("lignite_state_2", Keys!$B:$C, 2, FALSE),Q8=VLOOKUP("lignite_state_3", Keys!$B:$C, 2, FALSE),Q8=VLOOKUP("lignite_state_4", Keys!$B:$C, 2, FALSE)),VLOOKUP("lignite_label", Keys!$B:$C, 2, FALSE),VLOOKUP("hard_coal_label", Keys!$B:$C, 2, FALSE)) -> hard_coal
A9: 2024 | B9: 101401 | C9: No 7 Mine | D9: Alabama | E9: Jefferson | F9: Active | G9: Underground | H9: Independent Producer Operator | I9: Mine and Preparation Plant | J9: Warrior Met Coal Mining, Llc | K9: P.O. Box 133, Brookwood, AL 35444 | L9: United Mine Workers Of America | M9: Appalachia Southern | N9: 5269294 | O9: 646 | P9: 1875571 | Q9: =IFERROR(LEFT(D9, FIND(VLOOKUP("state_name_split_token", Keys!$B:$C, 2, FALSE), D9)-1), D9) -> Alabama | R9: =IF(OR(Q9=VLOOKUP("lignite_state_1", Keys!$B:$C, 2, FALSE),Q9=VLOOKUP("lignite_state_2", Keys!$B:$C, 2, FALSE),Q9=VLOOKUP("lignite_state_3", Keys!$B:$C, 2, FALSE),Q9=VLOOKUP("lignite_state_4", Keys!$B:$C, 2, FALSE)),VLOOKUP("lignite_label", Keys!$B:$C, 2, FALSE),VLOOKUP("hard_coal_label", Keys!$B:$C, 2, FALSE)) -> hard_coal
A10: 2024 | B10: 103182 | C10: Fishtrap | D10: Alabama | E10: Jefferson | F10: Active | G10: Surface | H10: Independent Producer Operator | I10: Mine only | J10: Highland Energy, Inc. | K10: 7802 Highway 78, Cordova, AL 35550 | M10: Appalachia Southern | N10: 12131 | O10: 10 | P10: 20616 | Q10: =IFERROR(LEFT(D10, FIND(VLOOKUP("state_name_split_token", Keys!$B:$C, 2, FALSE), D10)-1), D10) -> Alabama | R10: =IF(OR(Q10=VLOOKUP("lignite_state_1", Keys!$B:$C, 2, FALSE),Q10=VLOOKUP("lignite_state_2", Keys!$B:$C, 2, FALSE),Q10=VLOOKUP("lignite_state_3", Keys!$B:$C, 2, FALSE),Q10=VLOOKUP("lignite_state_4", Keys!$B:$C, 2, FALSE)),VLOOKUP("lignite_label", Keys!$B:$C, 2, FALSE),VLOOKUP("hard_coal_label", Keys!$B:$C, 2, FALSE)) -> hard_coal
A11: 2024 | B11: 103419 | C11: Maxine-Pratt Mine | D11: Alabama | E11: Jefferson | F11: Active | G11: Underground | H11: Independent Producer Operator | I11: Mine only | J11: Prospect Mining & Development | K11: 2002 Second Ave. S., Jasper, AL 35501 | M11: Appalachia Southern | N11: 102539 | O11: 35 | P11: 90127 | Q11: =IFERROR(LEFT(D11, FIND(VLOOKUP("state_name_split_token", Keys!$B:$C, 2, FALSE), D11)-1), D11) -> Alabama | R11: =IF(OR(Q11=VLOOKUP("lignite_state_1", Keys!$B:$C, 2, FALSE),Q11=VLOOKUP("lignite_state_2", Keys!$B:$C, 2, FALSE),Q11=VLOOKUP("lignite_state_3", Keys!$B:$C, 2, FALSE),Q11=VLOOKUP("lignite_state_4", Keys!$B:$C, 2, FALSE)),VLOOKUP("lignite_label", Keys!$B:$C, 2, FALSE),VLOOKUP("hard_coal_label", Keys!$B:$C, 2, FALSE)) -> hard_coal
A12: 2024 | B12: 103523 | C12: Shannon Mine No. 3 | D12: Alabama | E12: Jefferson | F12: Active | G12: Surface | H12: Independent Producer Operator | I12: Mine only | J12: Rjr Mining Company, Inc. | K12: 7202 Highway 78, Cordova, AL 35550 | M12: Appalachia Southern | N12: 234625 | O12: 66 | P12: 151432 | Q12: =IFERROR(LEFT(D12, FIND(VLOOKUP("state_name_split_token", Keys!$B:$C, 2, FALSE), D12)-1), D12) -> Alabama | R12: =IF(OR(Q12=VLOOKUP("lignite_state_1", Keys!$B:$C, 2, FALSE),Q12=VLOOKUP("lignite_state_2", Keys!$B:$C, 2, FALSE),Q12=VLOOKUP("lignite_state_3", Keys!$B:$C, 2, FALSE),Q12=VLOOKUP("lignite_state_4", Keys!$B:$C, 2, FALSE)),VLOOKUP("lignite_label", Keys!$B:$C, 2, FALSE),VLOOKUP("hard_coal_label", Keys!$B:$C, 2, FALSE)) -> hard_coal
A13: 2024 | B13: 102976 | C13: Piney Woods Preparation Plant | D13: Alabama | E13: Shelby | F13: Active | G13: Surface | H13: Independent Producer Operator | I13: Preparation Plant | J13: Camellia Met Mining, Llc | K13: 3400 County Road 260, Alabaster, AL 35114 | M13: Appalachia Southern | N13: 0 | O13: 3 | P13: 6240 | Q13: =IFERROR(LEFT(D13, FIND(VLOOKUP("state_name_split_token", Keys!$B:$C, 2, FALSE), D13)-1), D13) -> Alabama | R13: =IF(OR(Q13=VLOOKUP("lignite_state_1", Keys!$B:$C, 2, FALSE),Q13=VLOOKUP("lignite_state_2", Keys!$B:$C, 2, FALSE),Q13=VLOOKUP("lignite_state_3", Keys!$B:$C, 2, FALSE),Q13=VLOOKUP("lignite_state_4", Keys!$B:$C, 2, FALSE)),VLOOKUP("lignite_label", Keys!$B:$C, 2, FALSE),VLOOKUP("hard_coal_label", Keys!$B:$C, 2, FALSE)) -> hard_coal
A14: 2024 | B14: 103217 | C14: Coke Mine No 1 | D14: Alabama | E14: Shelby | F14: Active, men working, not producing | G14: Surface | H14: Independent Producer Operator | I14: Mine only | J14: Alabama Met Coal Resources Cor | K14: P.O. Box 217, St. Clairsvil, OH 43950 | M14: Appalachia Southern | N14: 1457 | O14: 4 | P14: 4965 | Q14: =IFERROR(LEFT(D14, FIND(VLOOKUP("state_name_split_token", Keys!$B:$C, 2, FALSE), D14)-1), D14) -> Alabama | R14: =IF(OR(Q14=VLOOKUP("lignite_state_1", Keys!$B:$C, 2, FALSE),Q14=VLOOKUP("lignite_state_2", Keys!$B:$C, 2, FALSE),Q14=VLOOKUP("lignite_state_3", Keys!$B:$C, 2, FALSE),Q14=VLOOKUP("lignite_state_4", Keys!$B:$C, 2, FALSE)),VLOOKUP("lignite_label", Keys!$B:$C, 2, FALSE),VLOOKUP("hard_coal_label", Keys!$B:$C, 2, FALSE)) -> hard_coal
A15: 2024 | B15: 103380 | C15: Calera | D15: Alabama | E15: Shelby | F15: Active | G15: Surface | H15: Independent Producer Operator | I15: Preparation Plant | J15: Conrad Yelvington Distributors | K15: 4636 Scarborough Dr, Lutz, FL 33559 | M15: Appalachia Southern | N15: 0 | O15: 1 | P15: 1251 | Q15: =IFERROR(LEFT(D15, FIND(VLOOKUP("state_name_split_token", Keys!$B:$C, 2, FALSE), D15)-1), D15) -> Alabama | R15: =IF(OR(Q15=VLOOKUP("lignite_state_1", Keys!$B:$C, 2, FALSE),Q15=VLOOKUP("lignite_state_2", Keys!$B:$C, 2, FALSE),Q15=VLOOKUP("lignite_state_3", Keys!$B:$C, 2, FALSE),Q15=VLOOKUP("lignite_state_4", Keys!$B:$C, 2, FALSE)),VLOOKUP("lignite_label", Keys!$B:$C, 2, FALSE),VLOOKUP("hard_coal_label", Keys!$B:$C, 2, FALSE)) -> hard_coal
A16: 2024 | B16: 103380 | C16: Calera | D16: Alabama | E16: Shelby | F16: Active | G16: Underground | H16: Independent Producer Operator | I16: Preparation Plant | J16: Conrad Yelvington Distributors | K16: 4636 Scarborough Dr, Lutz, FL 33559 | M16: Appalachia Southern | N16: 0 | O16: 11 | P16: 23779 | Q16: =IFERROR(LEFT(D16, FIND(VLOOKUP("state_name_split_token", Keys!$B:$C, 2, FALSE), D16)-1), D16) -> Alabama | R16: =IF(OR(Q16=VLOOKUP("lignite_state_1", Keys!$B:$C, 2, FALSE),Q16=VLOOKUP("lignite_state_2", Keys!$B:$C, 2, FALSE),Q16=VLOOKUP("lignite_state_3", Keys!$B:$C, 2, FALSE),Q16=VLOOKUP("lignite_state_4", Keys!$B:$C, 2, FALSE)),VLOOKUP("lignite_label", Keys!$B:$C, 2, FALSE),VLOOKUP("hard_coal_label", Keys!$B:$C, 2, FALSE)) -> hard_coal
A17: 2024 | B17: 101247 | C17: No 4 Mine | D17: Alabama | E17: Tuscaloosa | F17: Active | G17: Underground | H17: Independent Producer Operator | I17: Mine and Preparation Plant | J17: Warrior Met Coal Mining, Llc | K17: 14730 Lock 17 Rd, Brookwood, AL 35444 | L17: United Mine Workers Of America | M17: Appalachia Southern | N17: 2769238 | O17: 428 | P17: 1170251 | Q17: =IFERROR(LEFT(D17, FIND(VLOOKUP("state_name_split_token", Keys!$B:$C, 2, FALSE), D17)-1), D17) -> Alabama | R17: =IF(OR(Q17=VLOOKUP("lignite_state_1", Keys!$B:$C, 2, FALSE),Q17=VLOOKUP("lignite_state_2", Keys!$B:$C, 2, FALSE),Q17=VLOOKUP("lignite_state_3", Keys!$B:$C, 2, FALSE),Q17=VLOOKUP("lignite_state_4", Keys!$B:$C, 2, FALSE)),VLOOKUP("lignite_label", Keys!$B:$C, 2, FALSE),VLOOKUP("hard_coal_label", Keys!$B:$C, 2, FALSE)) -> hard_coal
A18: 2024 | B18: 103436 | C18: Swann's Crossing | D18: Alabama | E18: Tuscaloosa | F18: Active | G18: Surface | H18: Independent Producer Operator | I18: Mine only | J18: Southland Resources, Inc. | K18: P.O. Box 770, Cottondale, AL 35453 | M18: Appalachia Southern | N18: 270802 | O18: 80 | P18: 195467 | Q18: =IFERROR(LEFT(D18, FIND(VLOOKUP("state_name_split_token", Keys!$B:$C, 2, FALSE), D18)-1), D18) -> Alabama | R18: =IF(OR(Q18=VLOOKUP("lignite_state_1", Keys!$B:$C, 2, FALSE),Q18=VLOOKUP("lignite_state_2", Keys!$B:$C, 2, FALSE),Q18=VLOOKUP("lignite_state_3", Keys!$B:$C, 2, FALSE),Q18=VLOOKUP("lignite_state_4", Keys!$B:$C, 2, FALSE)),VLOOKUP("lignite_label", Keys!$B:$C, 2, FALSE),VLOOKUP("hard_coal_label", Keys!$B:$C, 2, FALSE)) -> hard_coal
A19: 2024 | B19: 103448 | C19: Blue Creek Mine No. 1 | D19: Alabama | E19: Tuscaloosa | F19: Active | G19: Underground | H19: Independent Producer Operator | I19: Mine only | J19: Warrior Met Coal Bc, Llc | K19: P.O. Box 133, Brookwood, AL 35444 | M19: Appalachia Southern | N19: 208760 | O19: 160 | P19: 67001 | Q19: =IFERROR(LEFT(D19, FIND(VLOOKUP("state_name_split_token", Keys!$B:$C, 2, FALSE), D19)-1), D19) -> Alabama | R19: =IF(OR(Q19=VLOOKUP("lignite_state_1", Keys!$B:$C, 2, FALSE),Q19=VLOOKUP("lignite_state_2", Keys!$B:$C, 2, FALSE),Q19=VLOOKUP("lignite_state_3", Keys!$B:$C, 2, FALSE),Q19=VLOOKUP("lignite_state_4", Keys!$B:$C, 2, FALSE)),VLOOKUP("lignite_label", Keys!$B:$C, 2, FALSE),VLOOKUP("hard_coal_label", Keys!$B:$C, 2, FALSE)) -> hard_coal
A20: 2024 | B20: 103548 | C20: Camp Cherry Austin | D20: Alabama | E20: Tuscaloosa | F20: Active | G20: Surface | H20: Independent Producer Operator | I20: Mine only | J20: Southland Resources, Inc. | K20: P.O. Box 770, Cottondale, AL 35453 | M20: Appalachia Southern | N20: 103949 | O20: 8 | P20: 23512 | Q20: =IFERROR(LEFT(D20, FIND(VLOOKUP("state_name_split_token", Keys!$B:$C, 2, FALSE), D20)-1), D20) -> Alabama | R20: =IF(OR(Q20=VLOOKUP("lignite_state_1", Keys!$B:$C, 2, FALSE),Q20=VLOOKUP("lignite_state_2", Keys!$B:$C, 2, FALSE),Q20=VLOOKUP("lignite_state_3", Keys!$B:$C, 2, FALSE),Q20=VLOOKUP("lignite_state_4", Keys!$B:$C, 2, FALSE)),VLOOKUP("lignite_label", Keys!$B:$C, 2, FALSE),VLOOKUP("hard_coal_label", Keys!$B:$C, 2, FALSE)) -> hard_coal
A21: 2024 | B21: 103556 | C21: Eaton Resources Pit 1 | D21: Alabama | E21: Tuscaloosa | F21: Active | G21: Surface | H21: Independent Producer Operator | I21: Mine only | J21: Eaton Resources Llc | K21: 16241 B&l Road, Cottondale, AL 35453 | M21: Appalachia Southern | N21: 58531 | O21: 15 | P21: 30662 | Q21: =IFERROR(LEFT(D21, FIND(VLOOKUP("state_name_split_token", Keys!$B:$C, 2, FALSE), D21)-1), D21) -> Alabama | R21: =IF(OR(Q21=VLOOKUP("lignite_state_1", Keys!$B:$C, 2, FALSE),Q21=VLOOKUP("lignite_state_2", Keys!$B:$C, 2, FALSE),Q21=VLOOKUP("lignite_state_3", Keys!$B:$C, 2, FALSE),Q21=VLOOKUP("lignite_state_4", Keys!$B:$C, 2, FALSE)),VLOOKUP("lignite_label", Keys!$B:$C, 2, FALSE),VLOOKUP("hard_coal_label", Keys!$B:$C, 2, FALSE)) -> hard_coal
A22: 2024 | B22: 103559 | C22: Rockcastle Mine | D22: Alabama | E22: Tuscaloosa | F22: Active | G22: Surface | H22: Independent Producer Operator | I22: Mine only | J22: Cahaba Resouces, Llc | K22: P.O. Box 122, Vance, AL 35490 | M22: Appalachia Southern | N22: 72209 | O22: 18 | P22: 38747 | Q22: =IFERROR(LEFT(D22, FIND(VLOOKUP("state_name_split_token", Keys!$B:$C, 2, FALSE), D22)-1), D22) -> Alabama | R22: =IF(OR(Q22=VLOOKUP("lignite_state_1", Keys!$B:$C, 2, FALSE),Q22=VLOOKUP("lignite_state_2", Keys!$B:$C, 2, FALSE),Q22=VLOOKUP("lignite_state_3", Keys!$B:$C, 2, FALSE),Q22=VLOOKUP("lignite_state_4", Keys!$B:$C, 2, FALSE)),VLOOKUP("lignite_label", Keys!$B:$C, 2, FALSE),VLOOKUP("hard_coal_label", Keys!$B:$C, 2, FALSE)) -> hard_coal
A23: 2024 | B23: 103577 | C23: Kellerman | D23: Alabama | E23: Tuscaloosa | F23: Active | G23: Underground | H23: Independent Producer Operator | I23: Mine only | J23: Alaco Llc | K23: 414 Elder Grove Dr., Ewing, VA 24248 | M23: Appalachia Southern | N23: 92066 | O23: 23 | P23: 46833 | Q23: =IFERROR(LEFT(D23, FIND(VLOOKUP("state_name_split_token", Keys!$B:$C, 2, FALSE), D23)-1), D23) -> Alabama | R23: =IF(OR(Q23=VLOOKUP("lignite_state_1", Keys!$B:$C, 2, FALSE),Q23=VLOOKUP("lignite_state_2", Keys!$B:$C, 2, FALSE),Q23=VLOOKUP("lignite_state_3", Keys!$B:$C, 2, FALSE),Q23=VLOOKUP("lignite_state_4", Keys!$B:$C, 2, FALSE)),VLOOKUP("lignite_label", Keys!$B:$C, 2, FALSE),VLOOKUP("hard_coal_label", Keys!$B:$C, 2, FALSE)) -> hard_coal
A24: 2024 | B24: 102901 | C24: Shoal Creek Mine | D24: Alabama | E24: Walker | F24: Active | G24: Underground | H24: Operating Subsidiary | I24: Mine and Preparation Plant | J24: Peabody Southeast Mining, Llc | K24: P.O. Box 327, Oakman, AL 35579 | L24: United Mine Workers Of America | M24: Appalachia Southern | N24: 2102725 | O24: 393 | P24: 1136153 | Q24: =IFERROR(LEFT(D24, FIND(VLOOKUP("state_name_split_token", Keys!$B:$C, 2, FALSE), D24)-1), D24) -> Alabama | R24: =IF(OR(Q24=VLOOKUP("lignite_state_1", Keys!$B:$C, 2, FALSE),Q24=VLOOKUP("lignite_state_2", Keys!$B:$C, 2, FALSE),Q24=VLOOKUP("lignite_state_3", Keys!$B:$C, 2, FALSE),Q24=VLOOKUP("lignite_state_4", Keys!$B:$C, 2, FALSE)),VLOOKUP("lignite_label", Keys!$B:$C, 2, FALSE),VLOOKUP("hard_coal_label", Keys!$B:$C, 2, FALSE)) -> hard_coal
A25: 2024 | B25: 103155 | C25: Corinth Prep Plant | D25: Alabama | E25: Walker | F25: Active | G25: Underground | H25: Independent Producer Operator | I25: Preparation Plant | J25: Prospect Mining & Development | K25: 1799 Elliott Blvd, Jasper, AL 35501 | M25: Appalachia Southern | N25: 0 | O25: 12 | P25: 31140 | Q25: =IFERROR(LEFT(D25, FIND(VLOOKUP("state_name_split_token", Keys!$B:$C, 2, FALSE), D25)-1), D25) -> Alabama | R25: =IF(OR(Q25=VLOOKUP("lignite_state_1", Keys!$B:$C, 2, FALSE),Q25=VLOOKUP("lignite_state_2", Keys!$B:$C, 2, FALSE),Q25=VLOOKUP("lignite_state_3", Keys!$B:$C, 2, FALSE),Q25=VLOOKUP("lignite_state_4", Keys!$B:$C, 2, FALSE)),VLOOKUP("lignite_label", Keys!$B:$C, 2, FALSE),VLOOKUP("hard_coal_label", Keys!$B:$C, 2, FALSE)) -> hard_coal
A26: 2024 | B26: 103389 | C26: Carbon Hill Mine | D26: Alabama | E26: Walker | F26: Active | G26: Underground | H26: Independent Producer Operator | I26: Mine only | J26: Clas Coal Company Inc. | K26: P.O. Box 400, Carbon Hill, AL 35549 | M26: Appalachia Southern | N26: 120633 | O26: 30 | P26: 68118 | Q26: =IFERROR(LEFT(D26, FIND(VLOOKUP("state_name_split_token", Keys!$B:$C, 2, FALSE), D26)-1), D26) -> Alabama | R26: =IF(OR(Q26=VLOOKUP("lignite_state_1", Keys!$B:$C, 2, FALSE),Q26=VLOOKUP("lignite_state_2", Keys!$B:$C, 2, FALSE),Q26=VLOOKUP("lignite_state_3", Keys!$B:$C, 2, FALSE),Q26=VLOOKUP("lignite_state_4", Keys!$B:$C, 2, FALSE)),VLOOKUP("lignite_label", Keys!$B:$C, 2, FALSE),VLOOKUP("hard_coal_label", Keys!$B:$C, 2, FALSE)) -> hard_coal
A27: 2024 | B27: 103426 | C27: Carbon Hill Prep Plant | D27: Alabama | E27: Walker | F27: Active | G27: Underground | H27: Independent Producer Operator | I27: Preparation Plant | J27: Prospect Mining & Development | K27: 218 Highway 195, Jasper, AL 35503 | M27: Appalachia Southern | N27: 0 | O27: 9 | P27: 23578 | Q27: =IFERROR(LEFT(D27, FIND(VLOOKUP("state_name_split_token", Keys!$B:$C, 2, FALSE), D27)-1), D27) -> Alabama | R27: =IF(OR(Q27=VLOOKUP("lignite_state_1", Keys!$B:$C, 2, FALSE),Q27=VLOOKUP("lignite_state_2", Keys!$B:$C, 2, FALSE),Q27=VLOOKUP("lignite_state_3", Keys!$B:$C, 2, FALSE),Q27=VLOOKUP("lignite_state_4", Keys!$B:$C, 2, FALSE)),VLOOKUP("lignite_label", Keys!$B:$C, 2, FALSE),VLOOKUP("hard_coal_label", Keys!$B:$C, 2, FALSE)) -> hard_coal
A28: 2024 | B28: 103456 | C28: No. 5 Mine | D28: Alabama | E28: Walker | F28: Active | G28: Surface | H28: Independent Producer Operator | I28: Mine only | J28: Highland Energy, Inc | K28: 7802 Highway 78, Cordova, AL 35550 | M28: Appalachia Southern | N28: 120122 | O28: 16 | P28: 41374 | Q28: =IFERROR(LEFT(D28, FIND(VLOOKUP("state_name_split_token", Keys!$B:$C, 2, FALSE), D28)-1), D28) -> Alabama | R28: =IF(OR(Q28=VLOOKUP("lignite_state_1", Keys!$B:$C, 2, FALSE),Q28=VLOOKUP("lignite_state_2", Keys!$B:$C, 2, FALSE),Q28=VLOOKUP("lignite_state_3", Keys!$B:$C, 2, FALSE),Q28=VLOOKUP("lignite_state_4", Keys!$B:$C, 2, FALSE)),VLOOKUP("lignite_label", Keys!$B:$C, 2, FALSE),VLOOKUP("hard_coal_label", Keys!$B:$C, 2, FALSE)) -> hard_coal
A29: 2024 | B29: 103497 | C29: Gooden Creek Ii | D29: Alabama | E29: Walker | F29: Active | G29: Surface | H29: Independent Producer Operator | I29: Mine only | J29: Kennedy Brothers Construction, | K29: P.O. Box 1608, Jasper, AL 35502 | M29: Appalachia Southern | N29: 3283 | O29: 2 | P29: 1897 | Q29: =IFERROR(LEFT(D29, FIND(VLOOKUP("state_name_split_token", Keys!$B:$C, 2, FALSE), D29)-1), D29) -> Alabama | R29: =IF(OR(Q29=VLOOKUP("lignite_state_1", Keys!$B:$C, 2, FALSE),Q29=VLOOKUP("lignite_state_2", Keys!$B:$C, 2, FALSE),Q29=VLOOKUP("lignite_state_3", Keys!$B:$C, 2, FALSE),Q29=VLOOKUP("lignite_state_4", Keys!$B:$C, 2, FALSE)),VLOOKUP("lignite_label", Keys!$B:$C, 2, FALSE),VLOOKUP("hard_coal_label", Keys!$B:$C, 2, FALSE)) -> hard_coal
A30: 2024 | B30: 5000030 | C30: Usibelli | D30: Alaska | E30: Denali | F30: Active | G30: Surface | H30: Independent Producer Operator | I30: Mine and Preparation Plant | J30: Usibelli Coal Mine Inc | K30: P.O. Box 1000, Healy, AK 99743 | L30: International Brotherhood Of Teamsters, Chauffeurs, Warehouse | M30: Western | N30: 1003565 | O30: 105 | P30: 202813 | Q30: =IFERROR(LEFT(D30, FIND(VLOOKUP("state_name_split_token", Keys!$B:$C, 2, FALSE), D30)-1), D30) -> Alaska | R30: =IF(OR(Q30=VLOOKUP("lignite_state_1", Keys!$B:$C, 2, FALSE),Q30=VLOOKUP("lignite_state_2", Keys!$B:$C, 2, FALSE),Q30=VLOOKUP("lignite_state_3", Keys!$B:$C, 2, FALSE),Q30=VLOOKUP("lignite_state_4", Keys!$B:$C, 2, FALSE)),VLOOKUP("lignite_label", Keys!$B:$C, 2, FALSE),VLOOKUP("hard_coal_label", Keys!$B:$C, 2, FALSE)) -> hard_coal
A31: 2024 | B31: 503672 | C31: West Elk Mine | D31: Colorado | E31: Gunnison | F31: Active | G31: Underground | H31: Operating Subsidiary | I31: Mine and Preparation Plant | J31: Mountain Coal Company, L.L.C. | K31: 5174 Highway 133, Somerset, CO 81434 | M31: Uinta Region | N31: 3705019 | O31: 323 | P31: 652830 | Q31: =IFERROR(LEFT(D31, FIND(VLOOKUP("state_name_split_token", Keys!$B:$C, 2, FALSE), D31)-1), D31) -> Colorado | R31: =IF(OR(Q31=VLOOKUP("lignite_state_1", Keys!$B:$C, 2, FALSE),Q31=VLOOKUP("lignite_state_2", Keys!$B:$C, 2, FALSE),Q31=VLOOKUP("lignite_state_3", Keys!$B:$C, 2, FALSE),Q31=VLOOKUP("lignite_state_4", Keys!$B:$C, 2, FALSE)),VLOOKUP("lignite_label", Keys!$B:$C, 2, FALSE),VLOOKUP("hard_coal_label", Keys!$B:$C, 2, FALSE)) -> hard_coal
A32: 2024 | B32: 504864 | C32: King Ii | D32: Colorado | E32: La Plata | F32: Active | G32: Underground | H32: Independent Producer Operator | I32: Mine only | J32: Gcc Energy Llc | K32: 6473 County Road 120, Hesperus, CO 81326 | M32: Western | N32: 582342 | O32: 104 | P32: 167632 | Q32: =IFERROR(LEFT(D32, FIND(VLOOKUP("state_name_split_token", Keys!$B:$C, 2, FALSE), D32)-1), D32) -> Colorado | R32: =IF(OR(Q32=VLOOKUP("lignite_state_1", Keys!$B:$C, 2, FALSE),Q32=VLOOKUP("lignite_state_2", Keys!$B:$C, 2, FALSE),Q32=VLOOKUP("lignite_state_3", Keys!$B:$C, 2, FALSE),Q32=VLOOKUP("lignite_state_4", Keys!$B:$C, 2, FALSE)),VLOOKUP("lignite_label", Keys!$B:$C, 2, FALSE),VLOOKUP("hard_coal_label", Keys!$B:$C, 2, FALSE)) -> hard_coal
A33: 2024 | B33: 502838 | C33: Trapper Mine | D33: Colorado | E33: Moffat | F33: Active | G33: Surface | H33: Independent Producer Operator | I33: Mine only | J33: Trapper Mining Inc | K33: P.O. Box 187, Craig, CO 81626 | L33: International Union Of Operation Engineers | M33: Uinta Region | N33: 1521960 | O33: 134 | P33: 286955 | Q33: =IFERROR(LEFT(D33, FIND(VLOOKUP("state_name_split_token", Keys!$B:$C, 2, FALSE), D33)-1), D33) -> Colorado | R33: =IF(OR(Q33=VLOOKUP("lignite_state_1", Keys!$B:$C, 2, FALSE),Q33=VLOOKUP("lignite_state_2", Keys!$B:$C, 2, FALSE),Q33=VLOOKUP("lignite_state_3", Keys!$B:$C, 2, FALSE),Q33=VLOOKUP("lignite_state_4", Keys!$B:$C, 2, FALSE)),VLOOKUP("lignite_label", Keys!$B:$C, 2, FALSE),VLOOKUP("hard_coal_label", Keys!$B:$C, 2, FALSE)) -> hard_coal
A34: 2024 | B34: 502962 | C34: Colowyo Mine | D34: Colorado | E34: Moffat | F34: Active | G34: Surface | H34: Operating Subsidiary | I34: Mine and Preparation Plant | J34: Colowyo Coal Company L P | K34: 5731 State Highway 13, Meeker, CO 81625 | M34: Uinta Region | N34: 1713919 | O34: 184 | P34: 305379 | Q34: =IFERROR(LEFT(D34, FIND(VLOOKUP("state_name_split_token", Keys!$B:$C, 2, FALSE), D34)-1), D34) -> Colorado | R34: =IF(OR(Q34=VLOOKUP("lignite_state_1", Keys!$B:$C, 2, FALSE),Q34=VLOOKUP("lignite_state_2", Keys!$B:$C, 2, FALSE),Q34=VLOOKUP("lignite_state_3", Keys!$B:$C, 2, FALSE),Q34=VLOOKUP("lignite_state_4", Keys!$B:$C, 2, FALSE)),VLOOKUP("lignite_label", Keys!$B:$C, 2, FALSE),VLOOKUP("hard_coal_label", Keys!$B:$C, 2, FALSE)) -> hard_coal
A35: 2024 | B35: 1202445 | C35: Addcar System 40 Hwm Serial No | D35: Colorado | E35: Moffat | F35: Active | G35: Surface | H35: Independent Producer Operator | I35: Mine only | J35: Mega Highwall Mining Llc | K35: 12081 Virginia Blvd., Ashland, KY 40112 | M35: Uinta Region | N35: 479996 | O35: 17 | P35: 44973 | Q35: =IFERROR(LEFT(D35, FIND(VLOOKUP("state_name_split_token", Keys!$B:$C, 2, FALSE), D35)-1), D35) -> Colorado | R35: =IF(OR(Q35=VLOOKUP("lignite_state_1", Keys!$B:$C, 2, FALSE),Q35=VLOOKUP("lignite_state_2", Keys!$B:$C, 2, FALSE),Q35=VLOOKUP("lignite_state_3", Keys!$B:$C, 2, FALSE),Q35=VLOOKUP("lignite_state_4", Keys!$B:$C, 2, FALSE)),VLOOKUP("lignite_label", Keys!$B:$C, 2, FALSE),VLOOKUP("hard_coal_label", Keys!$B:$C, 2, FALSE)) -> hard_coal
A36: 2024 | B36: 4003376 | C36: Addcar System 16 | D36: Colorado | E36: Moffat | F36: Active | G36: Surface | H36: Independent Producer Operator | I36: Mine only | J36: Mega Highwall Mining Llc | K36: 12081 Va. Blvd, Ashland, KY 41102 | M36: Uinta Region | N36: 1485020 | O36: 22 | P36: 56069 | Q36: =IFERROR(LEFT(D36, FIND(VLOOKUP("state_name_split_token", Keys!$B:$C, 2, FALSE), D36)-1), D36) -> Colorado | R36: =IF(OR(Q36=VLOOKUP("lignite_state_1", Keys!$B:$C, 2, FALSE),Q36=VLOOKUP("lignite_state_2", Keys!$B:$C, 2, FALSE),Q36=VLOOKUP("lignite_state_3", Keys!$B:$C, 2, FALSE),Q36=VLOOKUP("lignite_state_4", Keys!$B:$C, 2, FALSE)),VLOOKUP("lignite_label", Keys!$B:$C, 2, FALSE),VLOOKUP("hard_coal_label", Keys!$B:$C, 2, FALSE)) -> hard_coal
A37: 2024 | B37: 503505 | C37: Deserado Mine | D37: Colorado | E37: Rio Blanco | F37: Active | G37: Underground | H37: Operating Subsidiary | I37: Mine and Preparation Plant | J37: Blue Mountain Energy Inc | K37: 3607 County Road #65, Rangely, CO 81648 | L37: United Mine Workers Of America | M37: Uinta Region | N37: 1907363 | O37: 167 | P37: 318930 | Q37: =IFERROR(LEFT(D37, FIND(VLOOKUP("state_name_split_token", Keys!$B:$C, 2, FALSE), D37)-1), D37) -> Colorado | R37: =IF(OR(Q37=VLOOKUP("lignite_state_1", Keys!$B:$C, 2, FALSE),Q37=VLOOKUP("lignite_state_2", Keys!$B:$C, 2, FALSE),Q37=VLOOKUP("lignite_state_3", Keys!$B:$C, 2, FALSE),Q37=VLOOKUP("lignite_state_4", Keys!$B:$C, 2, FALSE)),VLOOKUP("lignite_label", Keys!$B:$C, 2, FALSE),VLOOKUP("hard_coal_label", Keys!$B:$C, 2, FALSE)) -> hard_coal
A38: 2024 | B38: 503836 | C38: Foidel Creek Mine | D38: Colorado | E38: Routt | F38: Active | G38: Underground | H38: Operating Subsidiary | I38: Mine and Preparation Plant | J38: Peabody Twentymile Mining Llc | K38: 29515 Routt Cnty Rd#27, Oak Creek, CO 80467 | M38: Uinta Region | N38: 995706 | O38: 215 | P38: 618434 | Q38: =IFERROR(LEFT(D38, FIND(VLOOKUP("state_name_split_token", Keys!$B:$C, 2, FALSE), D38)-1), D38) -> Colorado | R38: =IF(OR(Q38=VLOOKUP("lignite_state_1", Keys!$B:$C, 2, FALSE),Q38=VLOOKUP("lignite_state_2", Keys!$B:$C, 2, FALSE),Q38=VLOOKUP("lignite_state_3", Keys!$B:$C, 2, FALSE),Q38=VLOOKUP("lignite_state_4", Keys!$B:$C, 2, FALSE)),VLOOKUP("lignite_label", Keys!$B:$C, 2, FALSE),VLOOKUP("hard_coal_label", Keys!$B:$C, 2, FALSE)) -> hard_coal
A39: 2024 | B39: 1103189 | C39: Mc#1 Mine | D39: Illinois | E39: Franklin | F39: Active | G39: Underground | H39: Independent Producer Operator | I39: Mine and Preparation Plant | J39: M-Class Mining Llc | K39: 11351 N. Thompsonville Rd., Macedonia, IL 62860 | M39: Illinois Basin | N39: 6216015 | O39: 276 | P39: 636906 | Q39: =IFERROR(LEFT(D39, FIND(VLOOKUP("state_name_split_token", Keys!$B:$C, 2, FALSE), D39)-1), D39) -> Illinois | R39: =IF(OR(Q39=VLOOKUP("lignite_state_1", Keys!$B:$C, 2, FALSE),Q39=VLOOKUP("lignite_state_2", Keys!$B:$C, 2, FALSE),Q39=VLOOKUP("lignite_state_3", Keys!$B:$C, 2, FALSE),Q39=VLOOKUP("lignite_state_4", Keys!$B:$C, 2, FALSE)),VLOOKUP("lignite_label", Keys!$B:$C, 2, FALSE),VLOOKUP("hard_coal_label", Keys!$B:$C, 2, FALSE)) -> hard_coal
A40: 2024 | B40: 1103203 | C40: Mine No. 1 | D40: Illinois | E40: Hamilton | F40: Active | G40: Underground | H40: Operating Subsidiary | I40: Mine only | J40: Hamilton County Coal, Llc | K40: 18033 County Road 500 East, Dahlgren, IL 62828 | M40: Illinois Basin | N40: 4773185 | O40: 373 | P40: 863129 | Q40: =IFERROR(LEFT(D40, FIND(VLOOKUP("state_name_split_token", Keys!$B:$C, 2, FALSE), D40)-1), D40) -> Illinois | R40: =IF(OR(Q40=VLOOKUP("lignite_state_1", Keys!$B:$C, 2, FALSE),Q40=VLOOKUP("lignite_state_2", Keys!$B:$C, 2, FALSE),Q40=VLOOKUP("lignite_state_3", Keys!$B:$C, 2, FALSE),Q40=VLOOKUP("lignite_state_4", Keys!$B:$C, 2, FALSE)),VLOOKUP("lignite_label", Keys!$B:$C, 2, FALSE),VLOOKUP("hard_coal_label", Keys!$B:$C, 2, FALSE)) -> hard_coal
A41: 2024 | B41: 1103242 | C41: Hamilton County Coal Processin | D41: Illinois | E41: Hamilton | F41: Active | G41: Underground | H41: Independent Producer Operator | I41: Preparation Plant | J41: Hamilton County Coal, Llc | K41: 18031 County Rd 500 East, Dahlgren, IL 62828 | M41: Illinois Basin | N41: 0 | O41: 41 | P41: 86195 | Q41: =IFERROR(LEFT(D41, FIND(VLOOKUP("state_name_split_token", Keys!$B:$C, 2, FALSE), D41)-1), D41) -> Illinois | R41: =IF(OR(Q41=VLOOKUP("lignite_state_1", Keys!$B:$C, 2, FALSE),Q41=VLOOKUP("lignite_state_2", Keys!$B:$C, 2, FALSE),Q41=VLOOKUP("lignite_state_3", Keys!$B:$C, 2, FALSE),Q41=VLOOKUP("lignite_state_4", Keys!$B:$C, 2, FALSE)),VLOOKUP("lignite_label", Keys!$B:$C, 2, FALSE),VLOOKUP("hard_coal_label", Keys!$B:$C, 2, FALSE)) -> hard_coal
A42: 2024 | B42: 1103182 | C42: Deer Run Mine | D42: Illinois | E42: Montgomery | F42: Active | G42: Underground | H42: Operating Subsidiary | I42: Mine and Preparation Plant | J42: Patton Mining Llc | K42: P.O. Box 457, Hillsboro, IL 62049 | M42: Illinois Basin | N42: 2817637 | O42: 187 | P42: 381478 | Q42: =IFERROR(LEFT(D42, FIND(VLOOKUP("state_name_split_token", Keys!$B:$C, 2, FALSE), D42)-1), D42) -> Illinois | R42: =IF(OR(Q42=VLOOKUP("lignite_state_1", Keys!$B:$C, 2, FALSE),Q42=VLOOKUP("lignite_state_2", Keys!$B:$C, 2, FALSE),Q42=VLOOKUP("lignite_state_3", Keys!$B:$C, 2, FALSE),Q42=VLOOKUP("lignite_state_4", Keys!$B:$C, 2, FALSE)),VLOOKUP("lignite_label", Keys!$B:$C, 2, FALSE),VLOOKUP("hard_coal_label", Keys!$B:$C, 2, FALSE)) -> hard_coal
A43: 2024 | B43: 1103045 | C43: Red Hawk | D43: Illinois | E43: Perry | F43: Active, men working, not producing | G43: Surface | H43: Operating Subsidiary | I43: Preparation Plant | J43: Knight Hawk Coal, Llc | K43: 500 Cutler-Trico Road, Percy, IL 62272 | M43: Illinois Basin | N43: 0 | O43: 2 | P43: 7171 | Q43: =IFERROR(LEFT(D43, FIND(VLOOKUP("state_name_split_token", Keys!$B:$C, 2, FALSE), D43)-1), D43) -> Illinois | R43: =IF(OR(Q43=VLOOKUP("lignite_state_1", Keys!$B:$C, 2, FALSE),Q43=VLOOKUP("lignite_state_2", Keys!$B:$C, 2, FALSE),Q43=VLOOKUP("lignite_state_3", Keys!$B:$C, 2, FALSE),Q43=VLOOKUP("lignite_state_4", Keys!$B:$C, 2, FALSE)),VLOOKUP("lignite_label", Keys!$B:$C, 2, FALSE),VLOOKUP("hard_coal_label", Keys!$B:$C, 2, FALSE)) -> hard_coal
A44: 2024 | B44: 1103143 | C44: Prairie Eagle | D44: Illinois | E44: Perry | F44: Active | G44: Surface | H44: Operating Subsidiary | I44: Preparation Plant | J44: Knight Hawk Coal, Llc | K44: 500 Cutler-Trico Road, Percy, IL 62272 | M44: Illinois Basin | N44: 0 | O44: 2 | P44: 5199 | Q44: =IFERROR(LEFT(D44, FIND(VLOOKUP("state_name_split_token", Keys!$B:$C, 2, FALSE), D44)-1), D44) -> Illinois | R44: =IF(OR(Q44=VLOOKUP("lignite_state_1", Keys!$B:$C, 2, FALSE),Q44=VLOOKUP("lignite_state_2", Keys!$B:$C, 2, FALSE),Q44=VLOOKUP("lignite_state_3", Keys!$B:$C, 2, FALSE),Q44=VLOOKUP("lignite_state_4", Keys!$B:$C, 2, FALSE)),VLOOKUP("lignite_label", Keys!$B:$C, 2, FALSE),VLOOKUP("hard_coal_label", Keys!$B:$C, 2, FALSE)) -> hard_coal
A45: 2024 | B45: 1103143 | C45: Prairie Eagle | D45: Illinois | E45: Perry | F45: Active | G45: Underground | H45: Operating Subsidiary | I45: Preparation Plant | J45: Knight Hawk Coal, Llc | K45: 500 Cutler-Trico Road, Percy, IL 62272 | M45: Illinois Basin | N45: 0 | O45: 41 | P45: 98782 | Q45: =IFERROR(LEFT(D45, FIND(VLOOKUP("state_name_split_token", Keys!$B:$C, 2, FALSE), D45)-1), D45) -> Illinois | R45: =IF(OR(Q45=VLOOKUP("lignite_state_1", Keys!$B:$C, 2, FALSE),Q45=VLOOKUP("lignite_state_2", Keys!$B:$C, 2, FALSE),Q45=VLOOKUP("lignite_state_3", Keys!$B:$C, 2, FALSE),Q45=VLOOKUP("lignite_state_4", Keys!$B:$C, 2, FALSE)),VLOOKUP("lignite_label", Keys!$B:$C, 2, FALSE),VLOOKUP("hard_coal_label", Keys!$B:$C, 2, FALSE)) -> hard_coal
A46: 2024 | B46: 1103147 | C46: Prairie Eagle-Underground | D46: Illinois | E46: Perry | F46: Active | G46: Underground | H46: Operating Subsidiary | I46: Mine only | J46: Knight Hawk Coal, Llc | K46: 500 Cutler-Trico Rd, Percy, IL 62272 | M46: Illinois Basin | N46: 4113552 | O46: 298 | P46: 605487 | Q46: =IFERROR(LEFT(D46, FIND(VLOOKUP("state_name_split_token", Keys!$B:$C, 2, FALSE), D46)-1), D46) -> Illinois | R46: =IF(OR(Q46=VLOOKUP("lignite_state_1", Keys!$B:$C, 2, FALSE),Q46=VLOOKUP("lignite_state_2", Keys!$B:$C, 2, FALSE),Q46=VLOOKUP("lignite_state_3", Keys!$B:$C, 2, FALSE),Q46=VLOOKUP("lignite_state_4", Keys!$B:$C, 2, FALSE)),VLOOKUP("lignite_label", Keys!$B:$C, 2, FALSE),VLOOKUP("hard_coal_label", Keys!$B:$C, 2, FALSE)) -> hard_coal
A47: 2024 | B47: 1103274 | C47: Golden Eagle Mine | D47: Illinois | E47: Perry | F47: Active, men working, not producing | G47: Surface | H47: Operating Subsidiary | I47: Mine only | J47: Knight Hawk Coal, Llc | K47: 500 Cutler/Trico Road, Percy, IL 62272 | M47: Illinois Basin | N47: 496104 | O47: 27 | P47: 59221 | Q47: =IFERROR(LEFT(D47, FIND(VLOOKUP("state_name_split_token", Keys!$B:$C, 2, FALSE), D47)-1), D47) -> Illinois | R47: =IF(OR(Q47=VLOOKUP("lignite_state_1", Keys!$B:$C, 2, FALSE),Q47=VLOOKUP("lignite_state_2", Keys!$B:$C, 2, FALSE),Q47=VLOOKUP("lignite_state_3", Keys!$B:$C, 2, FALSE),Q47=VLOOKUP("lignite_state_4", Keys!$B:$C, 2, FALSE)),VLOOKUP("lignite_label", Keys!$B:$C, 2, FALSE),VLOOKUP("hard_coal_label", Keys!$B:$C, 2, FALSE)) -> hard_coal
A48: 2024 | B48: 1102546 | C48: Preparation Plant | D48: Illinois | E48: Randolph | F48: Active | G48: Underground | H48: Independent Producer Operator | I48: Preparation Plant | J48: Peabody Midwest Mining, Llc | K48: P.O. Box 397, Coulterville, IL 62237 | M48: Illinois Basin | N48: 0 | O48: 34 | P48: 66471 | Q48: =IFERROR(LEFT(D48, FIND(VLOOKUP("state_name_split_token", Keys!$B:$C, 2, FALSE), D48)-1), D48) -> Illinois | R48: =IF(OR(Q48=VLOOKUP("lignite_state_1", Keys!$B:$C, 2, FALSE),Q48=VLOOKUP("lignite_state_2", Keys!$B:$C, 2, FALSE),Q48=VLOOKUP("lignite_state_3", Keys!$B:$C, 2, FALSE),Q48=VLOOKUP("lignite_state_4", Keys!$B:$C, 2, FALSE)),VLOOKUP("lignite_label", Keys!$B:$C, 2, FALSE),VLOOKUP("hard_coal_label", Keys!$B:$C, 2, FALSE)) -> hard_coal
A49: 2024 | B49: 1103235 | C49: Gateway North Mine | D49: Illinois | E49: Randolph | F49: Active | G49: Underground | H49: Operating Subsidiary | I49: Mine only | J49: Peabody Gateway North Mining, | K49: 12968 State Route 13, Coulterville, IL 62237 | M49: Illinois Basin | N49: 2132415 | O49: 180 | P49: 360915 | Q49: =IFERROR(LEFT(D49, FIND(VLOOKUP("state_name_split_token", Keys!$B:$C, 2, FALSE), D49)-1), D49) -> Illinois | R49: =IF(OR(Q49=VLOOKUP("lignite_state_1", Keys!$B:$C, 2, FALSE),Q49=VLOOKUP("lignite_state_2", Keys!$B:$C, 2, FALSE),Q49=VLOOKUP("lignite_state_3", Keys!$B:$C, 2, FALSE),Q49=VLOOKUP("lignite_state_4", Keys!$B:$C, 2, FALSE)),VLOOKUP("lignite_label", Keys!$B:$C, 2, FALSE),VLOOKUP("hard_coal_label", Keys!$B:$C, 2, FALSE)) -> hard_coal
... A232: 2024 | B232: 2302262 | C232: Walnut Creek | D232: Missouri | E232: Bates | F232: Active | G232: Surface | H232: Independent Producer Operator | I232: Mine only | J232: Continental Coal Inc | K232: 10801 Main, Suite 920, Overland Park, KS 66210 | M232: Interior | N232: 147314 | O232: 8 | P232: 16226 | Q232: =IFERROR(LEFT(D232, FIND(VLOOKUP("state_name_split_token", Keys!$B:$C, 2, FALSE), D232)-1), D232) -> Missouri | R232: =IF(OR(Q232=VLOOKUP("lignite_state_1", Keys!$B:$C, 2, FALSE),Q232=VLOOKUP("lignite_state_2", Keys!$B:$C, 2, FALSE),Q232=VLOOKUP("lignite_state_3", Keys!$B:$C, 2, FALSE),Q232=VLOOKUP("lignite_state_4", Keys!$B:$C, 2, FALSE)),VLOOKUP("lignite_label", Keys!$B:$C, 2, FALSE),VLOOKUP("hard_coal_label", Keys!$B:$C, 2, FALSE)) -> hard_coal
A233: 2024 | B233: 2400910 | C233: Absaloka Mine | D233: Montana | E233: Big Horn | F233: Active | G233: Surface | H233: Operating Subsidiary | I233: Mine and Preparation Plant | J233: Westmoreland Absaloka Mining L | K233: P.O. Box 449, Hardin, MT 59034 | L233: International Union Of Operation Engineers | M233: Powder River Basin | N233: 883576 | O233: 68 | P233: 126319 | Q233: =IFERROR(LEFT(D233, FIND(VLOOKUP("state_name_split_token", Keys!$B:$C, 2, FALSE), D233)-1), D233) -> Montana | R233: =IF(OR(Q233=VLOOKUP("lignite_state_1", Keys!$B:$C, 2, FALSE),Q233=VLOOKUP("lignite_state_2", Keys!$B:$C, 2, FALSE),Q233=VLOOKUP("lignite_state_3", Keys!$B:$C, 2, FALSE),Q233=VLOOKUP("lignite_state_4", Keys!$B:$C, 2, FALSE)),VLOOKUP("lignite_label", Keys!$B:$C, 2, FALSE),VLOOKUP("hard_coal_label", Keys!$B:$C, 2, FALSE)) -> hard_coal
A234: 2024 | B234: 2401457 | C234: Spring Creek Mine | D234: Montana | E234: Big Horn | F234: Active | G234: Surface | H234: Operating Subsidiary | I234: Mine only | J234: Navajo Transitional Energy Com | K234: P.O. Box 67, Decker, MT 59025 | M234: Powder River Basin | N234: 13053955 | O234: 265 | P234: 535544 | Q234: =IFERROR(LEFT(D234, FIND(VLOOKUP("state_name_split_token", Keys!$B:$C, 2, FALSE), D234)-1), D234) -> Montana | R234: =IF(OR(Q234=VLOOKUP("lignite_state_1", Keys!$B:$C, 2, FALSE),Q234=VLOOKUP("lignite_state_2", Keys!$B:$C, 2, FALSE),Q234=VLOOKUP("lignite_state_3", Keys!$B:$C, 2, FALSE),Q234=VLOOKUP("lignite_state_4", Keys!$B:$C, 2, FALSE)),VLOOKUP("lignite_label", Keys!$B:$C, 2, FALSE),VLOOKUP("hard_coal_label", Keys!$B:$C, 2, FALSE)) -> hard_coal
A235: 2024 | B235: 2402703 | C235: Wolf Mountain Coal-Spring Cree | D235: Montana | E235: Big Horn | F235: Active | G235: Surface | H235: Independent Producer Operator | I235: Preparation Plant | J235: Wolf Mountain Coal, Inc. | K235: P.O. Box 6206, Sheridan, WY 82801 | M235: Powder River Basin | N235: 0 | O235: 11 | P235: 15544 | Q235: =IFERROR(LEFT(D235, FIND(VLOOKUP("state_name_split_token", Keys!$B:$C, 2, FALSE), D235)-1), D235) -> Montana | R235: =IF(OR(Q235=VLOOKUP("lignite_state_1", Keys!$B:$C, 2, FALSE),Q235=VLOOKUP("lignite_state_2", Keys!$B:$C, 2, FALSE),Q235=VLOOKUP("lignite_state_3", Keys!$B:$C, 2, FALSE),Q235=VLOOKUP("lignite_state_4", Keys!$B:$C, 2, FALSE)),VLOOKUP("lignite_label", Keys!$B:$C, 2, FALSE),VLOOKUP("hard_coal_label", Keys!$B:$C, 2, FALSE)) -> hard_coal
A236: 2024 | B236: 2401950 | C236: Bull Mountains Mine No 1 | D236: Montana | E236: Musselshell | F236: Active | G236: Underground | H236: Operating Subsidiary | I236: Mine and Preparation Plant | J236: Signal Peak Energy Llc | K236: 100 Portal Dr, Roundup, MT 59072 | M236: Western | N236: 7067888 | O236: 263 | P236: 558445 | Q236: =IFERROR(LEFT(D236, FIND(VLOOKUP("state_name_split_token", Keys!$B:$C, 2, FALSE), D236)-1), D236) -> Montana | R236: =IF(OR(Q236=VLOOKUP("lignite_state_1", Keys!$B:$C, 2, FALSE),Q236=VLOOKUP("lignite_state_2", Keys!$B:$C, 2, FALSE),Q236=VLOOKUP("lignite_state_3", Keys!$B:$C, 2, FALSE),Q236=VLOOKUP("lignite_state_4", Keys!$B:$C, 2, FALSE)),VLOOKUP("lignite_label", Keys!$B:$C, 2, FALSE),VLOOKUP("hard_coal_label", Keys!$B:$C, 2, FALSE)) -> hard_coal
A237: 2024 | B237: 2401747 | C237: Rosebud Mine & Crusher/Conveyo | D237: Montana | E237: Rosebud | F237: Active | G237: Surface | H237: Operating Subsidiary | I237: Mine and Preparation Plant | J237: Westmoreland Rosebud Mining Ll | K237: P.O. Box 99, Colstrip, MT 59323 | L237: International Union Of Operation Engineers | M237: Powder River Basin | N237: 5978039 | O237: 317 | P237: 595110 | Q237: =IFERROR(LEFT(D237, FIND(VLOOKUP("state_name_split_token", Keys!$B:$C, 2, FALSE), D237)-1), D237) -> Montana | R237: =IF(OR(Q237=VLOOKUP("lignite_state_1", Keys!$B:$C, 2, FALSE),Q237=VLOOKUP("lignite_state_2", Keys!$B:$C, 2, FALSE),Q237=VLOOKUP("lignite_state_3", Keys!$B:$C, 2, FALSE),Q237=VLOOKUP("lignite_state_4", Keys!$B:$C, 2, FALSE)),VLOOKUP("lignite_label", Keys!$B:$C, 2, FALSE),VLOOKUP("hard_coal_label", Keys!$B:$C, 2, FALSE)) -> hard_coal
A238: 2024 | B238: 2901879 | C238: Lee Ranch Coal Mine | D238: New Mexico | E238: Mckinley | F238: Active | G238: Surface | H238: Independent Producer Operator | I238: Mine and Preparation Plant | J238: Peabody Natural Resources Comp | K238: P.O. Box 757, Grants, NM 87020 | M238: Western | N238: 1410492 | O238: 143 | P238: 273705 | Q238: =IFERROR(LEFT(D238, FIND(VLOOKUP("state_name_split_token", Keys!$B:$C, 2, FALSE), D238)-1), D238) -> New Mexico | R238: =IF(OR(Q238=VLOOKUP("lignite_state_1", Keys!$B:$C, 2, FALSE),Q238=VLOOKUP("lignite_state_2", Keys!$B:$C, 2, FALSE),Q238=VLOOKUP("lignite_state_3", Keys!$B:$C, 2, FALSE),Q238=VLOOKUP("lignite_state_4", Keys!$B:$C, 2, FALSE)),VLOOKUP("lignite_label", Keys!$B:$C, 2, FALSE),VLOOKUP("hard_coal_label", Keys!$B:$C, 2, FALSE)) -> hard_coal
A239: 2024 | B239: 2902257 | C239: El Segundo | D239: New Mexico | E239: Mckinley | F239: Active | G239: Surface | H239: Operating Subsidiary | I239: Mine and Preparation Plant | J239: El Segundo Coal Company, Llc | K239: P.O. Box 757, Grants, NM 87020 | M239: Western | N239: 1028982 | O239: 97 | P239: 194769 | Q239: =IFERROR(LEFT(D239, FIND(VLOOKUP("state_name_split_token", Keys!$B:$C, 2, FALSE), D239)-1), D239) -> New Mexico | R239: =IF(OR(Q239=VLOOKUP("lignite_state_1", Keys!$B:$C, 2, FALSE),Q239=VLOOKUP("lignite_state_2", Keys!$B:$C, 2, FALSE),Q239=VLOOKUP("lignite_state_3", Keys!$B:$C, 2, FALSE),Q239=VLOOKUP("lignite_state_4", Keys!$B:$C, 2, FALSE)),VLOOKUP("lignite_label", Keys!$B:$C, 2, FALSE),VLOOKUP("hard_coal_label", Keys!$B:$C, 2, FALSE)) -> hard_coal
A240: 2024 | B240: 2900097 | C240: Navajo Mine | D240: New Mexico | E240: San Juan | F240: Active | G240: Surface | H240: Operating Subsidiary | I240: Mine only | J240: Bisti Fuels Company Llc | K240: P.O. Box 3767, Farmington, NM 87499 | L240: International Union Of Operation Engineers | M240: Western | N240: 4759297 | O240: 345 | P240: 665360 | Q240: =IFERROR(LEFT(D240, FIND(VLOOKUP("state_name_split_token", Keys!$B:$C, 2, FALSE), D240)-1), D240) -> New Mexico | R240: =IF(OR(Q240=VLOOKUP("lignite_state_1", Keys!$B:$C, 2, FALSE),Q240=VLOOKUP("lignite_state_2", Keys!$B:$C, 2, FALSE),Q240=VLOOKUP("lignite_state_3", Keys!$B:$C, 2, FALSE),Q240=VLOOKUP("lignite_state_4", Keys!$B:$C, 2, FALSE)),VLOOKUP("lignite_label", Keys!$B:$C, 2, FALSE),VLOOKUP("hard_coal_label", Keys!$B:$C, 2, FALSE)) -> hard_coal
A241: 2024 | B241: 3200491 | C241: Falkirk Mine | D241: North Dakota | E241: Mclean | F241: Active | G241: Surface | H241: Operating Subsidiary | I241: Mine only | J241: Falkirk Mining Company | K241: P.O. Box 1087, Underwood, ND 58576 | M241: Western | N241: 7400184 | O241: 441 | P241: 856489 | Q241: =IFERROR(LEFT(D241, FIND(VLOOKUP("state_name_split_token", Keys!$B:$C, 2, FALSE), D241)-1), D241) -> North Dakota | R241: =IF(OR(Q241=VLOOKUP("lignite_state_1", Keys!$B:$C, 2, FALSE),Q241=VLOOKUP("lignite_state_2", Keys!$B:$C, 2, FALSE),Q241=VLOOKUP("lignite_state_3", Keys!$B:$C, 2, FALSE),Q241=VLOOKUP("lignite_state_4", Keys!$B:$C, 2, FALSE)),VLOOKUP("lignite_label", Keys!$B:$C, 2, FALSE),VLOOKUP("hard_coal_label", Keys!$B:$C, 2, FALSE)) -> lignite
A242: 2024 | B242: 3200595 | C242: Freedom Mine | D242: North Dakota | E242: Mercer | F242: Active | G242: Surface | H242: Operating Subsidiary | I242: Mine only | J242: The Coteau Properties Company | K242: 204 61 Ave. Sw, Beulah, ND 58523 | M242: Western | N242: 11860169 | O242: 471 | P242: 948236 | Q242: =IFERROR(LEFT(D242, FIND(VLOOKUP("state_name_split_token", Keys!$B:$C, 2, FALSE), D242)-1), D242) -> North Dakota | R242: =IF(OR(Q242=VLOOKUP("lignite_state_1", Keys!$B:$C, 2, FALSE),Q242=VLOOKUP("lignite_state_2", Keys!$B:$C, 2, FALSE),Q242=VLOOKUP("lignite_state_3", Keys!$B:$C, 2, FALSE),Q242=VLOOKUP("lignite_state_4", Keys!$B:$C, 2, FALSE)),VLOOKUP("lignite_label", Keys!$B:$C, 2, FALSE),VLOOKUP("hard_coal_label", Keys!$B:$C, 2, FALSE)) -> lignite
A243: 2024 | B243: 3201028 | C243: Coyote Creek Mine | D243: North Dakota | E243: Mercer | F243: Active | G243: Surface | H243: Operating Subsidiary | I243: Mine only | J243: Coyote Creek Mining Company, L | K243: 6502 17th St Sw, Zap, ND 58580 | M243: Western | N243: 1913979 | O243: 114 | P243: 216550 | Q243: =IFERROR(LEFT(D243, FIND(VLOOKUP("state_name_split_token", Keys!$B:$C, 2, FALSE), D243)-1), D243) -> North Dakota | R243: =IF(OR(Q243=VLOOKUP("lignite_state_1", Keys!$B:$C, 2, FALSE),Q243=VLOOKUP("lignite_state_2", Keys!$B:$C, 2, FALSE),Q243=VLOOKUP("lignite_state_3", Keys!$B:$C, 2, FALSE),Q243=VLOOKUP("lignite_state_4", Keys!$B:$C, 2, FALSE)),VLOOKUP("lignite_label", Keys!$B:$C, 2, FALSE),VLOOKUP("hard_coal_label", Keys!$B:$C, 2, FALSE)) -> lignite
A244: 2024 | B244: 3200218 | C244: Center Mine | D244: North Dakota | E244: Oliver | F244: Active | G244: Surface | H244: Operating Subsidiary | I244: Mine only | J244: Bni Coal, Ltd | K244: 2360 35th Ave Sw, Center, ND 58530 | L244: International Brotherhood Of Electrical Workers | M244: Western | N244: 4240336 | O244: 174 | P244: 326080 | Q244: =IFERROR(LEFT(D244, FIND(VLOOKUP("state_name_split_token", Keys!$B:$C, 2, FALSE), D244)-1), D244) -> North Dakota | R244: =IF(OR(Q244=VLOOKUP("lignite_state_1", Keys!$B:$C, 2, FALSE),Q244=VLOOKUP("lignite_state_2", Keys!$B:$C, 2, FALSE),Q244=VLOOKUP("lignite_state_3", Keys!$B:$C, 2, FALSE),Q244=VLOOKUP("lignite_state_4", Keys!$B:$C, 2, FALSE)),VLOOKUP("lignite_label", Keys!$B:$C, 2, FALSE),VLOOKUP("hard_coal_label", Keys!$B:$C, 2, FALSE)) -> lignite
A245: 2024 | B245: 3304637 | C245: Ccu Athens Strip | D245: Ohio | E245: Athens | F245: Active | G245: Surface | H245: Independent Producer Operator | I245: Mine only | J245: Ccu Coal & Construction Llc | K245: 544 Chestnut St. Pb Box 1027, Coshocton, OH 43812 | M245: Appalachia Northern | N245: 58839 | O245: 10 | P245: 19887 | Q245: =IFERROR(LEFT(D245, FIND(VLOOKUP("state_name_split_token", Keys!$B:$C, 2, FALSE), D245)-1), D245) -> Ohio | R245: =IF(OR(Q245=VLOOKUP("lignite_state_1", Keys!$B:$C, 2, FALSE),Q245=VLOOKUP("lignite_state_2", Keys!$B:$C, 2, FALSE),Q245=VLOOKUP("lignite_state_3", Keys!$B:$C, 2, FALSE),Q245=VLOOKUP("lignite_state_4", Keys!$B:$C, 2, FALSE)),VLOOKUP("lignite_label", Keys!$B:$C, 2, FALSE),VLOOKUP("hard_coal_label", Keys!$B:$C, 2, FALSE)) -> hard_coal
A246: 2024 | B246: 3300965 | C246: Ccu Belmont Strip | D246: Ohio | E246: Belmont | F246: Active | G246: Surface | H246: Operating Subsidiary | I246: Mine only | J246: Ccu Coal And Construction Llc | K246: 544 Chestnut St, Coshocton, OH 43812 | M246: Appalachia Northern | N246: 343374 | O246: 67 | P246: 147239 | Q246: =IFERROR(LEFT(D246, FIND(VLOOKUP("state_name_split_token", Keys!$B:$C, 2, FALSE), D246)-1), D246) -> Ohio | R246: =IF(OR(Q246=VLOOKUP("lignite_state_1", Keys!$B:$C, 2, FALSE),Q246=VLOOKUP("lignite_state_2", Keys!$B:$C, 2, FALSE),Q246=VLOOKUP("lignite_state_3", Keys!$B:$C, 2, FALSE),Q246=VLOOKUP("lignite_state_4", Keys!$B:$C, 2, FALSE)),VLOOKUP("lignite_label", Keys!$B:$C, 2, FALSE),VLOOKUP("hard_coal_label", Keys!$B:$C, 2, FALSE)) -> hard_coal
A247: 2024 | B247: 3302937 | C247: Ccu Bellaire Dock | D247: Ohio | E247: Belmont | F247: Active | G247: Surface | H247: Operating Subsidiary | I247: Preparation Plant | J247: Ccu Coal And Construction Llc | K247: 544 Chestnut St., Coshocton, OH 43812 | M247: Appalachia Northern | N247: 0 | O247: 4 | P247: 7952 | Q247: =IFERROR(LEFT(D247, FIND(VLOOKUP("state_name_split_token", Keys!$B:$C, 2, FALSE), D247)-1), D247) -> Ohio | R247: =IF(OR(Q247=VLOOKUP("lignite_state_1", Keys!$B:$C, 2, FALSE),Q247=VLOOKUP("lignite_state_2", Keys!$B:$C, 2, FALSE),Q247=VLOOKUP("lignite_state_3", Keys!$B:$C, 2, FALSE),Q247=VLOOKUP("lignite_state_4", Keys!$B:$C, 2, FALSE)),VLOOKUP("lignite_label", Keys!$B:$C, 2, FALSE),VLOOKUP("hard_coal_label", Keys!$B:$C, 2, FALSE)) -> hard_coal
A248: 2024 | B248: 3302937 | C248: Ccu Bellaire Dock | D248: Ohio | E248: Belmont | F248: Active | G248: Underground | H248: Operating Subsidiary | I248: Preparation Plant | J248: Ccu Coal And Construction Llc | K248: 544 Chestnut St., Coshocton, OH 43812 | M248: Appalachia Northern | N248: 0 | O248: 3 | P248: 7952 | Q248: =IFERROR(LEFT(D248, FIND(VLOOKUP("state_name_split_token", Keys!$B:$C, 2, FALSE), D248)-1), D248) -> Ohio | R248: =IF(OR(Q248=VLOOKUP("lignite_state_1", Keys!$B:$C, 2, FALSE),Q248=VLOOKUP("lignite_state_2", Keys!$B:$C, 2, FALSE),Q248=VLOOKUP("lignite_state_3", Keys!$B:$C, 2, FALSE),Q248=VLOOKUP("lignite_state_4", Keys!$B:$C, 2, FALSE)),VLOOKUP("lignite_label", Keys!$B:$C, 2, FALSE),VLOOKUP("hard_coal_label", Keys!$B:$C, 2, FALSE)) -> hard_coal
A249: 2024 | B249: 3300968 | C249: Hopedale Mine | D249: Ohio | E249: Harrison | F249: Active | G249: Underground | H249: Operating Subsidiary | I249: Mine only | J249: Leesville Land Llc | K249: 86900 Sinfield Road, Hopedale, OH 43976 | M249: Appalachia Northern | N249: 219984 | O249: 69 | P249: 165102 | Q249: =IFERROR(LEFT(D249, FIND(VLOOKUP("state_name_split_token", Keys!$B:$C, 2, FALSE), D249)-1), D249) -> Ohio | R249: =IF(OR(Q249=VLOOKUP("lignite_state_1", Keys!$B:$C, 2, FALSE),Q249=VLOOKUP("lignite_state_2", Keys!$B:$C, 2, FALSE),Q249=VLOOKUP("lignite_state_3", Keys!$B:$C, 2, FALSE),Q249=VLOOKUP("lignite_state_4", Keys!$B:$C, 2, FALSE)),VLOOKUP("lignite_label", Keys!$B:$C, 2, FALSE),VLOOKUP("hard_coal_label", Keys!$B:$C, 2, FALSE)) -> hard_coal
A250: 2024 | B250: 3304187 | C250: Nelms Plant | D250: Ohio | E250: Harrison | F250: Active | G250: Underground | H250: Operating Subsidiary | I250: Preparation Plant | J250: Leesville Land Llc | K250: P.O. Box 415, Hopedale, OH 43976 | M250: Appalachia Northern | N250: 0 | O250: 9 | P250: 20422 | Q250: =IFERROR(LEFT(D250, FIND(VLOOKUP("state_name_split_token", Keys!$B:$C, 2, FALSE), D250)-1), D250) -> Ohio | R250: =IF(OR(Q250=VLOOKUP("lignite_state_1", Keys!$B:$C, 2, FALSE),Q250=VLOOKUP("lignite_state_2", Keys!$B:$C, 2, FALSE),Q250=VLOOKUP("lignite_state_3", Keys!$B:$C, 2, FALSE),Q250=VLOOKUP("lignite_state_4", Keys!$B:$C, 2, FALSE)),VLOOKUP("lignite_label", Keys!$B:$C, 2, FALSE),VLOOKUP("hard_coal_label", Keys!$B:$C, 2, FALSE)) -> hard_coal
A251: 2024 | B251: 3304414 | C251: Ccu Harrison Strip | D251: Ohio | E251: Harrison | F251: Permanently abandoned | G251: Surface | H251: Independent Producer Operator | I251: Mine only | J251: Ccu Coal And Construction Llc | K251: 544 Chestnut St., Coshocton, OH 43812 | M251: Appalachia Northern | N251: 27111 | O251: 9 | P251: 13094 | Q251: =IFERROR(LEFT(D251, FIND(VLOOKUP("state_name_split_token", Keys!$B:$C, 2, FALSE), D251)-1), D251) -> Ohio | R251: =IF(OR(Q251=VLOOKUP("lignite_state_1", Keys!$B:$C, 2, FALSE),Q251=VLOOKUP("lignite_state_2", Keys!$B:$C, 2, FALSE),Q251=VLOOKUP("lignite_state_3", Keys!$B:$C, 2, FALSE),Q251=VLOOKUP("lignite_state_4", Keys!$B:$C, 2, FALSE)),VLOOKUP("lignite_label", Keys!$B:$C, 2, FALSE),VLOOKUP("hard_coal_label", Keys!$B:$C, 2, FALSE)) -> hard_coal
A252: 2024 | B252: 3304484 | C252: Ccu Patterson Strip | D252: Ohio | E252: Harrison | F252: Permanently abandoned | G252: Surface | H252: Independent Producer Operator | I252: Mine only | J252: Ccu Coal And Construction Llc | K252: 3596 Sr 39 Nw, Dover, OH 44622 | M252: Appalachia Northern | N252: 900 | O252: 5 | P252: 6669 | Q252: =IFERROR(LEFT(D252, FIND(VLOOKUP("state_name_split_token", Keys!$B:$C, 2, FALSE), D252)-1), D252) -> Ohio | R252: =IF(OR(Q252=VLOOKUP("lignite_state_1", Keys!$B:$C, 2, FALSE),Q252=VLOOKUP("lignite_state_2", Keys!$B:$C, 2, FALSE),Q252=VLOOKUP("lignite_state_3", Keys!$B:$C, 2, FALSE),Q252=VLOOKUP("lignite_state_4", Keys!$B:$C, 2, FALSE)),VLOOKUP("lignite_label", Keys!$B:$C, 2, FALSE),VLOOKUP("hard_coal_label", Keys!$B:$C, 2, FALSE)) -> hard_coal
A253: 2024 | B253: 3304577 | C253: Ccu Sexton Strip | D253: Ohio | E253: Harrison | F253: Active | G253: Surface | H253: Operating Subsidiary | I253: Mine only | J253: Ccu Coal And Construction Llc | K253: 544 Chestnut St., Coshocton, OH 43812 | M253: Appalachia Northern | N253: 200420 | O253: 20 | P253: 41536 | Q253: =IFERROR(LEFT(D253, FIND(VLOOKUP("state_name_split_token", Keys!$B:$C, 2, FALSE), D253)-1), D253) -> Ohio | R253: =IF(OR(Q253=VLOOKUP("lignite_state_1", Keys!$B:$C, 2, FALSE),Q253=VLOOKUP("lignite_state_2", Keys!$B:$C, 2, FALSE),Q253=VLOOKUP("lignite_state_3", Keys!$B:$C, 2, FALSE),Q253=VLOOKUP("lignite_state_4", Keys!$B:$C, 2, FALSE)),VLOOKUP("lignite_label", Keys!$B:$C, 2, FALSE),VLOOKUP("hard_coal_label", Keys!$B:$C, 2, FALSE)) -> hard_coal
A254: 2024 | B254: 3304645 | C254: Vail Mine | D254: Ohio | E254: Harrison | F254: Active | G254: Underground | H254: Independent Producer Operator | I254: Mine only | J254: Rosebud Mining Company | K254: 28490 Birmingham Road, Freeport, OH 43973 | M254: Appalachia Northern | N254: 559753 | O254: 55 | P254: 114676 | Q254: =IFERROR(LEFT(D254, FIND(VLOOKUP("state_name_split_token", Keys!$B:$C, 2, FALSE), D254)-1), D254) -> Ohio | R254: =IF(OR(Q254=VLOOKUP("lignite_state_1", Keys!$B:$C, 2, FALSE),Q254=VLOOKUP("lignite_state_2", Keys!$B:$C, 2, FALSE),Q254=VLOOKUP("lignite_state_3", Keys!$B:$C, 2, FALSE),Q254=VLOOKUP("lignite_state_4", Keys!$B:$C, 2, FALSE)),VLOOKUP("lignite_label", Keys!$B:$C, 2, FALSE),VLOOKUP("hard_coal_label", Keys!$B:$C, 2, FALSE)) -> hard_coal
A255: 2024 | B255: 3301925 | C255: Orange Strip | D255: Ohio | E255: Noble | F255: Active | G255: Surface | H255: Independent Producer Operator | I255: Mine only | J255: B & N Coal Inc | K255: P.O. Box 100, Dexter City, OH 45727 | M255: Appalachia Northern | N255: 365626 | O255: 43 | P255: 111726 | Q255: =IFERROR(LEFT(D255, FIND(VLOOKUP("state_name_split_token", Keys!$B:$C, 2, FALSE), D255)-1), D255) -> Ohio | R255: =IF(OR(Q255=VLOOKUP("lignite_state_1", Keys!$B:$C, 2, FALSE),Q255=VLOOKUP("lignite_state_2", Keys!$B:$C, 2, FALSE),Q255=VLOOKUP("lignite_state_3", Keys!$B:$C, 2, FALSE),Q255=VLOOKUP("lignite_state_4", Keys!$B:$C, 2, FALSE)),VLOOKUP("lignite_label", Keys!$B:$C, 2, FALSE),VLOOKUP("hard_coal_label", Keys!$B:$C, 2, FALSE)) -> hard_coal
A256: 2024 | B256: 3303793 | C256: Stonecreek Mine | D256: Ohio | E256: Tuscarawas | F256: Active | G256: Surface | H256: Independent Producer Operator | I256: Preparation Plant | J256: Kimble Clay & Limestone | K256: 3596 St. Rt. 39 Nw, Dover, OH 44622 | M256: Appalachia Northern | N256: 0 | O256: 7 | P256: 14314 | Q256: =IFERROR(LEFT(D256, FIND(VLOOKUP("state_name_split_token", Keys!$B:$C, 2, FALSE), D256)-1), D256) -> Ohio | R256: =IF(OR(Q256=VLOOKUP("lignite_state_1", Keys!$B:$C, 2, FALSE),Q256=VLOOKUP("lignite_state_2", Keys!$B:$C, 2, FALSE),Q256=VLOOKUP("lignite_state_3", Keys!$B:$C, 2, FALSE),Q256=VLOOKUP("lignite_state_4", Keys!$B:$C, 2, FALSE)),VLOOKUP("lignite_label", Keys!$B:$C, 2, FALSE),VLOOKUP("hard_coal_label", Keys!$B:$C, 2, FALSE)) -> hard_coal
... A295: 2024 | B295: 3610386 | C295: Dragon Mine | D295: Pennsylvania (Bituminous) | E295: Clearfield | F295: Active | G295: Surface | H295: Independent Producer Operator | I295: Mine only | J295: Coal Loaders Inc | K295: 210 East Main Street, Ligonier, PA 15658 | M295: Appalachia Northern | N295: 33641 | O295: 7 | P295: 16636 | Q295: =IFERROR(LEFT(D295, FIND(VLOOKUP("state_name_split_token", Keys!$B:$C, 2, FALSE), D295)-1), D295) -> Pennsylvania | R295: =IF(OR(Q295=VLOOKUP("lignite_state_1", Keys!$B:$C, 2, FALSE),Q295=VLOOKUP("lignite_state_2", Keys!$B:$C, 2, FALSE),Q295=VLOOKUP("lignite_state_3", Keys!$B:$C, 2, FALSE),Q295=VLOOKUP("lignite_state_4", Keys!$B:$C, 2, FALSE)),VLOOKUP("lignite_label", Keys!$B:$C, 2, FALSE),VLOOKUP("hard_coal_label", Keys!$B:$C, 2, FALSE)) -> hard_coal
A296: 2024 | B296: 3608780 | C296: Logan Surface Mine | D296: Pennsylvania (Anthracite) | E296: Columbia | F296: Active | G296: Surface | H296: Operating Subsidiary | I296: Mine only | J296: Blaschak Anthracite Corporatio | K296: Route 54, P.O. Box 12, Mahanoy City, PA 17948 | L296: United Mine Workers Of America | M296: Appalachia Northern | N296: 102268 | O296: 35 | P296: 74488 | Q296: =IFERROR(LEFT(D296, FIND(VLOOKUP("state_name_split_token", Keys!$B:$C, 2, FALSE), D296)-1), D296) -> Pennsylvania | R296: =IF(OR(Q296=VLOOKUP("lignite_state_1", Keys!$B:$C, 2, FALSE),Q296=VLOOKUP("lignite_state_2", Keys!$B:$C, 2, FALSE),Q296=VLOOKUP("lignite_state_3", Keys!$B:$C, 2, FALSE),Q296=VLOOKUP("lignite_state_4", Keys!$B:$C, 2, FALSE)),VLOOKUP("lignite_label", Keys!$B:$C, 2, FALSE),VLOOKUP("hard_coal_label", Keys!$B:$C, 2, FALSE)) -> hard_coal
A297: 2024 | B297: 3601919 | C297: Rausch Creek Coal Preparation | D297: Pennsylvania (Anthracite) | E297: Dauphin | F297: Active | G297: Surface | H297: Independent Producer Operator | I297: Preparation Plant | J297: Rausch Creek Coal Preparation | K297: P.O. Box 1, Wiconisco, PA 17097 | M297: Appalachia Northern | N297: 0 | O297: 4 | P297: 5723 | Q297: =IFERROR(LEFT(D297, FIND(VLOOKUP("state_name_split_token", Keys!$B:$C, 2, FALSE), D297)-1), D297) -> Pennsylvania | R297: =IF(OR(Q297=VLOOKUP("lignite_state_1", Keys!$B:$C, 2, FALSE),Q297=VLOOKUP("lignite_state_2", Keys!$B:$C, 2, FALSE),Q297=VLOOKUP("lignite_state_3", Keys!$B:$C, 2, FALSE),Q297=VLOOKUP("lignite_state_4", Keys!$B:$C, 2, FALSE)),VLOOKUP("lignite_label", Keys!$B:$C, 2, FALSE),VLOOKUP("hard_coal_label", Keys!$B:$C, 2, FALSE)) -> hard_coal
A298: 2024 | B298: 3601919 | C298: Rausch Creek Coal Preparation | D298: Pennsylvania (Anthracite) | E298: Dauphin | F298: Active | G298: Underground | H298: Independent Producer Operator | I298: Preparation Plant | J298: Rausch Creek Coal Preparation | K298: P.O. Box 1, Wiconisco, PA 17097 | M298: Appalachia Northern | N298: 0 | O298: 3 | P298: 5722 | Q298: =IFERROR(LEFT(D298, FIND(VLOOKUP("state_name_split_token", Keys!$B:$C, 2, FALSE), D298)-1), D298) -> Pennsylvania | R298: =IF(OR(Q298=VLOOKUP("lignite_state_1", Keys!$B:$C, 2, FALSE),Q298=VLOOKUP("lignite_state_2", Keys!$B:$C, 2, FALSE),Q298=VLOOKUP("lignite_state_3", Keys!$B:$C, 2, FALSE),Q298=VLOOKUP("lignite_state_4", Keys!$B:$C, 2, FALSE)),VLOOKUP("lignite_label", Keys!$B:$C, 2, FALSE),VLOOKUP("hard_coal_label", Keys!$B:$C, 2, FALSE)) -> hard_coal
A299: 2024 | B299: 3609435 | C299: Williamstown Mine #1 | D299: Pennsylvania (Anthracite) | E299: Dauphin | F299: Active | G299: Underground | H299: Independent Producer Operator | I299: Mine only | J299: Kimmel's Mining, Inc | K299: 17rr East Grand Avenue, Tower City, PA 17980 | M299: Appalachia Northern | N299: 10024 | O299: 8 | P299: 15280 | Q299: =IFERROR(LEFT(D299, FIND(VLOOKUP("state_name_split_token", Keys!$B:$C, 2, FALSE), D299)-1), D299) -> Pennsylvania | R299: =IF(OR(Q299=VLOOKUP("lignite_state_1", Keys!$B:$C, 2, FALSE),Q299=VLOOKUP("lignite_state_2", Keys!$B:$C, 2, FALSE),Q299=VLOOKUP("lignite_state_3", Keys!$B:$C, 2, FALSE),Q299=VLOOKUP("lignite_state_4", Keys!$B:$C, 2, FALSE)),VLOOKUP("lignite_label", Keys!$B:$C, 2, FALSE),VLOOKUP("hard_coal_label", Keys!$B:$C, 2, FALSE)) -> hard_coal
A300: 2024 | B300: 3609826 | C300: T & B Strip | D300: Pennsylvania (Bituminous) | E300: Fayette | F300: Active | G300: Surface | H300: Independent Producer Operator | I300: Mine only | J300: T & B Excavating Inc. | K300: P.O. Box 337, Mcclellandtow, PA 15458 | M300: Appalachia Northern | N300: 11747 | O300: 2 | P300: 2788 | Q300: =IFERROR(LEFT(D300, FIND(VLOOKUP("state_name_split_token", Keys!$B:$C, 2, FALSE), D300)-1), D300) -> Pennsylvania | R300: =IF(OR(Q300=VLOOKUP("lignite_state_1", Keys!$B:$C, 2, FALSE),Q300=VLOOKUP("lignite_state_2", Keys!$B:$C, 2, FALSE),Q300=VLOOKUP("lignite_state_3", Keys!$B:$C, 2, FALSE),Q300=VLOOKUP("lignite_state_4", Keys!$B:$C, 2, FALSE)),VLOOKUP("lignite_label", Keys!$B:$C, 2, FALSE),VLOOKUP("hard_coal_label", Keys!$B:$C, 2, FALSE)) -> hard_coal
A301: 2024 | B301: 3609923 | C301: Tasara Strips | D301: Pennsylvania (Bituminous) | E301: Fulton | F301: Active | G301: Surface | H301: Independent Producer Operator | I301: Mine only | J301: J & J Svonavec Excavating, Inc | K301: 110 Windermere Lane, Somerset, PA 15501 | M301: Appalachia Northern | N301: 23017 | O301: 9 | P301: 13722 | Q301: =IFERROR(LEFT(D301, FIND(VLOOKUP("state_name_split_token", Keys!$B:$C, 2, FALSE), D301)-1), D301) -> Pennsylvania | R301: =IF(OR(Q301=VLOOKUP("lignite_state_1", Keys!$B:$C, 2, FALSE),Q301=VLOOKUP("lignite_state_2", Keys!$B:$C, 2, FALSE),Q301=VLOOKUP("lignite_state_3", Keys!$B:$C, 2, FALSE),Q301=VLOOKUP("lignite_state_4", Keys!$B:$C, 2, FALSE)),VLOOKUP("lignite_label", Keys!$B:$C, 2, FALSE),VLOOKUP("hard_coal_label", Keys!$B:$C, 2, FALSE)) -> hard_coal
A302: 2024 | B302: 3605018 | C302: Cumberland Mine | D302: Pennsylvania (Bituminous) | E302: Greene | F302: Active | G302: Underground | H302: Operating Subsidiary | I302: Mine and Preparation Plant | J302: Iron Cumberland Llc | K302: 576 Maple Run Road, Waynesburg, PA 15370 | L302: United Mine Workers Of America | M302: Appalachia Northern | N302: 5153309 | O302: 689 | P302: 1452404 | Q302: =IFERROR(LEFT(D302, FIND(VLOOKUP("state_name_split_token", Keys!$B:$C, 2, FALSE), D302)-1), D302) -> Pennsylvania | R302: =IF(OR(Q302=VLOOKUP("lignite_state_1", Keys!$B:$C, 2, FALSE),Q302=VLOOKUP("lignite_state_2", Keys!$B:$C, 2, FALSE),Q302=VLOOKUP("lignite_state_3", Keys!$B:$C, 2, FALSE),Q302=VLOOKUP("lignite_state_4", Keys!$B:$C, 2, FALSE)),VLOOKUP("lignite_label", Keys!$B:$C, 2, FALSE),VLOOKUP("hard_coal_label", Keys!$B:$C, 2, FALSE)) -> hard_coal
A303: 2024 | B303: 3607230 | C303: Bailey Mine | D303: Pennsylvania (Bituminous) | E303: Greene | F303: Active | G303: Underground | H303: Operating Subsidiary | I303: Mine and Preparation Plant | J303: Consol Pennsylvania Coal Compa | K303: 1000 Consol Energy Drive, Canonsburg, PA 15317 | M303: Appalachia Northern | N303: 10761880 | O303: 759 | P303: 1692764 | Q303: =IFERROR(LEFT(D303, FIND(VLOOKUP("state_name_split_token", Keys!$B:$C, 2, FALSE), D303)-1), D303) -> Pennsylvania | R303: =IF(OR(Q303=VLOOKUP("lignite_state_1", Keys!$B:$C, 2, FALSE),Q303=VLOOKUP("lignite_state_2", Keys!$B:$C, 2, FALSE),Q303=VLOOKUP("lignite_state_3", Keys!$B:$C, 2, FALSE),Q303=VLOOKUP("lignite_state_4", Keys!$B:$C, 2, FALSE)),VLOOKUP("lignite_label", Keys!$B:$C, 2, FALSE),VLOOKUP("hard_coal_label", Keys!$B:$C, 2, FALSE)) -> hard_coal
A304: 2024 | B304: 3610045 | C304: Harvey Mine | D304: Pennsylvania (Bituminous) | E304: Greene | F304: Active | G304: Underground | H304: Operating Subsidiary | I304: Mine only | J304: Consol Pennsylvania Coal Compa | K304: 1000 Consol Energy Drive, Canonsburg, PA 15317 | M304: Appalachia Northern | N304: 5743707 | O304: 326 | P304: 693086 | Q304: =IFERROR(LEFT(D304, FIND(VLOOKUP("state_name_split_token", Keys!$B:$C, 2, FALSE), D304)-1), D304) -> Pennsylvania | R304: =IF(OR(Q304=VLOOKUP("lignite_state_1", Keys!$B:$C, 2, FALSE),Q304=VLOOKUP("lignite_state_2", Keys!$B:$C, 2, FALSE),Q304=VLOOKUP("lignite_state_3", Keys!$B:$C, 2, FALSE),Q304=VLOOKUP("lignite_state_4", Keys!$B:$C, 2, FALSE)),VLOOKUP("lignite_label", Keys!$B:$C, 2, FALSE),VLOOKUP("hard_coal_label", Keys!$B:$C, 2, FALSE)) -> hard_coal
A305: 2024 | B305: 3601325 | C305: Beilchick Bros Strips | D305: Pennsylvania (Bituminous) | E305: Indiana | F305: Active | G305: Surface | H305: Independent Producer Operator | I305: Mine only | J305: Alverda Enterprises, Inc. | K305: 290 Staff Street Box 128, Heilwood, PA 15745 | M305: Appalachia Northern | N305: 2076 | O305: 1 | P305: 510 | Q305: =IFERROR(LEFT(D305, FIND(VLOOKUP("state_name_split_token", Keys!$B:$C, 2, FALSE), D305)-1), D305) -> Pennsylvania | R305: =IF(OR(Q305=VLOOKUP("lignite_state_1", Keys!$B:$C, 2, FALSE),Q305=VLOOKUP("lignite_state_2", Keys!$B:$C, 2, FALSE),Q305=VLOOKUP("lignite_state_3", Keys!$B:$C, 2, FALSE),Q305=VLOOKUP("lignite_state_4", Keys!$B:$C, 2, FALSE)),VLOOKUP("lignite_label", Keys!$B:$C, 2, FALSE),VLOOKUP("hard_coal_label", Keys!$B:$C, 2, FALSE)) -> hard_coal
A306: 2024 | B306: 3607688 | C306: Clymer Prep Plant | D306: Pennsylvania (Bituminous) | E306: Indiana | F306: Active | G306: Underground | H306: Independent Producer Operator | I306: Preparation Plant | J306: Rosebud Mining Company | K306: 301 Market Street, Kittanning, PA 16201 | M306: Appalachia Northern | N306: 0 | O306: 12 | P306: 25096 | Q306: =IFERROR(LEFT(D306, FIND(VLOOKUP("state_name_split_token", Keys!$B:$C, 2, FALSE), D306)-1), D306) -> Pennsylvania | R306: =IF(OR(Q306=VLOOKUP("lignite_state_1", Keys!$B:$C, 2, FALSE),Q306=VLOOKUP("lignite_state_2", Keys!$B:$C, 2, FALSE),Q306=VLOOKUP("lignite_state_3", Keys!$B:$C, 2, FALSE),Q306=VLOOKUP("lignite_state_4", Keys!$B:$C, 2, FALSE)),VLOOKUP("lignite_label", Keys!$B:$C, 2, FALSE),VLOOKUP("hard_coal_label", Keys!$B:$C, 2, FALSE)) -> hard_coal
A307: 2024 | B307: 3607880 | C307: Condor Mine | D307: Pennsylvania (Bituminous) | E307: Indiana | F307: Permanently abandoned | G307: Surface | H307: Independent Producer Operator | I307: Mine only | J307: Simkol Corp. | K307: 550 Beagle Road, Rockwood, PA 15557 | M307: Appalachia Northern | N307: 55888 | O307: 2 | P307: 2853 | Q307: =IFERROR(LEFT(D307, FIND(VLOOKUP("state_name_split_token", Keys!$B:$C, 2, FALSE), D307)-1), D307) -> Pennsylvania | R307: =IF(OR(Q307=VLOOKUP("lignite_state_1", Keys!$B:$C, 2, FALSE),Q307=VLOOKUP("lignite_state_2", Keys!$B:$C, 2, FALSE),Q307=VLOOKUP("lignite_state_3", Keys!$B:$C, 2, FALSE),Q307=VLOOKUP("lignite_state_4", Keys!$B:$C, 2, FALSE)),VLOOKUP("lignite_label", Keys!$B:$C, 2, FALSE),VLOOKUP("hard_coal_label", Keys!$B:$C, 2, FALSE)) -> hard_coal
A308: 2024 | B308: 3608316 | C308: Challenger Yard | D308: Pennsylvania (Bituminous) | E308: Indiana | F308: Active | G308: Surface | H308: Independent Producer Operator | I308: Preparation Plant | J308: Millcreek Processing | K308: Rt 711n, P.O. Box 435, Seward, PA 15954 | M308: Appalachia Northern | N308: 0 | O308: 8 | P308: 14573 | Q308: =IFERROR(LEFT(D308, FIND(VLOOKUP("state_name_split_token", Keys!$B:$C, 2, FALSE), D308)-1), D308) -> Pennsylvania | R308: =IF(OR(Q308=VLOOKUP("lignite_state_1", Keys!$B:$C, 2, FALSE),Q308=VLOOKUP("lignite_state_2", Keys!$B:$C, 2, FALSE),Q308=VLOOKUP("lignite_state_3", Keys!$B:$C, 2, FALSE),Q308=VLOOKUP("lignite_state_4", Keys!$B:$C, 2, FALSE)),VLOOKUP("lignite_label", Keys!$B:$C, 2, FALSE),VLOOKUP("hard_coal_label", Keys!$B:$C, 2, FALSE)) -> hard_coal
A309: 2024 | B309: 3609287 | C309: Lowry Mine | D309: Pennsylvania (Bituminous) | E309: Indiana | F309: Active | G309: Underground | H309: Independent Producer Operator | I309: Mine only | J309: Rosebud Mining Company | K309: 301 Market Street, Kittanning, PA 16201 | M309: Appalachia Northern | N309: 135717 | O309: 22 | P309: 50806 | Q309: =IFERROR(LEFT(D309, FIND(VLOOKUP("state_name_split_token", Keys!$B:$C, 2, FALSE), D309)-1), D309) -> Pennsylvania | R309: =IF(OR(Q309=VLOOKUP("lignite_state_1", Keys!$B:$C, 2, FALSE),Q309=VLOOKUP("lignite_state_2", Keys!$B:$C, 2, FALSE),Q309=VLOOKUP("lignite_state_3", Keys!$B:$C, 2, FALSE),Q309=VLOOKUP("lignite_state_4", Keys!$B:$C, 2, FALSE)),VLOOKUP("lignite_label", Keys!$B:$C, 2, FALSE),VLOOKUP("hard_coal_label", Keys!$B:$C, 2, FALSE)) -> hard_coal
A310: 2024 | B310: 3609342 | C310: Barrett Mine | D310: Pennsylvania (Bituminous) | E310: Indiana | F310: Active | G310: Underground | H310: Independent Producer Operator | I310: Mine only | J310: Rosebud Mining Company | K310: 301 Market Street, Kittanning, PA 16201 | M310: Appalachia Northern | N310: 282051 | O310: 39 | P310: 94077 | Q310: =IFERROR(LEFT(D310, FIND(VLOOKUP("state_name_split_token", Keys!$B:$C, 2, FALSE), D310)-1), D310) -> Pennsylvania | R310: =IF(OR(Q310=VLOOKUP("lignite_state_1", Keys!$B:$C, 2, FALSE),Q310=VLOOKUP("lignite_state_2", Keys!$B:$C, 2, FALSE),Q310=VLOOKUP("lignite_state_3", Keys!$B:$C, 2, FALSE),Q310=VLOOKUP("lignite_state_4", Keys!$B:$C, 2, FALSE)),VLOOKUP("lignite_label", Keys!$B:$C, 2, FALSE),VLOOKUP("hard_coal_label", Keys!$B:$C, 2, FALSE)) -> hard_coal
A311: 2024 | B311: 3609394 | C311: Knob Creek | D311: Pennsylvania (Bituminous) | E311: Indiana | F311: Active | G311: Underground | H311: Independent Producer Operator | I311: Mine only | J311: Rosebud Mining Company | K311: 301 Market Street, Kittanning, PA 16201 | M311: Appalachia Northern | N311: 101395 | O311: 25 | P311: 55410 | Q311: =IFERROR(LEFT(D311, FIND(VLOOKUP("state_name_split_token", Keys!$B:$C, 2, FALSE), D311)-1), D311) -> Pennsylvania | R311: =IF(OR(Q311=VLOOKUP("lignite_state_1", Keys!$B:$C, 2, FALSE),Q311=VLOOKUP("lignite_state_2", Keys!$B:$C, 2, FALSE),Q311=VLOOKUP("lignite_state_3", Keys!$B:$C, 2, FALSE),Q311=VLOOKUP("lignite_state_4", Keys!$B:$C, 2, FALSE)),VLOOKUP("lignite_label", Keys!$B:$C, 2, FALSE),VLOOKUP("hard_coal_label", Keys!$B:$C, 2, FALSE)) -> hard_coal
A312: 2024 | B312: 3609407 | C312: Heilwood | D312: Pennsylvania (Bituminous) | E312: Indiana | F312: Active | G312: Underground | H312: Independent Producer Operator | I312: Mine only | J312: Rosebud Mining Company | K312: 301 Market Street, Kittanning, PA 16201 | M312: Appalachia Northern | N312: 216146 | O312: 32 | P312: 64471 | Q312: =IFERROR(LEFT(D312, FIND(VLOOKUP("state_name_split_token", Keys!$B:$C, 2, FALSE), D312)-1), D312) -> Pennsylvania | R312: =IF(OR(Q312=VLOOKUP("lignite_state_1", Keys!$B:$C, 2, FALSE),Q312=VLOOKUP("lignite_state_2", Keys!$B:$C, 2, FALSE),Q312=VLOOKUP("lignite_state_3", Keys!$B:$C, 2, FALSE),Q312=VLOOKUP("lignite_state_4", Keys!$B:$C, 2, FALSE)),VLOOKUP("lignite_label", Keys!$B:$C, 2, FALSE),VLOOKUP("hard_coal_label", Keys!$B:$C, 2, FALSE)) -> hard_coal
A313: 2024 | B313: 3609437 | C313: Brush Valley | D313: Pennsylvania (Bituminous) | E313: Indiana | F313: Active | G313: Underground | H313: Independent Producer Operator | I313: Mine only | J313: Rosebud Mining Company | K313: 301 Market Street, Kittanning, PA 16201 | M313: Appalachia Northern | N313: 551303 | O313: 65 | P313: 153171 | Q313: =IFERROR(LEFT(D313, FIND(VLOOKUP("state_name_split_token", Keys!$B:$C, 2, FALSE), D313)-1), D313) -> Pennsylvania | R313: =IF(OR(Q313=VLOOKUP("lignite_state_1", Keys!$B:$C, 2, FALSE),Q313=VLOOKUP("lignite_state_2", Keys!$B:$C, 2, FALSE),Q313=VLOOKUP("lignite_state_3", Keys!$B:$C, 2, FALSE),Q313=VLOOKUP("lignite_state_4", Keys!$B:$C, 2, FALSE)),VLOOKUP("lignite_label", Keys!$B:$C, 2, FALSE),VLOOKUP("hard_coal_label", Keys!$B:$C, 2, FALSE)) -> hard_coal
A314: 2024 | B314: 3609595 | C314: Coral-Graceton | D314: Pennsylvania (Bituminous) | E314: Indiana | F314: Permanently abandoned | G314: Underground | H314: Independent Producer Operator | I314: Mine only | J314: Rosebud Mining Company | K314: 301 Market St, Kittanning, PA 16201 | M314: Appalachia Northern | N314: 5000 | O314: 5 | P314: 2987 | Q314: =IFERROR(LEFT(D314, FIND(VLOOKUP("state_name_split_token", Keys!$B:$C, 2, FALSE), D314)-1), D314) -> Pennsylvania | R314: =IF(OR(Q314=VLOOKUP("lignite_state_1", Keys!$B:$C, 2, FALSE),Q314=VLOOKUP("lignite_state_2", Keys!$B:$C, 2, FALSE),Q314=VLOOKUP("lignite_state_3", Keys!$B:$C, 2, FALSE),Q314=VLOOKUP("lignite_state_4", Keys!$B:$C, 2, FALSE)),VLOOKUP("lignite_label", Keys!$B:$C, 2, FALSE),VLOOKUP("hard_coal_label", Keys!$B:$C, 2, FALSE)) -> hard_coal
... A323: 2024 | B323: 3601734 | C323: Ebervale Mine | D323: Pennsylvania (Anthracite) | E323: Luzerne | F323: Active | G323: Surface | H323: Independent Producer Operator | I323: Mine only | J323: Atlantic Carbon Group, Inc. | K323: 100 Hazle Brook Road, Hazle Townshi, PA 18201 | M323: Appalachia Northern | N323: 113569 | O323: 8 | P323: 19670 | Q323: =IFERROR(LEFT(D323, FIND(VLOOKUP("state_name_split_token", Keys!$B:$C, 2, FALSE), D323)-1), D323) -> Pennsylvania | R323: =IF(OR(Q323=VLOOKUP("lignite_state_1", Keys!$B:$C, 2, FALSE),Q323=VLOOKUP("lignite_state_2", Keys!$B:$C, 2, FALSE),Q323=VLOOKUP("lignite_state_3", Keys!$B:$C, 2, FALSE),Q323=VLOOKUP("lignite_state_4", Keys!$B:$C, 2, FALSE)),VLOOKUP("lignite_label", Keys!$B:$C, 2, FALSE),VLOOKUP("hard_coal_label", Keys!$B:$C, 2, FALSE)) -> hard_coal
A324: 2024 | B324: 3604383 | C324: Lattimer Division | D324: Pennsylvania (Anthracite) | E324: Luzerne | F324: Active | G324: Surface | H324: Independent Producer Operator | I324: Mine and Preparation Plant | J324: Blaschak Anthracite Corporatio | K324: Route 54, P O Box 12, Mahanoy City, PA 17948 | L324: United Mine Workers Of America | M324: Appalachia Northern | N324: 8765 | O324: 15 | P324: 29103 | Q324: =IFERROR(LEFT(D324, FIND(VLOOKUP("state_name_split_token", Keys!$B:$C, 2, FALSE), D324)-1), D324) -> Pennsylvania | R324: =IF(OR(Q324=VLOOKUP("lignite_state_1", Keys!$B:$C, 2, FALSE),Q324=VLOOKUP("lignite_state_2", Keys!$B:$C, 2, FALSE),Q324=VLOOKUP("lignite_state_3", Keys!$B:$C, 2, FALSE),Q324=VLOOKUP("lignite_state_4", Keys!$B:$C, 2, FALSE)),VLOOKUP("lignite_label", Keys!$B:$C, 2, FALSE),VLOOKUP("hard_coal_label", Keys!$B:$C, 2, FALSE)) -> hard_coal
A325: 2024 | B325: 3605855 | C325: Laurel Breaker | D325: Pennsylvania (Anthracite) | E325: Luzerne | F325: Active | G325: Surface | H325: Independent Producer Operator | I325: Preparation Plant | J325: Carbon Sales, Inc. | K325: 350 Johnson St., Wilkes-Barre, PA 18702 | M325: Appalachia Northern | N325: 0 | O325: 9 | P325: 15836 | Q325: =IFERROR(LEFT(D325, FIND(VLOOKUP("state_name_split_token", Keys!$B:$C, 2, FALSE), D325)-1), D325) -> Pennsylvania | R325: =IF(OR(Q325=VLOOKUP("lignite_state_1", Keys!$B:$C, 2, FALSE),Q325=VLOOKUP("lignite_state_2", Keys!$B:$C, 2, FALSE),Q325=VLOOKUP("lignite_state_3", Keys!$B:$C, 2, FALSE),Q325=VLOOKUP("lignite_state_4", Keys!$B:$C, 2, FALSE)),VLOOKUP("lignite_label", Keys!$B:$C, 2, FALSE),VLOOKUP("hard_coal_label", Keys!$B:$C, 2, FALSE)) -> hard_coal
A326: 2024 | B326: 3608391 | C326: Glen Lyon Operation | D326: Pennsylvania (Anthracite) | E326: Luzerne | F326: Active | G326: Surface | H326: Independent Producer Operator | I326: Mine only | J326: Susquehanna Coal Company | K326: P.O. Box 85, Glen Lyon, PA 18617 | M326: Appalachia Northern | N326: 20996 | O326: 13 | P326: 26339 | Q326: =IFERROR(LEFT(D326, FIND(VLOOKUP("state_name_split_token", Keys!$B:$C, 2, FALSE), D326)-1), D326) -> Pennsylvania | R326: =IF(OR(Q326=VLOOKUP("lignite_state_1", Keys!$B:$C, 2, FALSE),Q326=VLOOKUP("lignite_state_2", Keys!$B:$C, 2, FALSE),Q326=VLOOKUP("lignite_state_3", Keys!$B:$C, 2, FALSE),Q326=VLOOKUP("lignite_state_4", Keys!$B:$C, 2, FALSE)),VLOOKUP("lignite_label", Keys!$B:$C, 2, FALSE),VLOOKUP("hard_coal_label", Keys!$B:$C, 2, FALSE)) -> hard_coal
A327: 2024 | B327: 3608550 | C327: Hazleton Shaft South | D327: Pennsylvania (Anthracite) | E327: Luzerne | F327: Active | G327: Surface | H327: Independent Producer Operator | I327: Mine only | J327: Atlantic Carbon Group, Inc. | K327: 100 Hazlebrook Road, P.O. Box, Hazleton, PA 18201 | M327: Appalachia Northern | N327: 191238 | O327: 42 | P327: 96604 | Q327: =IFERROR(LEFT(D327, FIND(VLOOKUP("state_name_split_token", Keys!$B:$C, 2, FALSE), D327)-1), D327) -> Pennsylvania | R327: =IF(OR(Q327=VLOOKUP("lignite_state_1", Keys!$B:$C, 2, FALSE),Q327=VLOOKUP("lignite_state_2", Keys!$B:$C, 2, FALSE),Q327=VLOOKUP("lignite_state_3", Keys!$B:$C, 2, FALSE),Q327=VLOOKUP("lignite_state_4", Keys!$B:$C, 2, FALSE)),VLOOKUP("lignite_label", Keys!$B:$C, 2, FALSE),VLOOKUP("hard_coal_label", Keys!$B:$C, 2, FALSE)) -> hard_coal
A328: 2024 | B328: 3608649 | C328: Jeddo No 8 Preparation Plant | D328: Pennsylvania (Anthracite) | E328: Luzerne | F328: Active | G328: Surface | H328: Operating Subsidiary | I328: Preparation Plant | J328: Wildcat Carbon Processing, Llc | K328: Route 940, Ebervale, PA 18223 | L328: United Mine Workers Of America | M328: Appalachia Northern | N328: 0 | O328: 18 | P328: 30872 | Q328: =IFERROR(LEFT(D328, FIND(VLOOKUP("state_name_split_token", Keys!$B:$C, 2, FALSE), D328)-1), D328) -> Pennsylvania | R328: =IF(OR(Q328=VLOOKUP("lignite_state_1", Keys!$B:$C, 2, FALSE),Q328=VLOOKUP("lignite_state_2", Keys!$B:$C, 2, FALSE),Q328=VLOOKUP("lignite_state_3", Keys!$B:$C, 2, FALSE),Q328=VLOOKUP("lignite_state_4", Keys!$B:$C, 2, FALSE)),VLOOKUP("lignite_label", Keys!$B:$C, 2, FALSE),VLOOKUP("hard_coal_label", Keys!$B:$C, 2, FALSE)) -> hard_coal
A329: 2024 | B329: 3608745 | C329: Stockton Mine | D329: Pennsylvania (Anthracite) | E329: Luzerne | F329: Active | G329: Surface | H329: Independent Producer Operator | I329: Mine only | J329: Atlantic Carbon Group, Inc. | K329: 100 Hazlebrook Road, P.O. Box, Hazleton, PA 18201 | M329: Appalachia Northern | N329: 38655 | O329: 39 | P329: 88564 | Q329: =IFERROR(LEFT(D329, FIND(VLOOKUP("state_name_split_token", Keys!$B:$C, 2, FALSE), D329)-1), D329) -> Pennsylvania | R329: =IF(OR(Q329=VLOOKUP("lignite_state_1", Keys!$B:$C, 2, FALSE),Q329=VLOOKUP("lignite_state_2", Keys!$B:$C, 2, FALSE),Q329=VLOOKUP("lignite_state_3", Keys!$B:$C, 2, FALSE),Q329=VLOOKUP("lignite_state_4", Keys!$B:$C, 2, FALSE)),VLOOKUP("lignite_label", Keys!$B:$C, 2, FALSE),VLOOKUP("hard_coal_label", Keys!$B:$C, 2, FALSE)) -> hard_coal
...

Sheet EIA923_Page1_coal_raw
A1: U.S. Department of Energy, The Energy Information Administration (EIA)
A2: EIA-923 Monthly Generation and Fuel Consumption Time Series File, 2024 Final Data
A3: Sources: EIA-923 and EIA-860 Reports
T5: Total Quantity Consumed In Physical Units (Consumed For Electric Generation And Useful Thermal Output) | AF5: Quantity Consumed In Physical Units For Electric Generation | AR5: Heat Content Of Fuels (MMBtu Per Unit) | BD5: Total Fuel Consumed (MMBtu) | BP5: Quantity Consumed For Electricity (MMBtu) | CB5: Electricity Net Generation (MWh) | CN5: Year-To-Date
A6: Plant Id | B6: Combined Heat And Power Plant | C6: Nuclear Unit Id | D6: Plant Name | E6: Operator Name | F6: Operator Id | G6: Plant State | H6: Census Region | I6: NERC Region | J6: Reserved | K6: NAICS Code | L6: EIA Sector Number | M6: Sector Name | N6: Reported Prime Mover | O6: Reported Fuel Type Code | P6: MER Fuel Type Code | Q6: Balancing Authority Code | R6: Respondent Frequency | S6: Physical Unit Label | T6: Quantity January | U6: Quantity February | V6: Quantity March | W6: Quantity April | X6: Quantity May | Y6: Quantity June | Z6: Quantity July | AA6: Quantity August | AB6: Quantity September | AC6: Quantity October | AD6: Quantity November | AE6: Quantity December | AF6: Elec_Quantity January | AG6: Elec_Quantity February | AH6: Elec_Quantity March | AI6: Elec_Quantity April | AJ6: Elec_Quantity May | AK6: Elec_Quantity June | AL6: Elec_Quantity July | AM6: Elec_Quantity August | AN6: Elec_Quantity September | AO6: Elec_Quantity October | AP6: Elec_Quantity November | AQ6: Elec_Quantity December | AR6: MMBtuPer_Unit January | AS6: MMBtuPer_Unit February | AT6: MMBtuPer_Unit March | AU6: MMBtuPer_Unit April | AV6: MMBtuPer_Unit May | AW6: MMBtuPer_Unit June | AX6: MMBtuPer_Unit July | AY6: MMBtuPer_Unit August | AZ6: MMBtuPer_Unit September | BA6: MMBtuPer_Unit October | BB6: MMBtuPer_Unit November | BC6: MMBtuPer_Unit December | BD6: Tot_MMBtu January | BE6: Tot_MMBtu February | BF6: Tot_MMBtu March | BG6: Tot_MMBtu April | BH6: Tot_MMBtu May | BI6: Tot_MMBtu June | BJ6: Tot_MMBtu July | BK6: Tot_MMBtu August | BL6: Tot_MMBtu September | BM6: Tot_MMBtu October | BN6: Tot_MMBtu November | BO6: Tot_MMBtu December | BP6: Elec_MMBtu January | BQ6: Elec_MMBtu February | BR6: Elec_MMBtu March | BS6: Elec_MMBtu April | BT6: Elec_MMBtu May | BU6: Elec_MMBtu June | BV6: Elec_MMBtu July | BW6: Elec_MMBtu August | BX6: Elec_MMBtu September | BY6: Elec_MMBtu October | BZ6: Elec_MMBtu November | CA6: Elec_MMBtu December | CB6: Netgen January | CC6: Netgen February | CD6: Netgen March | CE6: Netgen April | CF6: Netgen May | CG6: Netgen June | CH6: Netgen July | CI6: Netgen August | CJ6: Netgen September | CK6: Netgen October | CL6: Netgen November | CM6: Netgen December | CN6: Total Fuel Consumption Quantity | CO6: Electric Fuel Consumption Quantity | CP6: Total Fuel Consumption MMBtu | CQ6: Elec Fuel Consumption MMBtu | CR6: Net Generation (Megawatthours) | CS6: YEAR | CT6: helper: state_name | CU6: helper: rank
A7: 3 | B7: N | C7: . | D7: Barry | E7: Alabama Power Co | F7: 195 | G7: AL | H7: ESC | I7: SERC | K7: 22 | L7: 1 | M7: Electric Utility | N7: ST | O7: BIT | P7: COL | Q7: SOCO | R7: M | S7: short tons | T7: 44058 | U7: 0 | V7: 0 | W7: 47328 | X7: 0 | Y7: 44248 | Z7: 68612 | AA7: 0 | AB7: 15734 | AC7: 166757 | AD7: 8885 | AE7: 0 | AF7: 44058 | AG7: 0 | AH7: 0 | AI7: 47328 | AJ7: 0 | AK7: 44248 | AL7: 68612 | AM7: 0 | AN7: 15734 | AO7: 166757 | AP7: 8885 | AQ7: 0 | AR7: 19.908 | AS7: 0 | AT7: 0 | AU7: 19.908 | AV7: 0 | AW7: 19.908 | AX7: 19.908 | AY7: 0 | AZ7: 19.243 | BA7: 19.603 | BB7: 19.485 | BC7: 0 | BD7: 877107 | BE7: 0 | BF7: 0 | BG7: 942206 | BH7: 0 | BI7: 880889 | BJ7: 1365928 | BK7: 0 | BL7: 302769 | BM7: 3268937 | BN7: 173124 | BO7: 0 | BP7: 877107 | BQ7: 0 | BR7: 0 | BS7: 942206 | BT7: 0 | BU7: 880889 | BV7: 1365928 | BW7: 0 | BX7: 302769 | BY7: 3268937 | BZ7: 173124 | CA7: 0 | CB7: 74699.628 | CC7: -4538.357 | CD7: 0 | CE7: 83997.467 | CF7: 0 | CG7: 75098.285 | CH7: 114680.23 | CI7: 0 | CJ7: 20325.048 | CK7: 322168.46 | CL7: 11097.797 | CM7: 0 | CN7: 395622 | CO7: 395622 | CP7: 7810960 | CQ7: 7810960 | CR7: 697528.56 | CS7: 2024 | CT7: =IFERROR(INDEX(Geography!C:C, MATCH(G7, Geography!B:B, 0)), G7) -> Alabama | CU7: =IF(O7=VLOOKUP("eia923_lignite_fuel_code", Keys!$B:$C, 2, FALSE), VLOOKUP("lignite_label", Keys!$B:$C, 2, FALSE),VLOOKUP("hard_coal_label", Keys!$B:$C, 2, FALSE)) -> hard_coal
A8: 3 | B8: N | C8: . | D8: Barry | E8: Alabama Power Co | F8: 195 | G8: AL | H8: ESC | I8: SERC | K8: 22 | L8: 1 | M8: Electric Utility | N8: ST | O8: SUB | P8: COL | Q8: SOCO | R8: M | S8: short tons | T8: 0 | U8: 0 | V8: 0 | W8: 0 | X8: 0 | Y8: 0 | Z8: 0 | AA8: 0 | AB8: 0 | AC8: 0 | AD8: 0 | AE8: 0 | AF8: 0 | AG8: 0 | AH8: 0 | AI8: 0 | AJ8: 0 | AK8: 0 | AL8: 0 | AM8: 0 | AN8: 0 | AO8: 0 | AP8: 0 | AQ8: 0 | AR8: 0 | AS8: 0 | AT8: 0 | AU8: 0 | AV8: 0 | AW8: 0 | AX8: 0 | AY8: 0 | AZ8: 0 | BA8: 0 | BB8: 0 | BC8: 0 | BD8: 0 | BE8: 0 | BF8: 0 | BG8: 0 | BH8: 0 | BI8: 0 | BJ8: 0 | BK8: 0 | BL8: 0 | BM8: 0 | BN8: 0 | BO8: 0 | BP8: 0 | BQ8: 0 | BR8: 0 | BS8: 0 | BT8: 0 | BU8: 0 | BV8: 0 | BW8: 0 | BX8: 0 | BY8: 0 | BZ8: 0 | CA8: 0 | CB8: 0 | CC8: 0 | CD8: 0 | CE8: 0 | CF8: 0 | CG8: 0 | CH8: 0 | CI8: 0 | CJ8: 0 | CK8: 0 | CL8: 0 | CM8: 0 | CN8: 0 | CO8: 0 | CP8: 0 | CQ8: 0 | CR8: 0 | CS8: 2024 | CT8: =IFERROR(INDEX(Geography!C:C, MATCH(G8, Geography!B:B, 0)), G8) -> Alabama | CU8: =IF(O8=VLOOKUP("eia923_lignite_fuel_code", Keys!$B:$C, 2, FALSE), VLOOKUP("lignite_label", Keys!$B:$C, 2, FALSE),VLOOKUP("hard_coal_label", Keys!$B:$C, 2, FALSE)) -> hard_coal
A9: 26 | B9: N | C9: . | D9: E C Gaston | E9: Alabama Power Co | F9: 195 | G9: AL | H9: ESC | I9: SERC | K9: 22 | L9: 1 | M9: Electric Utility | N9: ST | O9: BIT | P9: COL | Q9: SOCO | R9: M | S9: short tons | T9: 80186 | U9: 61119 | V9: 117757 | W9: 0 | X9: 5875 | Y9: 165313 | Z9: 118868 | AA9: 180092 | AB9: 0 | AC9: 0 | AD9: 0 | AE9: 90857 | AF9: 80186 | AG9: 61119 | AH9: 117757 | AI9: 0 | AJ9: 5875 | AK9: 165313 | AL9: 118868 | AM9: 180092 | AN9: 0 | AO9: 0 | AP9: 0 | AQ9: 90857 | AR9: 22.416 | AS9: 23.586 | AT9: 23.817 | AU9: 0 | AV9: 23.994 | AW9: 24.036 | AX9: 24.14 | AY9: 24.009 | AZ9: 0 | BA9: 0 | BB9: 0 | BC9: 23.837 | BD9: 1797449 | BE9: 1441553 | BF9: 2804618 | BG9: 0 | BH9: 140965 | BI9: 3973463 | BJ9: 2869474 | BK9: 4323829 | BL9: 0 | BM9: 0 | BN9: 0 | BO9: 2165758 | BP9: 1797449 | BQ9: 1441553 | BR9: 2804618 | BS9: 0 | BT9: 140965 | BU9: 3973463 | BV9: 2869474 | BW9: 4323829 | BX9: 0 | BY9: 0 | BZ9: 0 | CA9: 2165758 | CB9: 148090.49 | CC9: 135973.82 | CD9: 282019.99 | CE9: 0 | CF9: 10581.478 | CG9: 370578.81 | CH9: 263675.48 | CI9: 422833.85 | CJ9: 0 | CK9: 0 | CL9: 0 | CM9: 192044.63 | CN9: 820067 | CO9: 820067 | CP9: 19517109 | CQ9: 19517109 | CR9: 1825798.5 | CS9: 2024 | CT9: =IFERROR(INDEX(Geography!C:C, MATCH(G9, Geography!B:B, 0)), G9) -> Alabama | CU9: =IF(O9=VLOOKUP("eia923_lignite_fuel_code", Keys!$B:$C, 2, FALSE), VLOOKUP("lignite_label", Keys!$B:$C, 2, FALSE),VLOOKUP("hard_coal_label", Keys!$B:$C, 2, FALSE)) -> hard_coal
A10: 59 | B10: N | C10: . | D10: Platte | E10: City of Grand Island - (NE) | F10: 40606 | G10: NE | H10: WNC | I10: MRO | K10: 22 | L10: 1 | M10: Electric Utility | N10: ST | O10: SUB | P10: COL | Q10: SWPP | R10: AM | S10: short tons | T10: 35233 | U10: 18781 | V10: 11229 | W10: 7299 | X10: 17626 | Y10: 30783 | Z10: 34018 | AA10: 32614 | AB10: 7282 | AC10: 3333 | AD10: 10038 | AE10: 30603 | AF10: 35233 | AG10: 18781 | AH10: 11229 | AI10: 7299 | AJ10: 17626 | AK10: 30783 | AL10: 34018 | AM10: 32614 | AN10: 7282 | AO10: 3333 | AP10: 10038 | AQ10: 30603 | AR10: 17.09 | AS10: 16.94 | AT10: 16.55 | AU10: 16.55 | AV10: 16.82 | AW10: 16.83 | AX10: 16.89 | AY10: 16.95 | AZ10: 16.92 | BA10: 16.91 | BB10: 16.91 | BC10: 16.66 | BD10: 602132 | BE10: 318150 | BF10: 185840 | BG10: 120798 | BH10: 296469 | BI10: 518078 | BJ10: 574564 | BK10: 552807 | BL10: 123211 | BM10: 56361 | BN10: 169743 | BO10: 509846 | BP10: 602132 | BQ10: 318150 | BR10: 185840 | BS10: 120798 | BT10: 296469 | BU10: 518078 | BV10: 574564 | BW10: 552807 | BX10: 123211 | BY10: 56361 | BZ10: 169743 | CA10: 509846 | CB10: 53779 | CC10: 27955.859 | CD10: 16786.958 | CE10: 10573.305 | CF10: 25727.723 | CG10: 46009 | CH10: 51226 | CI10: 49907 | CJ10: 10829.491 | CK10: 4771.198 | CL10: 14624.896 | CM10: 45931 | CN10: 238839 | CO10: 238839 | CP10: 4027999 | CQ10: 4027999 | CR10: 358121.43 | CS10: 2024 | CT10: =IFERROR(INDEX(Geography!C:C, MATCH(G10, Geography!B:B, 0)), G10) -> Nebraska | CU10: =IF(O10=VLOOKUP("eia923_lignite_fuel_code", Keys!$B:$C, 2, FALSE), VLOOKUP("lignite_label", Keys!$B:$C, 2, FALSE),VLOOKUP("hard_coal_label", Keys!$B:$C, 2, FALSE)) -> hard_coal
A11: 60 | B11: N | C11: . | D11: Whelan Energy Center | E11: City of Hastings - (NE) | F11: 8245 | G11: NE | H11: WNC | I11: MRO | K11: 22 | L11: 1 | M11: Electric Utility | N11: ST | O11: RC | P11: COL | Q11: SWPP | R11: M | S11: short tons | T11: 0 | U11: 0 | V11: 0 | W11: 0 | X11: 0 | Y11: 0 | Z11: 0 | AA11: 0 | AB11: 0 | AC11: 0 | AD11: 0 | AE11: 0 | AF11: 0 | AG11: 0 | AH11: 0 | AI11: 0 | AJ11: 0 | AK11: 0 | AL11: 0 | AM11: 0 | AN11: 0 | AO11: 0 | AP11: 0 | AQ11: 0 | AR11: 0 | AS11: 0 | AT11: 0 | AU11: 0 | AV11: 0 | AW11: 0 | AX11: 0 | AY11: 0 | AZ11: 0 | BA11: 0 | BB11: 0 | BC11: 0 | BD11: 0 | BE11: 0 | BF11: 0 | BG11: 0 | BH11: 0 | BI11: 0 | BJ11: 0 | BK11: 0 | BL11: 0 | BM11: 0 | BN11: 0 | BO11: 0 | BP11: 0 | BQ11: 0 | BR11: 0 | BS11: 0 | BT11: 0 | BU11: 0 | BV11: 0 | BW11: 0 | BX11: 0 | BY11: 0 | BZ11: 0 | CA11: 0 | CB11: 0 | CC11: 0 | CD11: 0 | CE11: 0 | CF11: 0 | CG11: 0 | CH11: 0 | CI11: 0 | CJ11: 0 | CK11: 0 | CL11: 0 | CM11: 0 | CN11: 0 | CO11: 0 | CP11: 0 | CQ11: 0 | CR11: 0 | CS11: 2024 | CT11: =IFERROR(INDEX(Geography!C:C, MATCH(G11, Geography!B:B, 0)), G11) -> Nebraska | CU11: =IF(O11=VLOOKUP("eia923_lignite_fuel_code", Keys!$B:$C, 2, FALSE), VLOOKUP("lignite_label", Keys!$B:$C, 2, FALSE),VLOOKUP("hard_coal_label", Keys!$B:$C, 2, FALSE)) -> hard_coal
A12: 60 | B12: N | C12: . | D12: Whelan Energy Center | E12: City of Hastings - (NE) | F12: 8245 | G12: NE | H12: WNC | I12: MRO | K12: 22 | L12: 1 | M12: Electric Utility | N12: ST | O12: SUB | P12: COL | Q12: SWPP | R12: M | S12: short tons | T12: 111074 | U12: 64243 | V12: 18333 | W12: 5822 | X12: 56674 | Y12: 66127 | Z12: 91597 | AA12: 87535 | AB12: 84539 | AC12: 61386 | AD12: 23137 | AE12: 99760 | AF12: 111074 | AG12: 64243 | AH12: 18333 | AI12: 5822 | AJ12: 56674 | AK12: 66127 | AL12: 91597 | AM12: 87535 | AN12: 84539 | AO12: 61386 | AP12: 23137 | AQ12: 99760 | AR12: 16.363 | AS12: 16.556 | AT12: 16.463 | AU12: 16.296 | AV12: 16.412 | AW12: 16.371 | AX12: 16.398 | AY12: 16.562 | AZ12: 16.467 | BA12: 16.718 | BB12: 16.293 | BC12: 16.289 | BD12: 1817504 | BE12: 1063607 | BF12: 301816 | BG12: 94875 | BH12: 930134 | BI12: 1082565 | BJ12: 1502008 | BK12: 1449755 | BL12: 1392104 | BM12: 1026251 | BN12: 376971 | BO12: 1624991 | BP12: 1817504 | BQ12: 1063607 | BR12: 301816 | BS12: 94875 | BT12: 930134 | BU12: 1082565 | BV12: 1502008 | BW12: 1449755 | BX12: 1392104 | BY12: 1026251 | BZ12: 376971 | CA12: 1624991 | CB12: 171614.13 | CC12: 97789.207 | CD12: 25884.948 | CE12: 7338.377 | CF12: 84770.3 | CG12: 101415.02 | CH12: 140733.82 | CI12: 134728.53 | CJ12: 134775.88 | CK12: 92727.072 | CL12: 30151.439 | CM12: 151853.87 | CN12: 770227 | CO12: 770227 | CP12: 12662581 | CQ12: 12662581 | CR12: 1173782.6 | CS12: 2024 | CT12: =IFERROR(INDEX(Geography!C:C, MATCH(G12, Geography!B:B, 0)), G12) -> Nebraska | CU12: =IF(O12=VLOOKUP("eia923_lignite_fuel_code", Keys!$B:$C, 2, FALSE), VLOOKUP("lignite_label", Keys!$B:$C, 2, FALSE),VLOOKUP("hard_coal_label", Keys!$B:$C, 2, FALSE)) -> hard_coal
A13: 79 | B13: Y | C13: . | D13: Chena Power Plant | E13: Aurora Energy LLC | F13: 986 | G13: AK | H13: PACN | K13: 22 | L13: 3 | M13: NAICS-22 Cogen | N13: ST | O13: SUB | P13: COL | R13: AM | S13: short tons | T13: 13399 | U13: 12613 | V13: 14385 | W13: 7254 | X13: 6795 | Y13: 14109 | Z13: 15517 | AA13: 15186 | AB13: 9995 | AC13: 11665 | AD13: 16519 | AE13: 17585 | AF13: 7379 | AG13: 7324 | AH13: 9328 | AI13: 3117 | AJ13: 3386 | AK13: 10521 | AL13: 11969 | AM13: 11400 | AN13: 6477 | AO13: 7681 | AP13: 11859 | AQ13: 11916 | AR13: 15.3 | AS13: 15.1 | AT13: 15.2 | AU13: 15.4 | AV13: 15.4 | AW13: 15.3 | AX13: 15.4 | AY13: 15.1 | AZ13: 14.8 | BA13: 14.6 | BB13: 14.8 | BC13: 15.1 | BD13: 205005 | BE13: 190456 | BF13: 218652 | BG13: 111712 | BH13: 104643 | BI13: 215868 | BJ13: 238962 | BK13: 229309 | BL13: 147926 | BM13: 170309 | BN13: 244481 | BO13: 265534 | BP13: 112903 | BQ13: 110594 | BR13: 141780 | BS13: 47995 | BT13: 52147 | BU13: 160967 | BV13: 184316 | BW13: 172135 | BX13: 95854 | BY13: 112141 | BZ13: 175513 | CA13: 179926 | CB13: 8687 | CC13: 8477 | CD13: 11157 | CE13: 3444 | CF13: 3784 | CG13: 12806 | CH13: 14823 | CI13: 13794 | CJ13: 7378 | CK13: 8696 | CL13: 13960 | CM13: 14330 | CN13: 155022 | CO13: 102357 | CP13: 2342857 | CQ13: 1546271 | CR13: 121336 | CS13: 2024 | CT13: =IFERROR(INDEX(Geography!C:C, MATCH(G13, Geography!B:B, 0)), G13) -> AK | CU13: =IF(O13=VLOOKUP("eia923_lignite_fuel_code", Keys!$B:$C, 2, FALSE), VLOOKUP("lignite_label", Keys!$B:$C, 2, FALSE),VLOOKUP("hard_coal_label", Keys!$B:$C, 2, FALSE)) -> hard_coal
A14: 108 | B14: N | C14: . | D14: Holcomb | E14: Sunflower Electric Power Corp | F14: 18315 | G14: KS | H14: WNC | I14: MRO | K14: 22 | L14: 1 | M14: Electric Utility | N14: ST | O14: SUB | P14: COL | Q14: SWPP | R14: M | S14: short tons | T14: 104306 | U14: 36622 | V14: 14703 | W14: 0 | X14: 15116 | Y14: 74564 | Z14: 94387 | AA14: 94724 | AB14: 81688 | AC14: 69391 | AD14: 59000 | AE14: 96610 | AF14: 104306 | AG14: 36622 | AH14: 14703 | AI14: 0 | AJ14: 15116 | AK14: 74564 | AL14: 94387 | AM14: 94724 | AN14: 81688 | AO14: 69391 | AP14: 59000 | AQ14: 96610 | AR14: 17.26 | AS14: 17.05 | AT14: 17.14 | AU14: 0 | AV14: 17.602 | AW14: 17.718 | AX14: 17.774 | AY14: 17.56 | AZ14: 17.468 | BA14: 17.674 | BB14: 17.204 | BC14: 16.87 | BD14: 1800322 | BE14: 624405 | BF14: 252009 | BG14: 0 | BH14: 266072 | BI14: 1321125 | BJ14: 1677635 | BK14: 1663353 | BL14: 1426926 | BM14: 1226417 | BN14: 1015036 | BO14: 1629811 | BP14: 1800322 | BQ14: 624405 | BR14: 252009 | BS14: 0 | BT14: 266072 | BU14: 1321125 | BV14: 1677635 | BW14: 1663353 | BX14: 1426926 | BY14: 1226417 | BZ14: 1015036 | CA14: 1629811 | CB14: 164188.81 | CC14: 48949.079 | CD14: 18849.404 | CE14: -1601.938 | CF14: 20238.454 | CG14: 114998.89 | CH14: 154882.37 | CI14: 151871.57 | CJ14: 130774.37 | CK14: 108717.45 | CL14: 87789.331 | CM14: 149401.28 | CN14: 741111 | CO14: 741111 | CP14: 12903111 | CQ14: 12903111 | CR14: 1149059.1 | CS14: 2024 | CT14: =IFERROR(INDEX(Geography!C:C, MATCH(G14, Geography!B:B, 0)), G14) -> Kansas | CU14: =IF(O14=VLOOKUP("eia923_lignite_fuel_code", Keys!$B:$C, 2, FALSE), VLOOKUP("lignite_label", Keys!$B:$C, 2, FALSE),VLOOKUP("hard_coal_label", Keys!$B:$C, 2, FALSE)) -> hard_coal
A15: 113 | B15: N | C15: . | D15: Cholla | E15: Arizona Public Service Co | F15: 803 | G15: AZ | H15: MTN | I15: WECC | K15: 22 | L15: 1 | M15: Electric Utility | N15: ST | O15: BIT | P15: COL | Q15: AZPS | R15: M | S15: short tons | T15: 0 | U15: 0 | V15: 0 | W15: 0 | X15: 0 | Y15: 0 | Z15: 0 | AA15: 0 | AB15: 0 | AC15: 0 | AD15: 0 | AE15: 0 | AF15: 0 | AG15: 0 | AH15: 0 | AI15: 0 | AJ15: 0 | AK15: 0 | AL15: 0 | AM15: 0 | AN15: 0 | AO15: 0 | AP15: 0 | AQ15: 0 | AR15: 0 | AS15: 0 | AT15: 0 | AU15: 0 | AV15: 0 | AW15: 0 | AX15: 0 | AY15: 0 | AZ15: 0 | BA15: 0 | BB15: 0 | BC15: 0 | BD15: 0 | BE15: 0 | BF15: 0 | BG15: 0 | BH15: 0 | BI15: 0 | BJ15: 0 | BK15: 0 | BL15: 0 | BM15: 0 | BN15: 0 | BO15: 0 | BP15: 0 | BQ15: 0 | BR15: 0 | BS15: 0 | BT15: 0 | BU15: 0 | BV15: 0 | BW15: 0 | BX15: 0 | BY15: 0 | BZ15: 0 | CA15: 0 | CB15: 0 | CC15: 0 | CD15: 0 | CE15: 0 | CF15: 0 | CG15: 0 | CH15: 0 | CI15: 0 | CJ15: 0 | CK15: 0 | CL15: 0 | CM15: 0 | CN15: 0 | CO15: 0 | CP15: 0 | CQ15: 0 | CR15: 0 | CS15: 2024 | CT15: =IFERROR(INDEX(Geography!C:C, MATCH(G15, Geography!B:B, 0)), G15) -> Arizona | CU15: =IF(O15=VLOOKUP("eia923_lignite_fuel_code", Keys!$B:$C, 2, FALSE), VLOOKUP("lignite_label", Keys!$B:$C, 2, FALSE),VLOOKUP("hard_coal_label", Keys!$B:$C, 2, FALSE)) -> hard_coal
A16: 113 | B16: N | C16: . | D16: Cholla | E16: Arizona Public Service Co | F16: 803 | G16: AZ | H16: MTN | I16: WECC | K16: 22 | L16: 1 | M16: Electric Utility | N16: ST | O16: SUB | P16: COL | Q16: AZPS | R16: M | S16: short tons | T16: 135583 | U16: 103742 | V16: 0 | W16: 0 | X16: 0 | Y16: 0 | Z16: 128137 | AA16: 98064 | AB16: 104394 | AC16: 75142 | AD16: 0 | AE16: 109373 | AF16: 135583 | AG16: 103742 | AH16: 0 | AI16: 0 | AJ16: 0 | AK16: 0 | AL16: 128137 | AM16: 98064 | AN16: 104394 | AO16: 75142 | AP16: 0 | AQ16: 109373 | AR16: 18.507 | AS16: 18.233 | AT16: 0 | AU16: 0 | AV16: 0 | AW16: 0 | AX16: 18.512 | AY16: 18.596 | AZ16: 18.55 | BA16: 18.604 | BB16: 0 | BC16: 18.6 | BD16: 2509235 | BE16: 1891528 | BF16: 0 | BG16: 0 | BH16: 0 | BI16: 0 | BJ16: 2372072 | BK16: 1823598 | BL16: 1936509 | BM16: 1397942 | BN16: 0 | BO16: 2034338 | BP16: 2509235 | BQ16: 1891528 | BR16: 0 | BS16: 0 | BT16: 0 | BU16: 0 | BV16: 2372072 | BW16: 1823598 | BX16: 1936509 | BY16: 1397942 | BZ16: 0 | CA16: 2034338 | CB16: 236495.18 | CC16: 175698.6 | CD16: 0 | CE16: 0 | CF16: 0 | CG16: 0 | CH16: 221000.06 | CI16: 174411.57 | CJ16: 180899.8 | CK16: 130748.95 | CL16: 0 | CM16: 200696.5 | CN16: 754435 | CO16: 754435 | CP16: 13965222 | CQ16: 13965222 | CR16: 1319950.7 | CS16: 2024 | CT16: =IFERROR(INDEX(Geography!C:C, MATCH(G16, Geography!B:B, 0)), G16) -> Arizona | CU16: =IF(O16=VLOOKUP("eia923_lignite_fuel_code", Keys!$B:$C, 2, FALSE), VLOOKUP("lignite_label", Keys!$B:$C, 2, FALSE),VLOOKUP("hard_coal_label", Keys!$B:$C, 2, FALSE)) -> hard_coal
A17: 130 | B17: N | C17: . | D17: Cross | E17: South Carolina Public Service Authority | F17: 17543 | G17: SC | H17: SAT | I17: SERC | K17: 22 | L17: 1 | M17: Electric Utility | N17: ST | O17: BIT | P17: COL | Q17: SC | R17: M | S17: short tons | T17: 329294 | U17: 180974 | V17: 214631 | W17: 243561 | X17: 372753 | Y17: 385794 | Z17: 471799 | AA17: 289063 | AB17: 273780 | AC17: 266707 | AD17: 250850 | AE17: 350253 | AF17: 329294 | AG17: 180974 | AH17: 214631 | AI17: 243561 | AJ17: 372753 | AK17: 385794 | AL17: 471799 | AM17: 289063 | AN17: 273780 | AO17: 266707 | AP17: 250850 | AQ17: 350253 | AR17: 24.296 | AS17: 24.183 | AT17: 24.535 | AU17: 24.474 | AV17: 24.584 | AW17: 24.673 | AX17: 24.27 | AY17: 24.298 | AZ17: 24.27 | BA17: 24.655 | BB17: 24.573 | BC17: 24.169 | BD17: 8000527 | BE17: 4376494 | BF17: 5265972 | BG17: 5960912 | BH17: 9163760 | BI17: 9518695 | BJ17: 11450562 | BK17: 7023653 | BL17: 6644641 | BM17: 6575661 | BN17: 6164137 | BO17: 8465265 | BP17: 8000527 | BQ17: 4376494 | BR17: 5265972 | BS17: 5960912 | BT17: 9163760 | BU17: 9518695 | BV17: 11450562 | BW17: 7023653 | BX17: 6644641 | BY17: 6575661 | BZ17: 6164137 | CA17: 8465265 | CB17: 748571.94 | CC17: 420713.17 | CD17: 489755.11 | CE17: 565713.74 | CF17: 867410.99 | CG17: 921969.76 | CH17: 1161479.4 | CI17: 650209.92 | CJ17: 647936.83 | CK17: 628715.42 | CL17: 567694.11 | CM17: 833777.54 | CN17: 3629459 | CO17: 3629459 | CP17: 88610279 | CQ17: 88610279 | CR17: 8503947.9 | CS17: 2024 | CT17: =IFERROR(INDEX(Geography!C:C, MATCH(G17, Geography!B:B, 0)), G17) -> South Carolina | CU17: =IF(O17=VLOOKUP("eia923_lignite_fuel_code", Keys!$B:$C, 2, FALSE), VLOOKUP("lignite_label", Keys!$B:$C, 2, FALSE),VLOOKUP("hard_coal_label", Keys!$B:$C, 2, FALSE)) -> hard_coal
A18: 136 | B18: N | C18: . | D18: Seminole (FL) | E18: Seminole Electric Cooperative Inc | F18: 21554 | G18: FL | H18: SAT | I18: SERC | K18: 22 | L18: 1 | M18: Electric Utility | N18: ST | O18: BIT | P18: COL | Q18: SEC | R18: M | S18: short tons | T18: 118738 | U18: 34240 | V18: 1477 | W18: 64483 | X18: 119366 | Y18: 139049 | Z18: 127562 | AA18: 130817 | AB18: 108371 | AC18: 61649 | AD18: 87361 | AE18: 14644 | AF18: 118738 | AG18: 34240 | AH18: 1477 | AI18: 64483 | AJ18: 119366 | AK18: 139049 | AL18: 127562 | AM18: 130817 | AN18: 108371 | AO18: 61649 | AP18: 87361 | AQ18: 14644 | AR18: 24 | AS18: 24 | AT18: 24 | AU18: 24.432 | AV18: 24 | AW18: 24.25 | AX18: 24 | AY18: 24 | AZ18: 24 | BA18: 24 | BB18: 24 | BC18: 24 | BD18: 2849712 | BE18: 821760 | BF18: 35448 | BG18: 1575449 | BH18: 2864784 | BI18: 3371938 | BJ18: 3061488 | BK18: 3139608 | BL18: 2600904 | BM18: 1479576 | BN18: 2096664 | BO18: 351456 | BP18: 2849712 | BQ18: 821760 | BR18: 35448 | BS18: 1575449 | BT18: 2864784 | BU18: 3371938 | BV18: 3061488 | BW18: 3139608 | BX18: 2600904 | BY18: 1479576 | BZ18: 2096664 | CA18: 351456 | CB18: 268782.89 | CC18: 69899.569 | CD18: 0 | CE18: 126281.42 | CF18: 269209.99 | CG18: 318118.68 | CH18: 281488.5 | CI18: 287964.29 | CJ18: 234678.9 | CK18: 125056.86 | CL18: 197121.22 | CM18: 26005.595 | CN18: 1007757 | CO18: 1007757 | CP18: 24248787 | CQ18: 24248787 | CR18: 2204607.9 | CS18: 2024 | CT18: =IFERROR(INDEX(Geography!C:C, MATCH(G18, Geography!B:B, 0)), G18) -> Florida | CU18: =IF(O18=VLOOKUP("eia923_lignite_fuel_code", Keys!$B:$C, 2, FALSE), VLOOKUP("lignite_label", Keys!$B:$C, 2, FALSE),VLOOKUP("hard_coal_label", Keys!$B:$C, 2, FALSE)) -> hard_coal
A19: 160 | B19: N | C19: . | D19: Apache Station | E19: Arizona Electric Pwr Coop Inc | F19: 796 | G19: AZ | H19: MTN | I19: WECC | K19: 22 | L19: 1 | M19: Electric Utility | N19: ST | O19: BIT | P19: COL | Q19: WALC | R19: M | S19: short tons | T19: 0 | U19: 0 | V19: 0 | W19: 0 | X19: 0 | Y19: 0 | Z19: 0 | AA19: 0 | AB19: 0 | AC19: 0 | AD19: 0 | AE19: 0 | AF19: 0 | AG19: 0 | AH19: 0 | AI19: 0 | AJ19: 0 | AK19: 0 | AL19: 0 | AM19: 0 | AN19: 0 | AO19: 0 | AP19: 0 | AQ19: 0 | AR19: 0 | AS19: 0 | AT19: 0 | AU19: 0 | AV19: 0 | AW19: 0 | AX19: 0 | AY19: 0 | AZ19: 0 | BA19: 0 | BB19: 0 | BC19: 0 | BD19: 0 | BE19: 0 | BF19: 0 | BG19: 0 | BH19: 0 | BI19: 0 | BJ19: 0 | BK19: 0 | BL19: 0 | BM19: 0 | BN19: 0 | BO19: 0 | BP19: 0 | BQ19: 0 | BR19: 0 | BS19: 0 | BT19: 0 | BU19: 0 | BV19: 0 | BW19: 0 | BX19: 0 | BY19: 0 | BZ19: 0 | CA19: 0 | CB19: 0 | CC19: 0 | CD19: 0 | CE19: 0 | CF19: 0 | CG19: 0 | CH19: 0 | CI19: 0 | CJ19: 0 | CK19: 0 | CL19: 0 | CM19: 0 | CN19: 0 | CO19: 0 | CP19: 0 | CQ19: 0 | CR19: 0 | CS19: 2024 | CT19: =IFERROR(INDEX(Geography!C:C, MATCH(G19, Geography!B:B, 0)), G19) -> Arizona | CU19: =IF(O19=VLOOKUP("eia923_lignite_fuel_code", Keys!$B:$C, 2, FALSE), VLOOKUP("lignite_label", Keys!$B:$C, 2, FALSE),VLOOKUP("hard_coal_label", Keys!$B:$C, 2, FALSE)) -> hard_coal
A20: 160 | B20: N | C20: . | D20: Apache Station | E20: Arizona Electric Pwr Coop Inc | F20: 796 | G20: AZ | H20: MTN | I20: WECC | K20: 22 | L20: 1 | M20: Electric Utility | N20: ST | O20: SUB | P20: COL | Q20: WALC | R20: M | S20: short tons | T20: 24810 | U20: 2625 | V20: 0 | W20: 0 | X20: 9421 | Y20: 9286 | Z20: 0 | AA20: 0 | AB20: 15357 | AC20: 0 | AD20: 38228 | AE20: 40521 | AF20: 24810 | AG20: 2625 | AH20: 0 | AI20: 0 | AJ20: 9421 | AK20: 9286 | AL20: 0 | AM20: 0 | AN20: 15357 | AO20: 0 | AP20: 38228 | AQ20: 40521 | AR20: 18.06 | AS20: 18.06 | AT20: 0 | AU20: 0 | AV20: 17.88 | AW20: 18.14 | AX20: 0 | AY20: 0 | AZ20: 18.12 | BA20: 0 | BB20: 18.13 | BC20: 18.1 | BD20: 448069 | BE20: 47408 | BF20: 0 | BG20: 0 | BH20: 168447 | BI20: 168448 | BJ20: 0 | BK20: 0 | BL20: 278269 | BM20: 0 | BN20: 693074 | BO20: 733430 | BP20: 448069 | BQ20: 47408 | BR20: 0 | BS20: 0 | BT20: 168447 | BU20: 168448 | BV20: 0 | BW20: 0 | BX20: 278269 | BY20: 0 | BZ20: 693074 | CA20: 733430 | CB20: 40683.539 | CC20: 4193.916 | CD20: 0 | CE20: 0 | CF20: 15110.193 | CG20: 15243.018 | CH20: 0 | CI20: 0 | CJ20: 26190.067 | CK20: 0 | CL20: 65240.879 | CM20: 69133.295 | CN20: 140248 | CO20: 140248 | CP20: 2537145 | CQ20: 2537145 | CR20: 235794.91 | CS20: 2024 | CT20: =IFERROR(INDEX(Geography!C:C, MATCH(G20, Geography!B:B, 0)), G20) -> Arizona | CU20: =IF(O20=VLOOKUP("eia923_lignite_fuel_code", Keys!$B:$C, 2, FALSE), VLOOKUP("lignite_label", Keys!$B:$C, 2, FALSE),VLOOKUP("hard_coal_label", Keys!$B:$C, 2, FALSE)) -> hard_coal
A21: 165 | B21: N | C21: . | D21: GREC | E21: Grand River Dam Authority | F21: 7490 | G21: OK | H21: WSC | I21: MRO | K21: 22 | L21: 1 | M21: Electric Utility | N21: ST | O21: SUB | P21: COL | Q21: SWPP | R21: M | S21: short tons | T21: 96232 | U21: 0 | V21: 4553 | W21: 16577 | X21: 47007 | Y21: 36877 | Z21: 77234 | AA21: 62130 | AB21: 2 | AC21: 95013 | AD21: 22533 | AE21: 15074 | AF21: 96232 | AG21: 0 | AH21: 4553 | AI21: 16577 | AJ21: 47007 | AK21: 36877 | AL21: 77234 | AM21: 62130 | AN21: 2 | AO21: 95013 | AP21: 22533 | AQ21: 15074 | AR21: 17.017 | AS21: 0 | AT21: 17.008 | AU21: 16.98 | AV21: 16.98 | AW21: 16.98 | AX21: 16.98 | AY21: 16.98 | AZ21: 16.98 | BA21: 16.98 | BB21: 16.87 | BC21: 16.7 | BD21: 1637580 | BE21: 0 | BF21: 77437 | BG21: 281477 | BH21: 798179 | BI21: 626171 | BJ21: 1311433 | BK21: 1054967 | BL21: 34 | BM21: 1613321 | BN21: 380132 | BO21: 251736 | BP21: 1637580 | BQ21: 0 | BR21: 77437 | BS21: 281477 | BT21: 798179 | BU21: 626171 | BV21: 1311433 | BW21: 1054967 | BX21: 34 | BY21: 1613321 | BZ21: 380132 | CA21: 251736 | CB21: 123009.72 | CC21: 0 | CD21: 1573.692 | CE21: 17614.002 | CF21: 56366.527 | CG21: 39129.684 | CH21: 98974.309 | CI21: 80469.589 | CJ21: -5.709 | CK21: 132483.16 | CL21: 22896.549 | CM21: 14436.688 | CN21: 473232 | CO21: 473232 | CP21: 8032467 | CQ21: 8032467 | CR21: 586948.21 | CS21: 2024 | CT21: =IFERROR(INDEX(Geography!C:C, MATCH(G21, Geography!B:B, 0)), G21) -> Oklahoma | CU21: =IF(O21=VLOOKUP("eia923_lignite_fuel_code", Keys!$B:$C, 2, FALSE), VLOOKUP("lignite_label", Keys!$B:$C, 2, FALSE),VLOOKUP("hard_coal_label", Keys!$B:$C, 2, FALSE)) -> hard_coal
A22: 298 | B22: N | C22: . | D22: Limestone | E22: NRG Texas Power LLC | F22: 54888 | G22: TX | H22: WSC | I22: TRE | K22: 22 | L22: 2 | M22: NAICS-22 Non-Cogen | N22: ST | O22: LIG | P22: COL | Q22: ERCO | R22: M | S22: short tons | T22: 0 | U22: 0 | V22: 0 | W22: 0 | X22: 0 | Y22: 0 | Z22: 0 | AA22: 0 | AB22: 0 | AC22: 0 | AD22: 0 | AE22: 0 | AF22: 0 | AG22: 0 | AH22: 0 | AI22: 0 | AJ22: 0 | AK22: 0 | AL22: 0 | AM22: 0 | AN22: 0 | AO22: 0 | AP22: 0 | AQ22: 0 | AR22: 0 | AS22: 0 | AT22: 0 | AU22: 0 | AV22: 0 | AW22: 0 | AX22: 0 | AY22: 0 | AZ22: 0 | BA22: 0 | BB22: 0 | BC22: 0 | BD22: 0 | BE22: 0 | BF22: 0 | BG22: 0 | BH22: 0 | BI22: 0 | BJ22: 0 | BK22: 0 | BL22: 0 | BM22: 0 | BN22: 0 | BO22: 0 | BP22: 0 | BQ22: 0 | BR22: 0 | BS22: 0 | BT22: 0 | BU22: 0 | BV22: 0 | BW22: 0 | BX22: 0 | BY22: 0 | BZ22: 0 | CA22: 0 | CB22: 0 | CC22: 0 | CD22: 0 | CE22: 0 | CF22: 0 | CG22: 0 | CH22: 0 | CI22: 0 | CJ22: 0 | CK22: 0 | CL22: 0 | CM22: 0 | CN22: 0 | CO22: 0 | CP22: 0 | CQ22: 0 | CR22: 0 | CS22: 2024 | CT22: =IFERROR(INDEX(Geography!C:C, MATCH(G22, Geography!B:B, 0)), G22) -> Texas | CU22: =IF(O22=VLOOKUP("eia923_lignite_fuel_code", Keys!$B:$C, 2, FALSE), VLOOKUP("lignite_label", Keys!$B:$C, 2, FALSE),VLOOKUP("hard_coal_label", Keys!$B:$C, 2, FALSE)) -> lignite
A23: 298 | B23: N | C23: . | D23: Limestone | E23: NRG Texas Power LLC | F23: 54888 | G23: TX | H23: WSC | I23: TRE | K23: 22 | L23: 2 | M23: NAICS-22 Non-Cogen | N23: ST | O23: SUB | P23: COL | Q23: ERCO | R23: M | S23: short tons | T23: 460944 | U23: 96502 | V23: 127123 | W23: 124973 | X23: 0 | Y23: 137387 | Z23: 498521 | AA23: 513155 | AB23: 410356 | AC23: 385558 | AD23: 320245 | AE23: 547287 | AF23: 460944 | AG23: 96502 | AH23: 127123 | AI23: 124973 | AJ23: 0 | AK23: 137387 | AL23: 498521 | AM23: 513155 | AN23: 410356 | AO23: 385558 | AP23: 320245 | AQ23: 547287 | AR23: 16.52 | AS23: 16.72 | AT23: 16.72 | AU23: 16.76 | AV23: 0 | AW23: 16.68 | AX23: 16.7 | AY23: 16.84 | AZ23: 16.976 | BA23: 16.578 | BB23: 16.63 | BC23: 16.46 | BD23: 7614795 | BE23: 1613513 | BF23: 2125497 | BG23: 2094547 | BH23: 0 | BI23: 2291615 | BJ23: 8325301 | BK23: 8641530 | BL23: 6966203 | BM23: 6391781 | BN23: 5325674 | BO23: 9008344 | BP23: 7614795 | BQ23: 1613513 | BR23: 2125497 | BS23: 2094547 | BT23: 0 | BU23: 2291615 | BV23: 8325301 | BW23: 8641530 | BX23: 6966203 | BY23: 6391781 | BZ23: 5325674 | CA23: 9008344 | CB23: 637231.75 | CC23: 123395.03 | CD23: 231922.94 | CE23: 159360.31 | CF23: -8581.194 | CG23: 188471.91 | CH23: 753992.84 | CI23: 761119.45 | CJ23: 608684.14 | CK23: 577268.52 | CL23: 467420.47 | CM23: 800250.56 | CN23: 3622051 | CO23: 3622051 | CP23: 60398800 | CQ23: 60398800 | CR23: 5300536.7 | CS23: 2024 | CT23: =IFERROR(INDEX(Geography!C:C, MATCH(G23, Geography!B:B, 0)), G23) -> Texas | CU23: =IF(O23=VLOOKUP("eia923_lignite_fuel_code", Keys!$B:$C, 2, FALSE), VLOOKUP("lignite_label", Keys!$B:$C, 2, FALSE),VLOOKUP("hard_coal_label", Keys!$B:$C, 2, FALSE)) -> hard_coal
A24: 469 | B24: N | C24: . | D24: Cherokee | E24: Public Service Co of Colorado | F24: 15466 | G24: CO | H24: MTN | I24: WECC | K24: 22 | L24: 1 | M24: Electric Utility | N24: ST | O24: BIT | P24: COL | Q24: PSCO | R24: M | S24: short tons | T24: 0 | U24: 0 | V24: 0 | W24: 0 | X24: 0 | Y24: 0 | Z24: 0 | AA24: 0 | AB24: 0 | AC24: 0 | AD24: 0 | AE24: 0 | AF24: 0 | AG24: 0 | AH24: 0 | AI24: 0 | AJ24: 0 | AK24: 0 | AL24: 0 | AM24: 0 | AN24: 0 | AO24: 0 | AP24: 0 | AQ24: 0 | AR24: 0 | AS24: 0 | AT24: 0 | AU24: 0 | AV24: 0 | AW24: 0 | AX24: 0 | AY24: 0 | AZ24: 0 | BA24: 0 | BB24: 0 | BC24: 0 | BD24: 0 | BE24: 0 | BF24: 0 | BG24: 0 | BH24: 0 | BI24: 0 | BJ24: 0 | BK24: 0 | BL24: 0 | BM24: 0 | BN24: 0 | BO24: 0 | BP24: 0 | BQ24: 0 | BR24: 0 | BS24: 0 | BT24: 0 | BU24: 0 | BV24: 0 | BW24: 0 | BX24: 0 | BY24: 0 | BZ24: 0 | CA24: 0 | CB24: 0 | CC24: 0 | CD24: 0 | CE24: 0 | CF24: 0 | CG24: 0 | CH24: 0 | CI24: 0 | CJ24: 0 | CK24: 0 | CL24: 0 | CM24: 0 | CN24: 0 | CO24: 0 | CP24: 0 | CQ24: 0 | CR24: 0 | CS24: 2024 | CT24: =IFERROR(INDEX(Geography!C:C, MATCH(G24, Geography!B:B, 0)), G24) -> Colorado | CU24: =IF(O24=VLOOKUP("eia923_lignite_fuel_code", Keys!$B:$C, 2, FALSE), VLOOKUP("lignite_label", Keys!$B:$C, 2, FALSE),VLOOKUP("hard_coal_label", Keys!$B:$C, 2, FALSE)) -> hard_coal
A25: 470 | B25: N | C25: . | D25: Comanche (CO) | E25: Public Service Co of Colorado | F25: 15466 | G25: CO | H25: MTN | I25: WECC | K25: 22 | L25: 1 | M25: Electric Utility | N25: ST | O25: SUB | P25: COL | Q25: WACM | R25: M | S25: short tons | T25: 284085 | U25: 319200 | V25: 199773 | W25: 69308 | X25: 68716 | Y25: 308174 | Z25: 330426 | AA25: 298868 | AB25: 314183 | AC25: 282934 | AD25: 317092 | AE25: 352182 | AF25: 284085 | AG25: 319200 | AH25: 199773 | AI25: 69308 | AJ25: 68716 | AK25: 308174 | AL25: 330426 | AM25: 298868 | AN25: 314183 | AO25: 282934 | AP25: 317092 | AQ25: 352182 | AR25: 17.735 | AS25: 17.601 | AT25: 17.711 | AU25: 17.764 | AV25: 17.652 | AW25: 17.583 | AX25: 17.637 | AY25: 17.59 | AZ25: 17.654 | BA25: 17.564 | BB25: 17.556 | BC25: 17.691 | BD25: 5038247 | BE25: 5618239 | BF25: 3538180 | BG25: 1231187 | BH25: 1212975 | BI25: 5418623 | BJ25: 5827723 | BK25: 5257088 | BL25: 5546587 | BM25: 4969453 | BN25: 5566867 | BO25: 6230452 | BP25: 5038247 | BQ25: 5618239 | BR25: 3538180 | BS25: 1231187 | BT25: 1212975 | BU25: 5418623 | BV25: 5827723 | BW25: 5257088 | BX25: 5546587 | BY25: 4969453 | BZ25: 5566867 | CA25: 6230452 | CB25: 503198.38 | CC25: 568959.99 | CD25: 351962.66 | CE25: 116583.59 | CF25: 107382.25 | CG25: 542061.52 | CH25: 587870.46 | CI25: 528340.49 | CJ25: 559074.8 | CK25: 497065.77 | CL25: 553582.56 | CM25: 631927.04 | CN25: 3144941 | CO25: 3144941 | CP25: 55455621 | CQ25: 55455621 | CR25: 5548009.5 | CS25: 2024 | CT25: =IFERROR(INDEX(Geography!C:C, MATCH(G25, Geography!B:B, 0)), G25) -> Colorado | CU25: =IF(O25=VLOOKUP("eia923_lignite_fuel_code", Keys!$B:$C, 2, FALSE), VLOOKUP("lignite_label", Keys!$B:$C, 2, FALSE),VLOOKUP("hard_coal_label", Keys!$B:$C, 2, FALSE)) -> hard_coal
A26: 492 | B26: N | C26: . | D26: South Plant (CO) | E26: City of Colorado Springs - (CO) | F26: 3989 | G26: CO | H26: MTN | I26: WECC | K26: 22 | L26: 1 | M26: Electric Utility | N26: GT | O26: ANT | P26: COL | Q26: WACM | R26: M | S26: short tons | T26: . | U26: . | V26: . | W26: . | X26: . | Y26: . | Z26: . | AA26: . | AB26: . | AC26: . | AD26: 0 | AE26: . | AF26: . | AG26: . | AH26: . | AI26: . | AJ26: . | AK26: . | AL26: . | AM26: . | AN26: . | AO26: . | AP26: 0 | AQ26: . | AR26: . | AS26: . | AT26: . | AU26: . | AV26: . | AW26: . | AX26: . | AY26: . | AZ26: . | BA26: . | BB26: 0 | BC26: . | BD26: . | BE26: . | BF26: . | BG26: . | BH26: . | BI26: . | BJ26: . | BK26: . | BL26: . | BM26: . | BN26: 0 | BO26: . | BP26: . | BQ26: . | BR26: . | BS26: . | BT26: . | BU26: . | BV26: . | BW26: . | BX26: . | BY26: . | BZ26: 0 | CA26: . | CB26: . | CC26: . | CD26: . | CE26: . | CF26: . | CG26: . | CH26: . | CI26: . | CJ26: . | CK26: . | CL26: 0 | CM26: . | CN26: 0 | CO26: 0 | CP26: 0 | CQ26: 0 | CR26: 0 | CS26: 2024 | CT26: =IFERROR(INDEX(Geography!C:C, MATCH(G26, Geography!B:B, 0)), G26) -> Colorado | CU26: =IF(O26=VLOOKUP("eia923_lignite_fuel_code", Keys!$B:$C, 2, FALSE), VLOOKUP("lignite_label", Keys!$B:$C, 2, FALSE),VLOOKUP("hard_coal_label", Keys!$B:$C, 2, FALSE)) -> hard_coal
A27: 508 | B27: N | C27: . | D27: Lamar Plant | E27: City of Lamar - (CO) | F27: 10633 | G27: CO | H27: MTN | I27: WECC | K27: 22 | L27: 1 | M27: Electric Utility | N27: ST | O27: SUB | P27: COL | Q27: PSCO | R27: A | S27: short tons | T27: 0 | U27: 0 | V27: 0 | W27: 0 | X27: 0 | Y27: 0 | Z27: 0 | AA27: 0 | AB27: 0 | AC27: 0 | AD27: 0 | AE27: 0 | AF27: 0 | AG27: 0 | AH27: 0 | AI27: 0 | AJ27: 0 | AK27: 0 | AL27: 0 | AM27: 0 | AN27: 0 | AO27: 0 | AP27: 0 | AQ27: 0 | AR27: 0 | AS27: 0 | AT27: 0 | AU27: 0 | AV27: 0 | AW27: 0 | AX27: 0 | AY27: 0 | AZ27: 0 | BA27: 0 | BB27: 0 | BC27: 0 | BD27: 0 | BE27: 0 | BF27: 0 | BG27: 0 | BH27: 0 | BI27: 0 | BJ27: 0 | BK27: 0 | BL27: 0 | BM27: 0 | BN27: 0 | BO27: 0 | BP27: 0 | BQ27: 0 | BR27: 0 | BS27: 0 | BT27: 0 | BU27: 0 | BV27: 0 | BW27: 0 | BX27: 0 | BY27: 0 | BZ27: 0 | CA27: 0 | CB27: 0 | CC27: 0 | CD27: 0 | CE27: 0 | CF27: 0 | CG27: 0 | CH27: 0 | CI27: 0 | CJ27: 0 | CK27: 0 | CL27: 0 | CM27: 0 | CN27: 0 | CO27: 0 | CP27: 0 | CQ27: 0 | CR27: 0 | CS27: 2024 | CT27: =IFERROR(INDEX(Geography!C:C, MATCH(G27, Geography!B:B, 0)), G27) -> Colorado | CU27: =IF(O27=VLOOKUP("eia923_lignite_fuel_code", Keys!$B:$C, 2, FALSE), VLOOKUP("lignite_label", Keys!$B:$C, 2, FALSE),VLOOKUP("hard_coal_label", Keys!$B:$C, 2, FALSE)) -> hard_coal
A28: 511 | B28: N | C28: . | D28: Trinidad (CO) | E28: City of Trinidad - (CO) | F28: 19204 | G28: CO | H28: MTN | I28: WECC | K28: 22 | L28: 1 | M28: Electric Utility | N28: IC | O28: BIT | P28: COL | Q28: WACM | R28: A | S28: short tons | T28: 0 | U28: 0 | V28: 0 | W28: 0 | X28: 0 | Y28: 0 | Z28: 0 | AA28: 0 | AB28: 0 | AC28: 0 | AD28: 0 | AE28: 0 | AF28: 0 | AG28: 0 | AH28: 0 | AI28: 0 | AJ28: 0 | AK28: 0 | AL28: 0 | AM28: 0 | AN28: 0 | AO28: 0 | AP28: 0 | AQ28: 0 | AR28: 0 | AS28: 0 | AT28: 0 | AU28: 0 | AV28: 0 | AW28: 0 | AX28: 0 | AY28: 0 | AZ28: 0 | BA28: 0 | BB28: 0 | BC28: 0 | BD28: 0 | BE28: 0 | BF28: 0 | BG28: 0 | BH28: 0 | BI28: 0 | BJ28: 0 | BK28: 0 | BL28: 0 | BM28: 0 | BN28: 0 | BO28: 0 | BP28: 0 | BQ28: 0 | BR28: 0 | BS28: 0 | BT28: 0 | BU28: 0 | BV28: 0 | BW28: 0 | BX28: 0 | BY28: 0 | BZ28: 0 | CA28: 0 | CB28: 0 | CC28: 0 | CD28: 0 | CE28: 0 | CF28: 0 | CG28: 0 | CH28: 0 | CI28: 0 | CJ28: 0 | CK28: 0 | CL28: 0 | CM28: 0 | CN28: 0 | CO28: 0 | CP28: 0 | CQ28: 0 | CR28: 0 | CS28: 2024 | CT28: =IFERROR(INDEX(Geography!C:C, MATCH(G28, Geography!B:B, 0)), G28) -> Colorado | CU28: =IF(O28=VLOOKUP("eia923_lignite_fuel_code", Keys!$B:$C, 2, FALSE), VLOOKUP("lignite_label", Keys!$B:$C, 2, FALSE),VLOOKUP("hard_coal_label", Keys!$B:$C, 2, FALSE)) -> hard_coal
A29: 525 | B29: N | C29: . | D29: Hayden | E29: Public Service Co of Colorado | F29: 15466 | G29: CO | H29: MTN | I29: WECC | K29: 22 | L29: 1 | M29: Electric Utility | N29: ST | O29: BIT | P29: COL | Q29: PSCO | R29: M | S29: short tons | T29: 121824 | U29: 59514 | V29: 90983 | W29: 48915 | X29: 71375 | Y29: 88233 | Z29: 96629 | AA29: 106179 | AB29: 88997 | AC29: 84982 | AD29: 88180 | AE29: 80223 | AF29: 121824 | AG29: 59514 | AH29: 90983 | AI29: 48915 | AJ29: 71375 | AK29: 88233 | AL29: 96629 | AM29: 106179 | AN29: 88997 | AO29: 84982 | AP29: 88180 | AQ29: 80223 | AR29: 21.883 | AS29: 21.91 | AT29: 21.474 | AU29: 21.801 | AV29: 22.02 | AW29: 22.077 | AX29: 22.494 | AY29: 22.66 | AZ29: 22.315 | BA29: 22.631 | BB29: 22.018 | BC29: 22.335 | BD29: 2665875 | BE29: 1303952 | BF29: 1953769 | BG29: 1066396 | BH29: 1571678 | BI29: 1947920 | BJ29: 2173573 | BK29: 2406016 | BL29: 1985968 | BM29: 1923228 | BN29: 1941547 | BO29: 1791781 | BP29: 2665875 | BQ29: 1303952 | BR29: 1953769 | BS29: 1066396 | BT29: 1571678 | BU29: 1947920 | BV29: 2173573 | BW29: 2406016 | BX29: 1985968 | BY29: 1923228 | BZ29: 1941547 | CA29: 1791781 | CB29: 253617.08 | CC29: 114857.32 | CD29: 183388.85 | CE29: 105359.6 | CF29: 140357.04 | CG29: 180802.93 | CH29: 199029.35 | CI29: 217141.94 | CJ29: 181977.36 | CK29: 171631.29 | CL29: 183249.85 | CM29: 166185.41 | CN29: 1026034 | CO29: 1026034 | CP29: 22731703 | CQ29: 22731703 | CR29: 2097598 | CS29: 2024 | CT29: =IFERROR(INDEX(Geography!C:C, MATCH(G29, Geography!B:B, 0)), G29) -> Colorado | CU29: =IF(O29=VLOOKUP("eia923_lignite_fuel_code", Keys!$B:$C, 2, FALSE), VLOOKUP("lignite_label", Keys!$B:$C, 2, FALSE),VLOOKUP("hard_coal_label", Keys!$B:$C, 2, FALSE)) -> hard_coal
A30: 564 | B30: N | C30: . | D30: Stanton Energy Center | E30: Orlando Utilities Comm | F30: 14610 | G30: FL | H30: SAT | I30: SERC | K30: 22 | L30: 1 | M30: Electric Utility | N30: ST | O30: BIT | P30: COL | Q30: FMPP | R30: M | S30: short tons | T30: 99581 | U30: 66259 | V30: 70258 | W30: 58218 | X30: 75401 | Y30: 117756 | Z30: 128717 | AA30: 135163 | AB30: 116990 | AC30: 81020 | AD30: 48097 | AE30: 93692 | AF30: 99581 | AG30: 66259 | AH30: 70258 | AI30: 58218 | AJ30: 75401 | AK30: 117756 | AL30: 128717 | AM30: 135163 | AN30: 116990 | AO30: 81020 | AP30: 48097 | AQ30: 93692 | AR30: 23.48 | AS30: 23.64 | AT30: 23.61 | AU30: 23.48 | AV30: 23.28 | AW30: 23.31 | AX30: 23.25 | AY30: 23.41 | AZ30: 23.33 | BA30: 23.53 | BB30: 23.84 | BC30: 23.58 | BD30: 2338162 | BE30: 1566363 | BF30: 1658791 | BG30: 1366959 | BH30: 1755335 | BI30: 2744892 | BJ30: 2992670 | BK30: 3164166 | BL30: 2729377 | BM30: 1906401 | BN30: 1146632 | BO30: 2209257 | BP30: 2338162 | BQ30: 1566363 | BR30: 1658791 | BS30: 1366959 | BT30: 1755335 | BU30: 2744892 | BV30: 2992670 | BW30: 3164166 | BX30: 2729377 | BY30: 1906401 | BZ30: 1146632 | CA30: 2209257 | CB30: 197708.1 | CC30: 119615.25 | CD30: 131853.88 | CE30: 104784.18 | CF30: 155962.37 | CG30: 253806.43 | CH30: 267736.99 | CI30: 280328.8 | CJ30: 245234.1 | CK30: 159767.68 | CL30: 88188.433 | CM30: 188987.68 | CN30: 1091152 | CO30: 1091152 | CP30: 25579005 | CQ30: 25579005 | CR30: 2193973.9 | CS30: 2024 | CT30: =IFERROR(INDEX(Geography!C:C, MATCH(G30, Geography!B:B, 0)), G30) -> Florida | CU30: =IF(O30=VLOOKUP("eia923_lignite_fuel_code", Keys!$B:$C, 2, FALSE), VLOOKUP("lignite_label", Keys!$B:$C, 2, FALSE),VLOOKUP("hard_coal_label", Keys!$B:$C, 2, FALSE)) -> hard_coal
A31: 594 | B31: N | C31: . | D31: Indian River Generating Station | E31: Indian River Operations Inc | F31: 9332 | G31: DE | H31: SAT | I31: RFC | K31: 22 | L31: 2 | M31: NAICS-22 Non-Cogen | N31: GT | O31: SUB | P31: COL | Q31: PJM | R31: M | S31: short tons | T31: . | U31: 0 | V31: . | W31: 0 | X31: . | Y31: . | Z31: . | AA31: . | AB31: . | AC31: 0 | AD31: . | AE31: . | AF31: . | AG31: 0 | AH31: . | AI31: 0 | AJ31: . | AK31: . | AL31: . | AM31: . | AN31: . | AO31: 0 | AP31: . | AQ31: . | AR31: . | AS31: 0 | AT31: . | AU31: 0 | AV31: . | AW31: . | AX31: . | AY31: . | AZ31: . | BA31: 0 | BB31: . | BC31: . | BD31: . | BE31: 0 | BF31: . | BG31: 0 | BH31: . | BI31: . | BJ31: . | BK31: . | BL31: . | BM31: 0 | BN31: . | BO31: . | BP31: . | BQ31: 0 | BR31: . | BS31: 0 | BT31: . | BU31: . | BV31: . | BW31: . | BX31: . | BY31: 0 | BZ31: . | CA31: . | CB31: . | CC31: 0 | CD31: . | CE31: 0 | CF31: . | CG31: . | CH31: . | CI31: . | CJ31: . | CK31: 0 | CL31: . | CM31: . | CN31: 0 | CO31: 0 | CP31: 0 | CQ31: 0 | CR31: 0 | CS31: 2024 | CT31: =IFERROR(INDEX(Geography!C:C, MATCH(G31, Geography!B:B, 0)), G31) -> Delaware | CU31: =IF(O31=VLOOKUP("eia923_lignite_fuel_code", Keys!$B:$C, 2, FALSE), VLOOKUP("lignite_label", Keys!$B:$C, 2, FALSE),VLOOKUP("hard_coal_label", Keys!$B:$C, 2, FALSE)) -> hard_coal
A32: 594 | B32: N | C32: . | D32: Indian River Generating Station | E32: Indian River Operations Inc | F32: 9332 | G32: DE | H32: SAT | I32: RFC | K32: 22 | L32: 2 | M32: NAICS-22 Non-Cogen | N32: ST | O32: BIT | P32: COL | Q32: PJM | R32: M | S32: short tons | T32: 13008 | U32: 0 | V32: 4754 | W32: 0 | X32: 5886 | Y32: 10807 | Z32: 19460 | AA32: 11867 | AB32: 0 | AC32: 0 | AD32: 4800 | AE32: 36709 | AF32: 13008 | AG32: 0 | AH32: 4754 | AI32: 0 | AJ32: 5886 | AK32: 10807 | AL32: 19460 | AM32: 11867 | AN32: 0 | AO32: 0 | AP32: 4800 | AQ32: 36709 | AR32: 23.38 | AS32: 0 | AT32: 23.38 | AU32: 0 | AV32: 23.382 | AW32: 23.38 | AX32: 23.38 | AY32: 23.38 | AZ32: 0 | BA32: 0 | BB32: 23.382 | BC32: 23.382 | BD32: 304127 | BE32: 0 | BF32: 111149 | BG32: 0 | BH32: 137626 | BI32: 252668 | BJ32: 454975 | BK32: 277450 | BL32: 0 | BM32: 0 | BN32: 112234 | BO32: 858330 | BP32: 304127 | BQ32: 0 | BR32: 111149 | BS32: 0 | BT32: 137626 | BU32: 252668 | BV32: 454975 | BW32: 277450 | BX32: 0 | BY32: 0 | BZ32: 112234 | CA32: 858330 | CB32: 17949.127 | CC32: -2416.514 | CD32: 7834.335 | CE32: -2278.178 | CF32: 7867.934 | CG32: 10328.004 | CH32: 26134.167 | CI32: 14428.229 | CJ32: -2113.574 | CK32: -1935.838 | CL32: 6896.807 | CM32: 61180.762 | CN32: 107291 | CO32: 107291 | CP32: 2508559 | CQ32: 2508559 | CR32: 143875.26 | CS32: 2024 | CT32: =IFERROR(INDEX(Geography!C:C, MATCH(G32, Geography!B:B, 0)), G32) -> Delaware | CU32: =IF(O32=VLOOKUP("eia923_lignite_fuel_code", Keys!$B:$C, 2, FALSE), VLOOKUP("lignite_label", Keys!$B:$C, 2, FALSE),VLOOKUP("hard_coal_label", Keys!$B:$C, 2, FALSE)) -> hard_coal
A33: 602 | B33: N | C33: . | D33: Brandon Shores | E33: Brandon Shores LLC | F33: 60421 | G33: MD | H33: SAT | I33: RFC | K33: 22 | L33: 2 | M33: NAICS-22 Non-Cogen | N33: ST | O33: BIT | P33: COL | Q33: PJM | R33: M | S33: short tons | T33: 96800 | U33: 9198 | V33: 18793 | W33: 40385 | X33: 145122 | Y33: 114795 | Z33: 172097 | AA33: 84193 | AB33: 56286 | AC33: 80071 | AD33: 25501 | AE33: 148606 | AF33: 96800 | AG33: 9198 | AH33: 18793 | AI33: 40385 | AJ33: 145122 | AK33: 114795 | AL33: 172097 | AM33: 84193 | AN33: 56286 | AO33: 80071 | AP33: 25501 | AQ33: 148606 | AR33: 26.04 | AS33: 26.04 | AT33: 26.04 | AU33: 26.04 | AV33: 25.7 | AW33: 25.7 | AX33: 25.7 | AY33: 25.7 | AZ33: 25.7 | BA33: 25.7 | BB33: 25.97 | BC33: 25.97 | BD33: 2520672 | BE33: 239516 | BF33: 489370 | BG33: 1051625 | BH33: 3729635 | BI33: 2950232 | BJ33: 4422893 | BK33: 2163760 | BL33: 1446550 | BM33: 2057825 | BN33: 662261 | BO33: 3859298 | BP33: 2520672 | BQ33: 239516 | BR33: 489370 | BS33: 1051625 | BT33: 3729635 | BU33: 2950232 | BV33: 4422893 | BW33: 2163760 | BX33: 1446550 | BY33: 2057825 | BZ33: 662261 | CA33: 3859298 | CB33: 218580.66 | CC33: 15836.47 | CD33: 36227.463 | CE33: 78702.975 | CF33: 313147.01 | CG33: 243373.2 | CH33: 385068.77 | CI33: 175937.62 | CJ33: 118135.91 | CK33: 168207.16 | CL33: 51625.763 | CM33: 334138.24 | CN33: 991847 | CO33: 991847 | CP33: 25593637 | CQ33: 25593637 | CR33: 2138981.2 | CS33: 2024 | CT33: =IFERROR(INDEX(Geography!C:C, MATCH(G33, Geography!B:B, 0)), G33) -> Maryland | CU33: =IF(O33=VLOOKUP("eia923_lignite_fuel_code", Keys!$B:$C, 2, FALSE), VLOOKUP("lignite_label", Keys!$B:$C, 2, FALSE),VLOOKUP("hard_coal_label", Keys!$B:$C, 2, FALSE)) -> hard_coal
A34: 602 | B34: N | C34: . | D34: Brandon Shores | E34: Brandon Shores LLC | F34: 60421 | G34: MD | H34: SAT | I34: RFC | K34: 22 | L34: 2 | M34: NAICS-22 Non-Cogen | N34: ST | O34: RC | P34: COL | Q34: PJM | R34: M | S34: short tons | T34: 0 | U34: 0 | V34: 0 | W34: 0 | X34: 0 | Y34: 0 | Z34: 0 | AA34: 0 | AB34: 0 | AC34: 0 | AD34: 0 | AE34: 0 | AF34: 0 | AG34: 0 | AH34: 0 | AI34: 0 | AJ34: 0 | AK34: 0 | AL34: 0 | AM34: 0 | AN34: 0 | AO34: 0 | AP34: 0 | AQ34: 0 | AR34: 0 | AS34: 0 | AT34: 0 | AU34: 0 | AV34: 0 | AW34: 0 | AX34: 0 | AY34: 0 | AZ34: 0 | BA34: 0 | BB34: 0 | BC34: 0 | BD34: 0 | BE34: 0 | BF34: 0 | BG34: 0 | BH34: 0 | BI34: 0 | BJ34: 0 | BK34: 0 | BL34: 0 | BM34: 0 | BN34: 0 | BO34: 0 | BP34: 0 | BQ34: 0 | BR34: 0 | BS34: 0 | BT34: 0 | BU34: 0 | BV34: 0 | BW34: 0 | BX34: 0 | BY34: 0 | BZ34: 0 | CA34: 0 | CB34: 0 | CC34: 0 | CD34: 0 | CE34: 0 | CF34: 0 | CG34: 0 | CH34: 0 | CI34: 0 | CJ34: 0 | CK34: 0 | CL34: 0 | CM34: 0 | CN34: 0 | CO34: 0 | CP34: 0 | CQ34: 0 | CR34: 0 | CS34: 2024 | CT34: =IFERROR(INDEX(Geography!C:C, MATCH(G34, Geography!B:B, 0)), G34) -> Maryland | CU34: =IF(O34=VLOOKUP("eia923_lignite_fuel_code", Keys!$B:$C, 2, FALSE), VLOOKUP("lignite_label", Keys!$B:$C, 2, FALSE),VLOOKUP("hard_coal_label", Keys!$B:$C, 2, FALSE)) -> hard_coal
A35: 628 | B35: N | C35: . | D35: Crystal River | E35: Duke Energy Florida, LLC | F35: 6455 | G35: FL | H35: SAT | I35: SERC | K35: 22 | L35: 1 | M35: Electric Utility | N35: ST | O35: BIT | P35: COL | Q35: FPC | R35: M | S35: short tons | T35: 148920 | U35: 68704 | V35: 64784 | W35: 108448 | X35: 165069 | Y35: 255005 | Z35: 259754 | AA35: 205440 | AB35: 197410 | AC35: 0 | AD35: 39927 | AE35: 103273 | AF35: 148920 | AG35: 68704 | AH35: 64784 | AI35: 108448 | AJ35: 165069 | AK35: 255005 | AL35: 259754 | AM35: 205440 | AN35: 197410 | AO35: 0 | AP35: 39927 | AQ35: 103273 | AR35: 22.73 | AS35: 22.078 | AT35: 21.976 | AU35: 22.444 | AV35: 22.224 | AW35: 22.23 | AX35: 22.23 | AY35: 22.432 | AZ35: 22.292 | BA35: 0 | BB35: 22.432 | BC35: 22.31 | BD35: 3384952 | BE35: 1516847 | BF35: 1423693 | BG35: 2434007 | BH35: 3668493 | BI35: 5668761 | BJ35: 5774331 | BK35: 4608430 | BL35: 4400664 | BM35: 0 | BN35: 895642 | BO35: 2304021 | BP35: 3384952 | BQ35: 1516847 | BR35: 1423693 | BS35: 2434007 | BT35: 3668493 | BU35: 5668761 | BV35: 5774331 | BW35: 4608430 | BX35: 4400664 | BY35: 0 | BZ35: 895642 | CA35: 2304021 | CB35: 323311.47 | CC35: 139803.75 | CD35: 125637.75 | CE35: 208702.11 | CF35: 272406.94 | CG35: 541236.86 | CH35: 538100.01 | CI35: 411028.5 | CJ35: 404399.21 | CK35: 0 | CL35: 65282.372 | CM35: 209766.16 | CN35: 1616734 | CO35: 1616734 | CP35: 36079841 | CQ35: 36079841 | CR35: 3239675.1 | CS35: 2024 | CT35: =IFERROR(INDEX(Geography!C:C, MATCH(G35, Geography!B:B, 0)), G35) -> Florida | CU35: =IF(O35=VLOOKUP("eia923_lignite_fuel_code", Keys!$B:$C, 2, FALSE), VLOOKUP("lignite_label", Keys!$B:$C, 2, FALSE),VLOOKUP("hard_coal_label", Keys!$B:$C, 2, FALSE)) -> hard_coal
A36: 641 | B36: N | C36: . | D36: Gulf Clean Energy Center | E36: Florida Power & Light Co | F36: 6452 | G36: FL | H36: SAT | I36: SERC | K36: 22 | L36: 1 | M36: Electric Utility | N36: ST | O36: BIT | P36: COL | Q36: FPL | R36: M | S36: short tons | T36: 0 | U36: 0 | V36: 0 | W36: 0 | X36: 0 | Y36: 0 | Z36: 0 | AA36: 0 | AB36: 0 | AC36: 0 | AD36: 0 | AE36: 0 | AF36: 0 | AG36: 0 | AH36: 0 | AI36: 0 | AJ36: 0 | AK36: 0 | AL36: 0 | AM36: 0 | AN36: 0 | AO36: 0 | AP36: 0 | AQ36: 0 | AR36: 0 | AS36: 0 | AT36: 0 | AU36: 0 | AV36: 0 | AW36: 0 | AX36: 0 | AY36: 0 | AZ36: 0 | BA36: 0 | BB36: 0 | BC36: 0 | BD36: 0 | BE36: 0 | BF36: 0 | BG36: 0 | BH36: 0 | BI36: 0 | BJ36: 0 | BK36: 0 | BL36: 0 | BM36: 0 | BN36: 0 | BO36: 0 | BP36: 0 | BQ36: 0 | BR36: 0 | BS36: 0 | BT36: 0 | BU36: 0 | BV36: 0 | BW36: 0 | BX36: 0 | BY36: 0 | BZ36: 0 | CA36: 0 | CB36: 0 | CC36: 0 | CD36: 0 | CE36: 0 | CF36: 0 | CG36: 0 | CH36: 0 | CI36: 0 | CJ36: 0 | CK36: 0 | CL36: 0 | CM36: 0 | CN36: 0 | CO36: 0 | CP36: 0 | CQ36: 0 | CR36: 0 | CS36: 2024 | CT36: =IFERROR(INDEX(Geography!C:C, MATCH(G36, Geography!B:B, 0)), G36) -> Florida | CU36: =IF(O36=VLOOKUP("eia923_lignite_fuel_code", Keys!$B:$C, 2, FALSE), VLOOKUP("lignite_label", Keys!$B:$C, 2, FALSE),VLOOKUP("hard_coal_label", Keys!$B:$C, 2, FALSE)) -> hard_coal
A37: 645 | B37: N | C37: . | D37: Big Bend | E37: Tampa Electric Co | F37: 18454 | G37: FL | H37: SAT | I37: SERC | K37: 22 | L37: 1 | M37: Electric Utility | N37: ST | O37: BIT | P37: COL | Q37: TEC | R37: M | S37: short tons | T37: 15647 | U37: 0 | V37: 0 | W37: 0 | X37: 0 | Y37: 0 | Z37: 0 | AA37: 0 | AB37: 9542 | AC37: 0 | AD37: 0 | AE37: 0 | AF37: 15647 | AG37: 0 | AH37: 0 | AI37: 0 | AJ37: 0 | AK37: 0 | AL37: 0 | AM37: 0 | AN37: 9542 | AO37: 0 | AP37: 0 | AQ37: 0 | AR37: 22.406 | AS37: 0 | AT37: 0 | AU37: 0 | AV37: 0 | AW37: 0 | AX37: 0 | AY37: 0 | AZ37: 22.17 | BA37: 0 | BB37: 0 | BC37: 0 | BD37: 350587 | BE37: 0 | BF37: 0 | BG37: 0 | BH37: 0 | BI37: 0 | BJ37: 0 | BK37: 0 | BL37: 211546 | BM37: 0 | BN37: 0 | BO37: 0 | BP37: 350587 | BQ37: 0 | BR37: 0 | BS37: 0 | BT37: 0 | BU37: 0 | BV37: 0 | BW37: 0 | BX37: 211546 | BY37: 0 | BZ37: 0 | CA37: 0 | CB37: 32875.155 | CC37: 0 | CD37: 0 | CE37: 0 | CF37: 0 | CG37: 0 | CH37: 0 | CI37: 0 | CJ37: 17503.042 | CK37: 0 | CL37: 0 | CM37: 0 | CN37: 25189 | CO37: 25189 | CP37: 562133 | CQ37: 562133 | CR37: 50378.197 | CS37: 2024 | CT37: =IFERROR(INDEX(Geography!C:C, MATCH(G37, Geography!B:B, 0)), G37) -> Florida | CU37: =IF(O37=VLOOKUP("eia923_lignite_fuel_code", Keys!$B:$C, 2, FALSE), VLOOKUP("lignite_label", Keys!$B:$C, 2, FALSE),VLOOKUP("hard_coal_label", Keys!$B:$C, 2, FALSE)) -> hard_coal
A38: 663 | B38: N | C38: . | D38: Deerhaven Generating Station | E38: Gainesville Regional Utilities | F38: 6909 | G38: FL | H38: SAT | I38: SERC | K38: 22 | L38: 1 | M38: Electric Utility | N38: ST | O38: BIT | P38: COL | Q38: GVL | R38: M | S38: short tons | T38: 238 | U38: 239 | V38: 0 | W38: 0 | X38: 0 | Y38: 0 | Z38: 47 | AA38: 28 | AB38: 54 | AC38: 31 | AD38: 20 | AE38: 62 | AF38: 238 | AG38: 239 | AH38: 0 | AI38: 0 | AJ38: 0 | AK38: 0 | AL38: 47 | AM38: 28 | AN38: 54 | AO38: 31 | AP38: 20 | AQ38: 62 | AR38: 25.162 | AS38: 25.162 | AT38: 0 | AU38: 0 | AV38: 0 | AW38: 0 | AX38: 25.162 | AY38: 25.162 | AZ38: 25.162 | BA38: 25.162 | BB38: 25.162 | BC38: 25.16 | BD38: 5989 | BE38: 6014 | BF38: 0 | BG38: 0 | BH38: 0 | BI38: 0 | BJ38: 1183 | BK38: 705 | BL38: 1359 | BM38: 780 | BN38: 503 | BO38: 1560 | BP38: 5989 | BQ38: 6014 | BR38: 0 | BS38: 0 | BT38: 0 | BU38: 0 | BV38: 1183 | BW38: 705 | BX38: 1359 | BY38: 780 | BZ38: 503 | CA38: 1560 | CB38: 509.479 | CC38: 499.305 | CD38: 0 | CE38: 0 | CF38: 0 | CG38: 0 | CH38: 91.989 | CI38: 57.159 | CJ38: 110.537 | CK38: 61.622 | CL38: 38.637 | CM38: 116.556 | CN38: 719 | CO38: 719 | CP38: 18093 | CQ38: 18093 | CR38: 1485.284 | CS38: 2024 | CT38: =IFERROR(INDEX(Geography!C:C, MATCH(G38, Geography!B:B, 0)), G38) -> Florida | CU38: =IF(O38=VLOOKUP("eia923_lignite_fuel_code", Keys!$B:$C, 2, FALSE), VLOOKUP("lignite_label", Keys!$B:$C, 2, FALSE),VLOOKUP("hard_coal_label", Keys!$B:$C, 2, FALSE)) -> hard_coal
A39: 667 | B39: N | C39: . | D39: Northside Generating Station | E39: JEA | F39: 9617 | G39: FL | H39: SAT | I39: SERC | K39: 22 | L39: 1 | M39: Electric Utility | N39: ST | O39: BIT | P39: COL | Q39: JEA | R39: M | S39: short tons | T39: 2133 | U39: 1660 | V39: 694 | W39: 2011 | X39: 3614 | Y39: 13548 | Z39: 16358 | AA39: 19978 | AB39: 3702 | AC39: 192 | AD39: 4721 | AE39: 4228 | AF39: 2133 | AG39: 1660 | AH39: 694 | AI39: 2011 | AJ39: 3614 | AK39: 13548 | AL39: 16358 | AM39: 19978 | AN39: 3702 | AO39: 192 | AP39: 4721 | AQ39: 4228 | AR39: 21.846 | AS39: 21.833 | AT39: 21.827 | AU39: 21.823 | AV39: 21.822 | AW39: 21.821 | AX39: 21.201 | AY39: 21.896 | AZ39: 22.243 | BA39: 22.243 | BB39: 22.503 | BC39: 22.547 | BD39: 46598 | BE39: 36243 | BF39: 15148 | BG39: 43886 | BH39: 78865 | BI39: 295631 | BJ39: 346806 | BK39: 437438 | BL39: 82344 | BM39: 4271 | BN39: 106237 | BO39: 95329 | BP39: 46598 | BQ39: 36243 | BR39: 15148 | BS39: 43886 | BT39: 78865 | BU39: 295631 | BV39: 346806 | BW39: 437438 | BX39: 82344 | BY39: 4271 | BZ39: 106237 | CA39: 95329 | CB39: 4053.956 | CC39: 3089.25 | CD39: 1305.498 | CE39: 3976.828 | CF39: 6425.597 | CG39: 26152.163 | CH39: 30697.118 | CI39: 38406.257 | CJ39: 7520.382 | CK39: 363.049 | CL39: 6908.354 | CM39: 8375.9 | CN39: 72839 | CO39: 72839 | CP39: 1588796 | CQ39: 1588796 | CR39: 137274.35 | CS39: 2024 | CT39: =IFERROR(INDEX(Geography!C:C, MATCH(G39, Geography!B:B, 0)), G39) -> Florida | CU39: =IF(O39=VLOOKUP("eia923_lignite_fuel_code", Keys!$B:$C, 2, FALSE), VLOOKUP("lignite_label", Keys!$B:$C, 2, FALSE),VLOOKUP("hard_coal_label", Keys!$B:$C, 2, FALSE)) -> hard_coal
A40: 703 | B40: N | C40: . | D40: Bowen | E40: Georgia Power Co | F40: 7140 | G40: GA | H40: SAT | I40: SERC | K40: 22 | L40: 1 | M40: Electric Utility | N40: ST | O40: BIT | P40: COL | Q40: SOCO | R40: M | S40: short tons | T40: 495861 | U40: 296992 | V40: 180931 | W40: 282151 | X40: 298524 | Y40: 542600 | Z40: 589629 | AA40: 573855 | AB40: 441747 | AC40: 255710 | AD40: 206128 | AE40: 308033 | AF40: 495861 | AG40: 296992 | AH40: 180931 | AI40: 282151 | AJ40: 298524 | AK40: 542600 | AL40: 589629 | AM40: 573855 | AN40: 441747 | AO40: 255710 | AP40: 206128 | AQ40: 308033 | AR40: 23.617 | AS40: 23.325 | AT40: 23.364 | AU40: 23.581 | AV40: 23.689 | AW40: 24.015 | AX40: 23.755 | AY40: 24.178 | AZ40: 23.687 | BA40: 23.907 | BB40: 23.759 | BC40: 23.805 | BD40: 11710749 | BE40: 6927338 | BF40: 4227272 | BG40: 6653403 | BH40: 7071735 | BI40: 13030539 | BJ40: 14006637 | BK40: 13874666 | BL40: 10463661 | BM40: 6113259 | BN40: 4897395 | BO40: 7332726 | BP40: 11710749 | BQ40: 6927338 | BR40: 4227272 | BS40: 6653403 | BT40: 7071735 | BU40: 13030539 | BV40: 14006637 | BW40: 13874666 | BX40: 10463661 | BY40: 6113259 | BZ40: 4897395 | CA40: 7332726 | CB40: 1179255.3 | CC40: 713102.62 | CD40: 429265.43 | CE40: 695790.44 | CF40: 720833.82 | CG40: 1328956.4 | CH40: 1391009.1 | CI40: 1383015.2 | CJ40: 1050522.8 | CK40: 592226.64 | CL40: 486637.38 | CM40: 723906.3 | CN40: 4472161 | CO40: 4472161 | CP40: 106309380 | CQ40: 106309380 | CR40: 10694521 | CS40: 2024 | CT40: =IFERROR(INDEX(Geography!C:C, MATCH(G40, Geography!B:B, 0)), G40) -> Georgia | CU40: =IF(O40=VLOOKUP("eia923_lignite_fuel_code", Keys!$B:$C, 2, FALSE), VLOOKUP("lignite_label", Keys!$B:$C, 2, FALSE),VLOOKUP("hard_coal_label", Keys!$B:$C, 2, FALSE)) -> hard_coal
A41: 703 | B41: N | C41: . | D41: Bowen | E41: Georgia Power Co | F41: 7140 | G41: GA | H41: SAT | I41: SERC | K41: 22 | L41: 1 | M41: Electric Utility | N41: ST | O41: SUB | P41: COL | Q41: SOCO | R41: M | S41: short tons | T41: . | U41: 0 | V41: 0 | W41: . | X41: . | Y41: . | Z41: . | AA41: . | AB41: . | AC41: . | AD41: . | AE41: . | AF41: . | AG41: 0 | AH41: 0 | AI41: . | AJ41: . | AK41: . | AL41: . | AM41: . | AN41: . | AO41: . | AP41: . | AQ41: . | AR41: . | AS41: 0 | AT41: 0 | AU41: . | AV41: . | AW41: . | AX41: . | AY41: . | AZ41: . | BA41: . | BB41: . | BC41: . | BD41: . | BE41: 0 | BF41: 0 | BG41: . | BH41: . | BI41: . | BJ41: . | BK41: . | BL41: . | BM41: . | BN41: . | BO41: . | BP41: . | BQ41: 0 | BR41: 0 | BS41: . | BT41: . | BU41: . | BV41: . | BW41: . | BX41: . | BY41: . | BZ41: . | CA41: . | CB41: . | CC41: 0 | CD41: 0 | CE41: . | CF41: . | CG41: . | CH41: . | CI41: . | CJ41: . | CK41: . | CL41: . | CM41: . | CN41: 0 | CO41: 0 | CP41: 0 | CQ41: 0 | CR41: 0 | CS41: 2024 | CT41: =IFERROR(INDEX(Geography!C:C, MATCH(G41, Geography!B:B, 0)), G41) -> Georgia | CU41: =IF(O41=VLOOKUP("eia923_lignite_fuel_code", Keys!$B:$C, 2, FALSE), VLOOKUP("lignite_label", Keys!$B:$C, 2, FALSE),VLOOKUP("hard_coal_label", Keys!$B:$C, 2, FALSE)) -> hard_coal
A42: 753 | B42: N | C42: . | D42: Crisp Plant | E42: Crisp County Power Comm | F42: 4538 | G42: GA | H42: SAT | I42: SERC | K42: 22 | L42: 1 | M42: Electric Utility | N42: ST | O42: BIT | P42: COL | Q42: SOCO | R42: AM | S42: short tons | T42: 0 | U42: 0 | V42: 0 | W42: 0 | X42: 0 | Y42: 0 | Z42: 0 | AA42: 0 | AB42: 0 | AC42: 0 | AD42: 0 | AE42: 0 | AF42: 0 | AG42: 0 | AH42: 0 | AI42: 0 | AJ42: 0 | AK42: 0 | AL42: 0 | AM42: 0 | AN42: 0 | AO42: 0 | AP42: 0 | AQ42: 0 | AR42: 0 | AS42: 0 | AT42: 0 | AU42: 0 | AV42: 0 | AW42: 0 | AX42: 0 | AY42: 0 | AZ42: 0 | BA42: 0 | BB42: 0 | BC42: 0 | BD42: 0 | BE42: 0 | BF42: 0 | BG42: 0 | BH42: 0 | BI42: 0 | BJ42: 0 | BK42: 0 | BL42: 0 | BM42: 0 | BN42: 0 | BO42: 0 | BP42: 0 | BQ42: 0 | BR42: 0 | BS42: 0 | BT42: 0 | BU42: 0 | BV42: 0 | BW42: 0 | BX42: 0 | BY42: 0 | BZ42: 0 | CA42: 0 | CB42: 0 | CC42: 0 | CD42: 0 | CE42: 0 | CF42: 0 | CG42: 0 | CH42: 0 | CI42: 0 | CJ42: 0 | CK42: 0 | CL42: 0 | CM42: 0 | CN42: 0 | CO42: 0 | CP42: 0 | CQ42: 0 | CR42: 0 | CS42: 2024 | CT42: =IFERROR(INDEX(Geography!C:C, MATCH(G42, Geography!B:B, 0)), G42) -> Georgia | CU42: =IF(O42=VLOOKUP("eia923_lignite_fuel_code", Keys!$B:$C, 2, FALSE), VLOOKUP("lignite_label", Keys!$B:$C, 2, FALSE),VLOOKUP("hard_coal_label", Keys!$B:$C, 2, FALSE)) -> hard_coal
A43: 876 | B43: N | C43: . | D43: Kincaid Generation LLC | E43: Dynegy Kincaid Generation | F43: 59918 | G43: IL | H43: ENC | I43: RFC | K43: 22 | L43: 2 | M43: NAICS-22 Non-Cogen | N43: ST | O43: RC | P43: COL | Q43: PJM | R43: M | S43: short tons | T43: 0 | U43: 0 | V43: 0 | W43: 0 | X43: 0 | Y43: 0 | Z43: 0 | AA43: 0 | AB43: 0 | AC43: 0 | AD43: 0 | AE43: 0 | AF43: 0 | AG43: 0 | AH43: 0 | AI43: 0 | AJ43: 0 | AK43: 0 | AL43: 0 | AM43: 0 | AN43: 0 | AO43: 0 | AP43: 0 | AQ43: 0 | AR43: 0 | AS43: 0 | AT43: 0 | AU43: 0 | AV43: 0 | AW43: 0 | AX43: 0 | AY43: 0 | AZ43: 0 | BA43: 0 | BB43: 0 | BC43: 0 | BD43: 0 | BE43: 0 | BF43: 0 | BG43: 0 | BH43: 0 | BI43: 0 | BJ43: 0 | BK43: 0 | BL43: 0 | BM43: 0 | BN43: 0 | BO43: 0 | BP43: 0 | BQ43: 0 | BR43: 0 | BS43: 0 | BT43: 0 | BU43: 0 | BV43: 0 | BW43: 0 | BX43: 0 | BY43: 0 | BZ43: 0 | CA43: 0 | CB43: 0 | CC43: 0 | CD43: 0 | CE43: 0 | CF43: 0 | CG43: 0 | CH43: 0 | CI43: 0 | CJ43: 0 | CK43: 0 | CL43: 0 | CM43: 0 | CN43: 0 | CO43: 0 | CP43: 0 | CQ43: 0 | CR43: 0 | CS43: 2024 | CT43: =IFERROR(INDEX(Geography!C:C, MATCH(G43, Geography!B:B, 0)), G43) -> Illinois | CU43: =IF(O43=VLOOKUP("eia923_lignite_fuel_code", Keys!$B:$C, 2, FALSE), VLOOKUP("lignite_label", Keys!$B:$C, 2, FALSE),VLOOKUP("hard_coal_label", Keys!$B:$C, 2, FALSE)) -> hard_coal
A44: 876 | B44: N | C44: . | D44: Kincaid Generation LLC | E44: Dynegy Kincaid Generation | F44: 59918 | G44: IL | H44: ENC | I44: RFC | K44: 22 | L44: 2 | M44: NAICS-22 Non-Cogen | N44: ST | O44: SUB | P44: COL | Q44: PJM | R44: M | S44: short tons | T44: 171109 | U44: 0 | V44: 0 | W44: 8090 | X44: 75798 | Y44: 210372 | Z44: 237655 | AA44: 206395 | AB44: 145303 | AC44: 115941 | AD44: 89498 | AE44: 209128 | AF44: 171109 | AG44: 0 | AH44: 0 | AI44: 8090 | AJ44: 75798 | AK44: 210372 | AL44: 237655 | AM44: 206395 | AN44: 145303 | AO44: 115941 | AP44: 89498 | AQ44: 209128 | AR44: 17.821 | AS44: 0 | AT44: 0 | AU44: 17.742 | AV44: 17.622 | AW44: 17.71 | AX44: 17.918 | AY44: 17.786 | AZ44: 17.832 | BA44: 17.802 | BB44: 17.816 | BC44: 17.812 | BD44: 3049333 | BE44: 0 | BF44: 0 | BG44: 143533 | BH44: 1335712 | BI44: 3725688 | BJ44: 4258302 | BK44: 3670941 | BL44: 2591043 | BM44: 2063982 | BN44: 1594496 | BO44: 3724988 | BP44: 3049333 | BQ44: 0 | BR44: 0 | BS44: 143533 | BT44: 1335712 | BU44: 3725688 | BV44: 4258302 | BW44: 3670941 | BX44: 2591043 | BY44: 2063982 | BZ44: 1594496 | CA44: 3724988 | CB44: 253378.92 | CC44: 0 | CD44: 0 | CE44: 6636.505 | CF44: 104160.38 | CG44: 300600.24 | CH44: 369558.99 | CI44: 309490.33 | CJ44: 254851.18 | CK44: 167233.54 | CL44: 131449.37 | CM44: 300495.67 | CN44: 1469289 | CO44: 1469289 | CP44: 26158018 | CQ44: 26158018 | CR44: 2197855.1 | CS44: 2024 | CT44: =IFERROR(INDEX(Geography!C:C, MATCH(G44, Geography!B:B, 0)), G44) -> Illinois | CU44: =IF(O44=VLOOKUP("eia923_lignite_fuel_code", Keys!$B:$C, 2, FALSE), VLOOKUP("lignite_label", Keys!$B:$C, 2, FALSE),VLOOKUP("hard_coal_label", Keys!$B:$C, 2, FALSE)) -> hard_coal
A45: 879 | B45: N | C45: . | D45: Powerton | E45: Midwest Generations EME LLC | F45: 12384 | G45: IL | H45: ENC | I45: RFC | K45: 22 | L45: 2 | M45: NAICS-22 Non-Cogen | N45: ST | O45: BIT | P45: COL | Q45: PJM | R45: M | S45: short tons | T45: 0 | U45: 0 | V45: 0 | W45: 0 | X45: 0 | Y45: 0 | Z45: 0 | AA45: 0 | AB45: 0 | AC45: 0 | AD45: 0 | AE45: 0 | AF45: 0 | AG45: 0 | AH45: 0 | AI45: 0 | AJ45: 0 | AK45: 0 | AL45: 0 | AM45: 0 | AN45: 0 | AO45: 0 | AP45: 0 | AQ45: 0 | AR45: 0 | AS45: 0 | AT45: 0 | AU45: 0 | AV45: 0 | AW45: 0 | AX45: 0 | AY45: 0 | AZ45: 0 | BA45: 0 | BB45: 0 | BC45: 0 | BD45: 0 | BE45: 0 | BF45: 0 | BG45: 0 | BH45: 0 | BI45: 0 | BJ45: 0 | BK45: 0 | BL45: 0 | BM45: 0 | BN45: 0 | BO45: 0 | BP45: 0 | BQ45: 0 | BR45: 0 | BS45: 0 | BT45: 0 | BU45: 0 | BV45: 0 | BW45: 0 | BX45: 0 | BY45: 0 | BZ45: 0 | CA45: 0 | CB45: 0 | CC45: 0 | CD45: 0 | CE45: 0 | CF45: 0 | CG45: 0 | CH45: 0 | CI45: 0 | CJ45: 0 | CK45: 0 | CL45: 0 | CM45: 0 | CN45: 0 | CO45: 0 | CP45: 0 | CQ45: 0 | CR45: 0 | CS45: 2024 | CT45: =IFERROR(INDEX(Geography!C:C, MATCH(G45, Geography!B:B, 0)), G45) -> Illinois | CU45: =IF(O45=VLOOKUP("eia923_lignite_fuel_code", Keys!$B:$C, 2, FALSE), VLOOKUP("lignite_label", Keys!$B:$C, 2, FALSE),VLOOKUP("hard_coal_label", Keys!$B:$C, 2, FALSE)) -> hard_coal
A46: 879 | B46: N | C46: . | D46: Powerton | E46: Midwest Generations EME LLC | F46: 12384 | G46: IL | H46: ENC | I46: RFC | K46: 22 | L46: 2 | M46: NAICS-22 Non-Cogen | N46: ST | O46: SUB | P46: COL | Q46: PJM | R46: M | S46: short tons | T46: 238472 | U46: 24920 | V46: 212 | W46: 26420 | X46: 95336 | Y46: 310948 | Z46: 257084 | AA46: 429374 | AB46: 101292 | AC46: 0 | AD46: 20368 | AE46: 252880 | AF46: 238472 | AG46: 24920 | AH46: 212 | AI46: 26420 | AJ46: 95336 | AK46: 310948 | AL46: 257084 | AM46: 429374 | AN46: 101292 | AO46: 0 | AP46: 20368 | AQ46: 252880 | AR46: 17 | AS46: 17 | AT46: 16.89 | AU46: 17 | AV46: 17 | AW46: 17 | AX46: 17 | AY46: 16.89 | AZ46: 17 | BA46: 0 | BB46: 17 | BC46: 17 | BD46: 4054024 | BE46: 423640 | BF46: 3581 | BG46: 449140 | BH46: 1620712 | BI46: 5286116 | BJ46: 4370428 | BK46: 7252127 | BL46: 1721964 | BM46: 0 | BN46: 346256 | BO46: 4298960 | BP46: 4054024 | BQ46: 423640 | BR46: 3581 | BS46: 449140 | BT46: 1620712 | BU46: 5286116 | BV46: 4370428 | BW46: 7252127 | BX46: 1721964 | BY46: 0 | BZ46: 346256 | CA46: 4298960 | CB46: 347136.32 | CC46: 26992.789 | CD46: -8054 | CE46: 21654.894 | CF46: 117413.35 | CG46: 418263.4 | CH46: 318531.27 | CI46: 562120.06 | CJ46: 117072.76 | CK46: -5624.096 | CL46: 2114.363 | CM46: 295639.26 | CN46: 1757306 | CO46: 1757306 | CP46: 29826948 | CQ46: 29826948 | CR46: 2213260.4 | CS46: 2024 | CT46: =IFERROR(INDEX(Geography!C:C, MATCH(G46, Geography!B:B, 0)), G46) -> Illinois | CU46: =IF(O46=VLOOKUP("eia923_lignite_fuel_code", Keys!$B:$C, 2, FALSE), VLOOKUP("lignite_label", Keys!$B:$C, 2, FALSE),VLOOKUP("hard_coal_label", Keys!$B:$C, 2, FALSE)) -> hard_coal
A47: 883 | B47: N | C47: . | D47: Waukegan | E47: Midwest Generations EME LLC | F47: 12384 | G47: IL | H47: ENC | I47: RFC | K47: 22 | L47: 2 | M47: NAICS-22 Non-Cogen | N47: GT | O47: SUB | P47: COL | Q47: PJM | R47: M | S47: short tons | T47: . | U47: 0 | V47: . | W47: 0 | X47: 0 | Y47: 0 | Z47: . | AA47: . | AB47: 0 | AC47: 0 | AD47: . | AE47: . | AF47: . | AG47: 0 | AH47: . | AI47: 0 | AJ47: 0 | AK47: 0 | AL47: . | AM47: . | AN47: 0 | AO47: 0 | AP47: . | AQ47: . | AR47: . | AS47: 0 | AT47: . | AU47: 0 | AV47: 0 | AW47: 0 | AX47: . | AY47: . | AZ47: 0 | BA47: 0 | BB47: . | BC47: . | BD47: . | BE47: 0 | BF47: . | BG47: 0 | BH47: 0 | BI47: 0 | BJ47: . | BK47: . | BL47: 0 | BM47: 0 | BN47: . | BO47: . | BP47: . | BQ47: 0 | BR47: . | BS47: 0 | BT47: 0 | BU47: 0 | BV47: . | BW47: . | BX47: 0 | BY47: 0 | BZ47: . | CA47: . | CB47: . | CC47: 0 | CD47: . | CE47: 0 | CF47: 0 | CG47: 0 | CH47: . | CI47: . | CJ47: 0 | CK47: 0 | CL47: . | CM47: . | CN47: 0 | CO47: 0 | CP47: 0 | CQ47: 0 | CR47: 0 | CS47: 2024 | CT47: =IFERROR(INDEX(Geography!C:C, MATCH(G47, Geography!B:B, 0)), G47) -> Illinois | CU47: =IF(O47=VLOOKUP("eia923_lignite_fuel_code", Keys!$B:$C, 2, FALSE), VLOOKUP("lignite_label", Keys!$B:$C, 2, FALSE),VLOOKUP("hard_coal_label", Keys!$B:$C, 2, FALSE)) -> hard_coal
A48: 886 | B48: N | C48: . | D48: Fisk Street | E48: Midwest Generations EME LLC | F48: 12384 | G48: IL | H48: ENC | I48: RFC | K48: 22 | L48: 2 | M48: NAICS-22 Non-Cogen | N48: GT | O48: SUB | P48: COL | Q48: PJM | R48: A | S48: short tons | T48: 0 | U48: 0 | V48: 0 | W48: 0 | X48: 0 | Y48: 0 | Z48: 0 | AA48: 0 | AB48: 0 | AC48: 0 | AD48: 0 | AE48: 0 | AF48: 0 | AG48: 0 | AH48: 0 | AI48: 0 | AJ48: 0 | AK48: 0 | AL48: 0 | AM48: 0 | AN48: 0 | AO48: 0 | AP48: 0 | AQ48: 0 | AR48: 0 | AS48: 0 | AT48: 0 | AU48: 0 | AV48: 0 | AW48: 0 | AX48: 0 | AY48: 0 | AZ48: 0 | BA48: 0 | BB48: 0 | BC48: 0 | BD48: 0 | BE48: 0 | BF48: 0 | BG48: 0 | BH48: 0 | BI48: 0 | BJ48: 0 | BK48: 0 | BL48: 0 | BM48: 0 | BN48: 0 | BO48: 0 | BP48: 0 | BQ48: 0 | BR48: 0 | BS48: 0 | BT48: 0 | BU48: 0 | BV48: 0 | BW48: 0 | BX48: 0 | BY48: 0 | BZ48: 0 | CA48: 0 | CB48: 0 | CC48: 0 | CD48: 0 | CE48: 0 | CF48: 0 | CG48: 0 | CH48: 0 | CI48: 0 | CJ48: 0 | CK48: 0 | CL48: 0 | CM48: 0 | CN48: 0 | CO48: 0 | CP48: 0 | CQ48: 0 | CR48: 0 | CS48: 2024 | CT48: =IFERROR(INDEX(Geography!C:C, MATCH(G48, Geography!B:B, 0)), G48) -> Illinois | CU48: =IF(O48=VLOOKUP("eia923_lignite_fuel_code", Keys!$B:$C, 2, FALSE), VLOOKUP("lignite_label", Keys!$B:$C, 2, FALSE),VLOOKUP("hard_coal_label", Keys!$B:$C, 2, FALSE)) -> hard_coal
A49: 889 | B49: N | C49: . | D49: Baldwin Energy Complex | E49: Dynegy Midwest Generation Inc | F49: 5517 | G49: IL | H49: ENC | I49: SERC | K49: 22 | L49: 2 | M49: NAICS-22 Non-Cogen | N49: ST | O49: RC | P49: COL | Q49: MISO | R49: M | S49: short tons | T49: 0 | U49: 0 | V49: 0 | W49: 0 | X49: 0 | Y49: 0 | Z49: 0 | AA49: 0 | AB49: 0 | AC49: 0 | AD49: 0 | AE49: 0 | AF49: 0 | AG49: 0 | AH49: 0 | AI49: 0 | AJ49: 0 | AK49: 0 | AL49: 0 | AM49: 0 | AN49: 0 | AO49: 0 | AP49: 0 | AQ49: 0 | AR49: 0 | AS49: 0 | AT49: 0 | AU49: 0 | AV49: 0 | AW49: 0 | AX49: 0 | AY49: 0 | AZ49: 0 | BA49: 0 | BB49: 0 | BC49: 0 | BD49: 0 | BE49: 0 | BF49: 0 | BG49: 0 | BH49: 0 | BI49: 0 | BJ49: 0 | BK49: 0 | BL49: 0 | BM49: 0 | BN49: 0 | BO49: 0 | BP49: 0 | BQ49: 0 | BR49: 0 | BS49: 0 | BT49: 0 | BU49: 0 | BV49: 0 | BW49: 0 | BX49: 0 | BY49: 0 | BZ49: 0 | CA49: 0 | CB49: 0 | CC49: 0 | CD49: 0 | CE49: 0 | CF49: 0 | CG49: 0 | CH49: 0 | CI49: 0 | CJ49: 0 | CK49: 0 | CL49: 0 | CM49: 0 | CN49: 0 | CO49: 0 | CP49: 0 | CQ49: 0 | CR49: 0 | CS49: 2024 | CT49: =IFERROR(INDEX(Geography!C:C, MATCH(G49, Geography!B:B, 0)), G49) -> Illinois | CU49: =IF(O49=VLOOKUP("eia923_lignite_fuel_code", Keys!$B:$C, 2, FALSE), VLOOKUP("lignite_label", Keys!$B:$C, 2, FALSE),VLOOKUP("hard_coal_label", Keys!$B:$C, 2, FALSE)) -> hard_coal
A50: 889 | B50: N | C50: . | D50: Baldwin Energy Complex | E50: Dynegy Midwest Generation Inc | F50: 5517 | G50: IL | H50: ENC | I50: SERC | K50: 22 | L50: 2 | M50: NAICS-22 Non-Cogen | N50: ST | O50: SUB | P50: COL | Q50: MISO | R50: M | S50: short tons | T50: 428090 | U50: 235566 | V50: 124517 | W50: 321191 | X50: 371183 | Y50: 402180 | Z50: 347204 | AA50: 388960 | AB50: 319359 | AC50: 312917 | AD50: 373596 | AE50: 380912 | AF50: 428090 | AG50: 235566 | AH50: 124517 | AI50: 321191 | AJ50: 371183 | AK50: 402180 | AL50: 347204 | AM50: 388960 | AN50: 319359 | AO50: 312917 | AP50: 373596 | AQ50: 380912 | AR50: 17.606 | AS50: 17.51 | AT50: 17.52 | AU50: 17.49 | AV50: 17.256 | AW50: 17.478 | AX50: 17.489 | AY50: 17.489 | AZ50: 17.489 | BA50: 17.26 | BB50: 17.31 | BC50: 17.46 | BD50: 7536953 | BE50: 4124761 | BF50: 2181538 | BG50: 5617631 | BH50: 6405134 | BI50: 7029302 | BJ50: 6072251 | BK50: 6802521 | BL50: 5585270 | BM50: 5400947 | BN50: 6466947 | BO50: 6650724 | BP50: 7536953 | BQ50: 4124761 | BR50: 2181538 | BS50: 5617631 | BT50: 6405134 | BU50: 7029302 | BV50: 6072251 | BW50: 6802521 | BX50: 5585270 | BY50: 5400947 | BZ50: 6466947 | CA50: 6650724 | CB50: 709211.17 | CC50: 378829.82 | CD50: 195019.27 | CE50: 521346.01 | CF50: 601741.12 | CG50: 653083.81 | CH50: 561339.52 | CI50: 631188.19 | CJ50: 510754.06 | CK50: 491202.5 | CL50: 611329.86 | CM50: 611145.03 | CN50: 4005675 | CO50: 4005675 | CP50: 69873979 | CQ50: 69873979 | CR50: 6476190.3 | CS50: 2024 | CT50: =IFERROR(INDEX(Geography!C:C, MATCH(G50, Geography!B:B, 0)), G50) -> Illinois | CU50: =IF(O50=VLOOKUP("eia923_lignite_fuel_code", Keys!$B:$C, 2, FALSE), VLOOKUP("lignite_label", Keys!$B:$C, 2, FALSE),VLOOKUP("hard_coal_label", Keys!$B:$C, 2, FALSE)) -> hard_coal
A51: 963 | B51: N | C51: . | D51: Dallman | E51: City of Springfield - (IL) | F51: 17828 | G51: IL | H51: ENC | I51: SERC | K51: 22 | L51: 1 | M51: Electric Utility | N51: ST | O51: BIT | P51: COL | Q51: MISO | R51: M | S51: short tons | T51: 49458 | U51: 18275 | V51: 35159 | W51: 20901 | X51: 0 | Y51: 2617 | Z51: 36418 | AA51: 39839 | AB51: 39083 | AC51: 13507 | AD51: 18383 | AE51: 43208 | AF51: 49458 | AG51: 18275 | AH51: 35159 | AI51: 20901 | AJ51: 0 | AK51: 2617 | AL51: 36418 | AM51: 39839 | AN51: 39083 | AO51: 13507 | AP51: 18383 | AQ51: 43208 | AR51: 21.34 | AS51: 21.166 | AT51: 21.3 | AU51: 21.2 | AV51: 0 | AW51: 21.18 | AX51: 21.1 | AY51: 21.1 | AZ51: 21.093 | BA51: 21.09 | BB51: 21.09 | BC51: 21.09 | BD51: 1055434 | BE51: 386809 | BF51: 748887 | BG51: 443101 | BH51: 0 | BI51: 55428 | BJ51: 768420 | BK51: 840603 | BL51: 824378 | BM51: 284863 | BN51: 387697 | BO51: 911257 | BP51: 1055434 | BQ51: 386809 | BR51: 748887 | BS51: 443101 | BT51: 0 | BU51: 55428 | BV51: 768420 | BW51: 840603 | BX51: 824378 | BY51: 284863 | BZ51: 387697 | CA51: 911257 | CB51: 91975.995 | CC51: 29396.248 | CD51: 59376.344 | CE51: 34471.441 | CF51: 0 | CG51: 2744.367 | CH51: 62587.304 | CI51: 70577.243 | CJ51: 69949.102 | CK51: 21991.808 | CL51: 26902.08 | CM51: 72320.112 | CN51: 316848 | CO51: 316848 | CP51: 6706877 | CQ51: 6706877 | CR51: 542292.04 | CS51: 2024 | CT51: =IFERROR(INDEX(Geography!C:C, MATCH(G51, Geography!B:B, 0)), G51) -> Illinois | CU51: =IF(O51=VLOOKUP("eia923_lignite_fuel_code", Keys!$B:$C, 2, FALSE), VLOOKUP("lignite_label", Keys!$B:$C, 2, FALSE),VLOOKUP("hard_coal_label", Keys!$B:$C, 2, FALSE)) -> hard_coal
A52: 964 | B52: N | C52: . | D52: Lakeside | E52: City of Springfield - (IL) | F52: 17828 | G52: IL | H52: ENC | I52: SERC | K52: 22 | L52: 1 | M52: Electric Utility | N52: IC | O52: BIT | P52: COL | Q52: MISO | R52: A | S52: short tons | T52: 0 | U52: 0 | V52: 0 | W52: 0 | X52: 0 | Y52: 0 | Z52: 0 | AA52: 0 | AB52: 0 | AC52: 0 | AD52: 0 | AE52: 0 | AF52: 0 | AG52: 0 | AH52: 0 | AI52: 0 | AJ52: 0 | AK52: 0 | AL52: 0 | AM52: 0 | AN52: 0 | AO52: 0 | AP52: 0 | AQ52: 0 | AR52: 0 | AS52: 0 | AT52: 0 | AU52: 0 | AV52: 0 | AW52: 0 | AX52: 0 | AY52: 0 | AZ52: 0 | BA52: 0 | BB52: 0 | BC52: 0 | BD52: 0 | BE52: 0 | BF52: 0 | BG52: 0 | BH52: 0 | BI52: 0 | BJ52: 0 | BK52: 0 | BL52: 0 | BM52: 0 | BN52: 0 | BO52: 0 | BP52: 0 | BQ52: 0 | BR52: 0 | BS52: 0 | BT52: 0 | BU52: 0 | BV52: 0 | BW52: 0 | BX52: 0 | BY52: 0 | BZ52: 0 | CA52: 0 | CB52: 0 | CC52: 0 | CD52: 0 | CE52: 0 | CF52: 0 | CG52: 0 | CH52: 0 | CI52: 0 | CJ52: 0 | CK52: 0 | CL52: 0 | CM52: 0 | CN52: 0 | CO52: 0 | CP52: 0 | CQ52: 0 | CR52: 0 | CS52: 2024 | CT52: =IFERROR(INDEX(Geography!C:C, MATCH(G52, Geography!B:B, 0)), G52) -> Illinois | CU52: =IF(O52=VLOOKUP("eia923_lignite_fuel_code", Keys!$B:$C, 2, FALSE), VLOOKUP("lignite_label", Keys!$B:$C, 2, FALSE),VLOOKUP("hard_coal_label", Keys!$B:$C, 2, FALSE)) -> hard_coal
A53: 976 | B53: N | C53: . | D53: Marion | E53: Southern Illinois Power Coop | F53: 17632 | G53: IL | H53: ENC | I53: SERC | K53: 22 | L53: 1 | M53: Electric Utility | N53: ST | O53: BIT | P53: COL | Q53: MISO | R53: M | S53: short tons | T53: 43494 | U53: 38721 | V53: 34714 | W53: 7555 | X53: 36255 | Y53: 29868 | Z53: 43175 | AA53: 44721 | AB53: 44523 | AC53: 11736 | AD53: 34217 | AE53: 45016 | AF53: 43494 | AG53: 38721 | AH53: 34714 | AI53: 7555 | AJ53: 36255 | AK53: 29868 | AL53: 43175 | AM53: 44721 | AN53: 44523 | AO53: 11736 | AP53: 34217 | AQ53: 45016 | AR53: 24 | AS53: 25 | AT53: 25 | AU53: 27 | AV53: 26 | AW53: 26 | AX53: 24 | AY53: 24 | AZ53: 25 | BA53: 24 | BB53: 26 | BC53: 25 | BD53: 1043856 | BE53: 968025 | BF53: 867850 | BG53: 203985 | BH53: 942630 | BI53: 776568 | BJ53: 1036200 | BK53: 1073304 | BL53: 1113075 | BM53: 281664 | BN53: 889642 | BO53: 1125400 | BP53: 1043856 | BQ53: 968025 | BR53: 867850 | BS53: 203985 | BT53: 942630 | BU53: 776568 | BV53: 1036200 | BW53: 1073304 | BX53: 1113075 | BY53: 281664 | BZ53: 889642 | CA53: 1125400 | CB53: 70332.777 | CC53: 61382.664 | CD53: 56530.804 | CE53: 9791.807 | CF53: 56771.679 | CG53: 43971.889 | CH53: 62936.252 | CI53: 66876.473 | CJ53: 64618.822 | CK53: 15540.405 | CL53: 53249.112 | CM53: 70076.871 | CN53: 413995 | CO53: 413995 | CP53: 10322199 | CQ53: 10322199 | CR53: 632079.56 | CS53: 2024 | CT53: =IFERROR(INDEX(Geography!C:C, MATCH(G53, Geography!B:B, 0)), G53) -> Illinois | CU53: =IF(O53=VLOOKUP("eia923_lignite_fuel_code", Keys!$B:$C, 2, FALSE), VLOOKUP("lignite_label", Keys!$B:$C, 2, FALSE),VLOOKUP("hard_coal_label", Keys!$B:$C, 2, FALSE)) -> hard_coal
A54: 983 | B54: N | C54: . | D54: Clifty Creek | E54: Indiana-Kentucky Electric Corp | F54: 9269 | G54: IN | H54: ENC | I54: RFC | K54: 22 | L54: 1 | M54: Electric Utility | N54: ST | O54: BIT | P54: COL | Q54: PJM | R54: M | S54: short tons | T54: 258535 | U54: 201345 | V54: 171221 | W54: 133686 | X54: 127857 | Y54: 191742 | Z54: 208130 | AA54: 194778 | AB54: 121893 | AC54: 178548 | AD54: 217624 | AE54: 263705 | AF54: 258535 | AG54: 201345 | AH54: 171221 | AI54: 133686 | AJ54: 127857 | AK54: 191742 | AL54: 208130 | AM54: 194778 | AN54: 121893 | AO54: 178548 | AP54: 217624 | AQ54: 263705 | AR54: 22.621 | AS54: 22.56 | AT54: 22.421 | AU54: 22.508 | AV54: 22.521 | AW54: 22.562 | AX54: 22.567 | AY54: 22.581 | AZ54: 22.601 | BA54: 22.609 | BB54: 22.629 | BC54: 22.681 | BD54: 5848320 | BE54: 4542343 | BF54: 3838946 | BG54: 3009004 | BH54: 2879467 | BI54: 4326083 | BJ54: 4696870 | BK54: 4398282 | BL54: 2754904 | BM54: 4036792 | BN54: 4924613 | BO54: 5981093 | BP54: 5848320 | BQ54: 4542343 | BR54: 3838946 | BS54: 3009004 | BT54: 2879467 | BU54: 4326083 | BV54: 4696870 | BW54: 4398282 | BX54: 2754904 | BY54: 4036792 | BZ54: 4924613 | CA54: 5981093 | CB54: 544825.89 | CC54: 420994.22 | CD54: 356270.13 | CE54: 289140.79 | CF54: 260322.21 | CG54: 395433.99 | CH54: 429706.06 | CI54: 401894 | CJ54: 259360.5 | CK54: 374700.66 | CL54: 455320.56 | CM54: 573957.25 | CN54: 2269064 | CO54: 2269064 | CP54: 51236717 | CQ54: 51236717 | CR54: 4761926.3 | CS54: 2024 | CT54: =IFERROR(INDEX(Geography!C:C, MATCH(G54, Geography!B:B, 0)), G54) -> Indiana | CU54: =IF(O54=VLOOKUP("eia923_lignite_fuel_code", Keys!$B:$C, 2, FALSE), VLOOKUP("lignite_label", Keys!$B:$C, 2, FALSE),VLOOKUP("hard_coal_label", Keys!$B:$C, 2, FALSE)) -> hard_coal
A55: 983 | B55: N | C55: . | D55: Clifty Creek | E55: Indiana-Kentucky Electric Corp | F55: 9269 | G55: IN | H55: ENC | I55: RFC | K55: 22 | L55: 1 | M55: Electric Utility | N55: ST | O55: SUB | P55: COL | Q55: PJM | R55: M | S55: short tons | T55: 4568 | U55: 7492 | V55: 21937 | W55: 15138 | X55: 15349 | Y55: 18404 | Z55: 21512 | AA55: 20689 | AB55: 12908 | AC55: 18581 | AD55: 20564 | AE55: 15727 | AF55: 4568 | AG55: 7492 | AH55: 21937 | AI55: 15138 | AJ55: 15349 | AK55: 18404 | AL55: 21512 | AM55: 20689 | AN55: 12908 | AO55: 18581 | AP55: 20564 | AQ55: 15727 | AR55: 22.56 | AS55: 22.53 | AT55: 22.415 | AU55: 22.508 | AV55: 22.521 | AW55: 22.558 | AX55: 22.566 | AY55: 23.38 | AZ55: 22.598 | BA55: 22.607 | BB55: 22.629 | BC55: 22.68 | BD55: 103054 | BE55: 168795 | BF55: 491718 | BG55: 340726 | BH55: 345675 | BI55: 415157 | BJ55: 485440 | BK55: 483709 | BL55: 291695 | BM55: 420061 | BN55: 465343 | BO55: 356688 | BP55: 103054 | BQ55: 168795 | BR55: 491718 | BS55: 340726 | BT55: 345675 | BU55: 415157 | BV55: 485440 | BW55: 483709 | BX55: 291695 | BY55: 420061 | BZ55: 465343 | CA55: 356688 | CB55: 9600.454 | CC55: 15644.264 | CD55: 45633.458 | CE55: 32740.999 | CF55: 31251.208 | CG55: 37948.269 | CH55: 44411.797 | CI55: 44199.002 | CJ55: 27461.634 | CK55: 38990.619 | CL55: 43024.721 | CM55: 34228.504 | CN55: 192869 | CO55: 192869 | CP55: 4368061 | CQ55: 4368061 | CR55: 405134.93 | CS55: 2024 | CT55: =IFERROR(INDEX(Geography!C:C, MATCH(G55, Geography!B:B, 0)), G55) -> Indiana | CU55: =IF(O55=VLOOKUP("eia923_lignite_fuel_code", Keys!$B:$C, 2, FALSE), VLOOKUP("lignite_label", Keys!$B:$C, 2, FALSE),VLOOKUP("hard_coal_label", Keys!$B:$C, 2, FALSE)) -> hard_coal
A56: 990 | B56: N | C56: . | D56: Harding Street | E56: AES Indiana | F56: 9273 | G56: IN | H56: ENC | I56: RFC | K56: 22 | L56: 1 | M56: Electric Utility | N56: ST | O56: BIT | P56: COL | Q56: MISO | R56: M | S56: short tons | T56: 0 | U56: 0 | V56: 0 | W56: 0 | X56: 0 | Y56: 0 | Z56: 0 | AA56: 0 | AB56: 0 | AC56: 0 | AD56: 0 | AE56: 0 | AF56: 0 | AG56: 0 | AH56: 0 | AI56: 0 | AJ56: 0 | AK56: 0 | AL56: 0 | AM56: 0 | AN56: 0 | AO56: 0 | AP56: 0 | AQ56: 0 | AR56: 0 | AS56: 0 | AT56: 0 | AU56: 0 | AV56: 0 | AW56: 0 | AX56: 0 | AY56: 0 | AZ56: 0 | BA56: 0 | BB56: 0 | BC56: 0 | BD56: 0 | BE56: 0 | BF56: 0 | BG56: 0 | BH56: 0 | BI56: 0 | BJ56: 0 | BK56: 0 | BL56: 0 | BM56: 0 | BN56: 0 | BO56: 0 | BP56: 0 | BQ56: 0 | BR56: 0 | BS56: 0 | BT56: 0 | BU56: 0 | BV56: 0 | BW56: 0 | BX56: 0 | BY56: 0 | BZ56: 0 | CA56: 0 | CB56: 0 | CC56: 0 | CD56: 0 | CE56: 0 | CF56: 0 | CG56: 0 | CH56: 0 | CI56: 0 | CJ56: 0 | CK56: 0 | CL56: 0 | CM56: 0 | CN56: 0 | CO56: 0 | CP56: 0 | CQ56: 0 | CR56: 0 | CS56: 2024 | CT56: =IFERROR(INDEX(Geography!C:C, MATCH(G56, Geography!B:B, 0)), G56) -> Indiana | CU56: =IF(O56=VLOOKUP("eia923_lignite_fuel_code", Keys!$B:$C, 2, FALSE), VLOOKUP("lignite_label", Keys!$B:$C, 2, FALSE),VLOOKUP("hard_coal_label", Keys!$B:$C, 2, FALSE)) -> hard_coal
A57: 992 | B57: N | C57: . | D57: CC Perry K | E57: Citizens Thermal Energy | F57: 3599 | G57: IN | H57: ENC | I57: RFC | K57: 22 | L57: 2 | M57: NAICS-22 Non-Cogen | N57: ST | O57: BIT | P57: COL | Q57: MISO | R57: M | S57: short tons | T57: . | U57: . | V57: . | W57: . | X57: . | Y57: . | Z57: . | AA57: . | AB57: . | AC57: . | AD57: 0 | AE57: 0 | AF57: . | AG57: . | AH57: . | AI57: . | AJ57: . | AK57: . | AL57: . | AM57: . | AN57: . | AO57: . | AP57: 0 | AQ57: 0 | AR57: . | AS57: . | AT57: . | AU57: . | AV57: . | AW57: . | AX57: . | AY57: . | AZ57: . | BA57: . | BB57: 0 | BC57: 0 | BD57: . | BE57: . | BF57: . | BG57: . | BH57: . | BI57: . | BJ57: . | BK57: . | BL57: . | BM57: . | BN57: 0 | BO57: 0 | BP57: . | BQ57: . | BR57: . | BS57: . | BT57: . | BU57: . | BV57: . | BW57: . | BX57: . | BY57: . | BZ57: 0 | CA57: 0 | CB57: . | CC57: . | CD57: . | CE57: . | CF57: . | CG57: . | CH57: . | CI57: . | CJ57: . | CK57: . | CL57: 0 | CM57: 0 | CN57: 0 | CO57: 0 | CP57: 0 | CQ57: 0 | CR57: 0 | CS57: 2024 | CT57: =IFERROR(INDEX(Geography!C:C, MATCH(G57, Geography!B:B, 0)), G57) -> Indiana | CU57: =IF(O57=VLOOKUP("eia923_lignite_fuel_code", Keys!$B:$C, 2, FALSE), VLOOKUP("lignite_label", Keys!$B:$C, 2, FALSE),VLOOKUP("hard_coal_label", Keys!$B:$C, 2, FALSE)) -> hard_coal
A58: 992 | B58: Y | C58: . | D58: CC Perry K | E58: Citizens Thermal Energy | F58: 3599 | G58: IN | H58: ENC | I58: RFC | K58: 22 | L58: 3 | M58: NAICS-22 Cogen | N58: ST | O58: BIT | P58: COL | Q58: MISO | R58: M | S58: short tons | T58: 0 | U58: 0 | V58: 0 | W58: 0 | X58: 0 | Y58: 0 | Z58: 0 | AA58: 0 | AB58: 0 | AC58: 0 | AD58: . | AE58: . | AF58: 0 | AG58: 0 | AH58: 0 | AI58: 0 | AJ58: 0 | AK58: 0 | AL58: 0 | AM58: 0 | AN58: 0 | AO58: 0 | AP58: . | AQ58: . | AR58: 0 | AS58: 0 | AT58: 0 | AU58: 0 | AV58: 0 | AW58: 0 | AX58: 0 | AY58: 0 | AZ58: 0 | BA58: 0 | BB58: . | BC58: . | BD58: 0 | BE58: 0 | BF58: 0 | BG58: 0 | BH58: 0 | BI58: 0 | BJ58: 0 | BK58: 0 | BL58: 0 | BM58: 0 | BN58: . | BO58: . | BP58: 0 | BQ58: 0 | BR58: 0 | BS58: 0 | BT58: 0 | BU58: 0 | BV58: 0 | BW58: 0 | BX58: 0 | BY58: 0 | BZ58: . | CA58: . | CB58: 0 | CC58: 0 | CD58: 0 | CE58: 0 | CF58: 0 | CG58: 0 | CH58: 0 | CI58: 0 | CJ58: 0 | CK58: 0 | CL58: . | CM58: . | CN58: 0 | CO58: 0 | CP58: 0 | CQ58: 0 | CR58: 0 | CS58: 2024 | CT58: =IFERROR(INDEX(Geography!C:C, MATCH(G58, Geography!B:B, 0)), G58) -> Indiana | CU58: =IF(O58=VLOOKUP("eia923_lignite_fuel_code", Keys!$B:$C, 2, FALSE), VLOOKUP("lignite_label", Keys!$B:$C, 2, FALSE),VLOOKUP("hard_coal_label", Keys!$B:$C, 2, FALSE)) -> hard_coal
A59: 994 | B59: N | C59: . | D59: AES Petersburg | E59: AES Indiana | F59: 9273 | G59: IN | H59: ENC | I59: RFC | K59: 22 | L59: 1 | M59: Electric Utility | N59: ST | O59: BIT | P59: COL | Q59: MISO | R59: M | S59: short tons | T59: 210757 | U59: 147953 | V59: 108151 | W59: 84086 | X59: 98284 | Y59: 126833 | Z59: 98455 | AA59: 180044 | AB59: 123504 | AC59: 59604 | AD59: 117881 | AE59: 220766 | AF59: 210757 | AG59: 147953 | AH59: 108151 | AI59: 84086 | AJ59: 98284 | AK59: 126833 | AL59: 98455 | AM59: 180044 | AN59: 123504 | AO59: 59604 | AP59: 117881 | AQ59: 220766 | AR59: 22 | AS59: 22.212 | AT59: 22.59 | AU59: 22.5 | AV59: 22.3 | AW59: 22.575 | AX59: 22.841 | AY59: 22.249 | AZ59: 22.1 | BA59: 22.5 | BB59: 22 | BC59: 22.154 | BD59: 4636654 | BE59: 3286332 | BF59: 2443131 | BG59: 1891935 | BH59: 2191733 | BI59: 2863255 | BJ59: 2248811 | BK59: 4005799 | BL59: 2729438 | BM59: 1341090 | BN59: 2593382 | BO59: 4890850 | BP59: 4636654 | BQ59: 3286332 | BR59: 2443131 | BS59: 1891935 | BT59: 2191733 | BU59: 2863255 | BV59: 2248811 | BW59: 4005799 | BX59: 2729438 | BY59: 1341090 | BZ59: 2593382 | CA59: 4890850 | CB59: 421460.16 | CC59: 282585.6 | CD59: 198992.79 | CE59: 151020.23 | CF59: 190248.51 | CG59: 235035.07 | CH59: 177563.11 | CI59: 336518.23 | CJ59: 227571.85 | CK59: 106375.52 | CL59: 210372.35 | CM59: 441311.55 | CN59: 1576318 | CO59: 1576318 | CP59: 35122410 | CQ59: 35122410 | CR59: 2979055 | CS59: 2024 | CT59: =IFERROR(INDEX(Geography!C:C, MATCH(G59, Geography!B:B, 0)), G59) -> Indiana | CU59: =IF(O59=VLOOKUP("eia923_lignite_fuel_code", Keys!$B:$C, 2, FALSE), VLOOKUP("lignite_label", Keys!$B:$C, 2, FALSE),VLOOKUP("hard_coal_label", Keys!$B:$C, 2, FALSE)) -> hard_coal
A60: 997 | B60: N | C60: . | D60: Michigan City | E60: Northern Indiana Pub Serv Co | F60: 13756 | G60: IN | H60: ENC | I60: RFC | K60: 22 | L60: 1 | M60: Electric Utility | N60: ST | O60: BIT | P60: COL | Q60: MISO | R60: M | S60: short tons | T60: 16140 | U60: 17425 | V60: 9033 | W60: 0 | X60: 0 | Y60: 1500 | Z60: 13741 | AA60: 11451 | AB60: 10064 | AC60: 0 | AD60: 0 | AE60: 1764 | AF60: 16140 | AG60: 17425 | AH60: 9033 | AI60: 0 | AJ60: 0 | AK60: 1500 | AL60: 13741 | AM60: 11451 | AN60: 10064 | AO60: 0 | AP60: 0 | AQ60: 1764 | AR60: 26.24 | AS60: 26.07 | AT60: 26.32 | AU60: 0 | AV60: 0 | AW60: 26.29 | AX60: 26.29 | AY60: 26.3 | AZ60: 26.3 | BA60: 0 | BB60: 0 | BC60: 26.6 | BD60: 423514 | BE60: 454270 | BF60: 237749 | BG60: 0 | BH60: 0 | BI60: 39435 | BJ60: 361251 | BK60: 301161 | BL60: 264683 | BM60: 0 | BN60: 0 | BO60: 46922 | BP60: 423514 | BQ60: 454270 | BR60: 237749 | BS60: 0 | BT60: 0 | BU60: 39435 | BV60: 361251 | BW60: 301161 | BX60: 264683 | BY60: 0 | BZ60: 0 | CA60: 46922 | CB60: 38763.674 | CC60: 43363.172 | CD60: 21663.116 | CE60: -954.862 | CF60: 0 | CG60: 1596.237 | CH60: 33179.75 | CI60: 27164.639 | CJ60: 23332.121 | CK60: 0 | CL60: 0 | CM60: 1411.844 | CN60: 81118 | CO60: 81118 | CP60: 2128985 | CQ60: 2128985 | CR60: 189519.69 | CS60: 2024 | CT60: =IFERROR(INDEX(Geography!C:C, MATCH(G60, Geography!B:B, 0)), G60) -> Indiana | CU60: =IF(O60=VLOOKUP("eia923_lignite_fuel_code", Keys!$B:$C, 2, FALSE), VLOOKUP("lignite_label", Keys!$B:$C, 2, FALSE),VLOOKUP("hard_coal_label", Keys!$B:$C, 2, FALSE)) -> hard_coal
